Workbook

Sheet N-01 Cover
A1: Made by Jose Zapatero, jmazsantos@gmail.com
B2: N-01 — Cover and Version Control | K2: TRANSVERSAL
B3: ← Back to Index | D3: Phase: TRANSVERSAL / EXAM | Data required: None | Min. sample: n/a | Complexity: 1/5 | Typical output: Version record and block map
B5: PURPOSE
B7: This workbook is a complete Lean Six Sigma Black Belt toolkit built to do two jobs at the same time.
B8: Job A - exam preparation: it covers the Body of Knowledge to the standard required by an ASQ or IASSC Black Belt examination, with correct theory, formulas, worked derivations and self-test questions.
B10: Job B - live project tool: every tool sheet contains a working calculator that accepts real data from the PET and keg lines and returns an answer together with an explicit decision rule. Nothing is hardcoded; every result is a live Excel formula.
B12: Neither job outranks the other. A sheet that teaches but does not calculate is incomplete, and so is the reverse.
B14: IDENTIFICATION
B16: Workbook | C16: LSSBB_Toolkit_v6_4.xlsx
B17: Version | C17: v6.4 - Delivery 6 of 6 - COMPLETE (all 130 sheets built and QA passed)
B18: Owner | C18: Jose Zapatero - Packaging and Manufacturing Excellence Manager
B19: Organisation | C19: Cerveceria Cubana - Royal Swinkels Family Brewers
B20: Reference operation | C20: PET line 18,000 BPH, 24/7, shifts A/B/C/D; keg line Monobloc 80 (4-2)
B21: Total sheets | C21: 130
B22: Language | C22: English (sheet U-05 is bilingual EN-ES by design)
B23: Macros | C23: None. No VBA, no external links, no Power Query.
B25: BLOCK MAP
B27: Block | C27: Content | D27: Sheets | E27: Built in delivery
B28: N | C28: Navigation | D28: 8 | E28: 1
B29: E | C29: Statistics | D29: 60 | E29: 2, 3, 4
B30: L | C30: Lean and Improvement | D30: 26 | E30: 5
B31: H | C31: Quality and Problem Solving | D31: 16 | E31: 5
B32: G | C32: Project and Change Management | D32: 10 | E32: 6
B33: U | C33: Utilities and Exam Preparation | D33: 10 | E33: 6
B34: TOTAL | D34: 130 | E34: 1 to 6
B36: VERSION HISTORY
B38: Version | C38: Date | D38: Delivery | E38: Change | F38: Author
B39: v6.0 | C39: 2026-07-26 | D39: 1 of 6 | E39: All 130 sheets created. Navigation layer N-01 to N-08 built in full. Every tool sheet stubbed so that all index hyperlinks resolve. | F39: Jose Zapatero
B40: v6.1 | C40: 2026-07-27 | D40: 2 of 6 | E40: Statistics Levels 0-2 built in full (E-01 to E-21): data types, distributions, sampling, central limit theorem simulation, confidence intervals, hypothesis framework, sample size, statistical vs practical significance. | F40: Jose Zapatero
B41: v6.1 | C41: 2026-07-27 | D41: 3 of 6 | E41: Hypothesis testing and regression built in full (E-22 to E-40): all parametric and nonparametric tests, ANOVA, variance tests, normality testing, correlation and regression, multi-vari analysis. | F41: Jose Zapatero
B42: v6.2 | C42: 2026-07-27 | D42: 4 of 6 | E42: DOE, SPC, capability and MSA built in full (E-41 to E-60): full and fractional factorials, screening designs, centre points and response surface methods; I-MR, Xbar-R, Xbar-S, p/np, c/u, Laney p'/u', CUSUM/EWMA control charts and Nelson rules; Cp/Cpk/Pp/Ppk/Cpm capability and Z-bench; Gage R&R (ANOVA) and full MSA (bias, linearity, stability, attribute agreement). | F42: Jose Zapatero
B43: v6.3 | C43: 2026-07-27 | D43: 5 of 6 | E43: Lean and Quality tools built in full (L-01 to L-26, H-01 to H-16): wastes, VSM, takt, Little's Law, TOC, line balancing, OEE with the six big losses, 5S, standard work, SMED, TPM, poka-yoke, jidoka, kanban, heijunka, kaizen, gemba, PDCA, Pugh selection, pilot confirmation, charter, SIPOC, VOC/CTQ, Kano, check sheets, Pareto, histogram and box plot, run chart, stratification, Ishikawa, 5 Whys, C&E matrix, FMEA with AIAG-VDA Action Priority, A3, 8D and the control plan with a three-level reaction plan. | F43: Jose Zapatero
B44: v6.4 | C44: 2026-07-28 | D44: 6 of 6 | E44: Project management and utilities built in full (G-01 to G-10, U-01 to U-10): project selection, COPQ business case, stakeholder analysis, RACI, communication plan, ADKAR change management, risk register, PERT/CPM schedule with Gantt, benefit validation and closure with replication; plus statistical tables, control chart constants, Excel function guide, master formula sheet, 236-term EN-ES glossary, universal sample size calculator, example data bank and three 40-question exam banks. Final QA passed: 130 sheets, zero formula errors. | F44: Jose Zapatero
B46: Add one row per delivery. Do not overwrite history rows.

Sheet N-02 How To Use
A1: Made by Jose Zapatero, jmazsantos@gmail.com
B2: N-02 — How To Use This Workbook | K2: TRANSVERSAL
B3: ← Back to Index | D3: Phase: TRANSVERSAL / EXAM | Data required: None | Min. sample: n/a | Complexity: 1/5 | Typical output: Colour legend and sheet anatomy
B5: IF YOU ONLY READ ONE THING
B7: Do not start from the list of tools. Start from your problem.
B8: Open N-06 Index by Problem, find the archetype that matches what is happening on the line, and follow the numbered route.
B9: Every step in that route is a hyperlink to a sheet that produces one specific, named output.
B10: → Go to N-06 Index by Problem
B12: COLOUR LEGEND
B14: YELLOW = overwrite with your data | C14: GREEN = calculated automatically
B16: Colour | C16: Meaning | D16: May I type in it?
B17: Yellow fill, gold border | C17: Input cell. Pre-filled with a realistic packaging example. | D17: Yes - overwrite freely
B18: Green fill, green border | C18: Calculated cell. Contains a live Excel formula. | D18: No - it will recalculate itself
B19: Dark blue band | C19: Section header inside a sheet. | D19: No
B20: Mid blue band | C20: Table header row. | D20: No
B21: Blue underlined text | C21: Internal hyperlink to another sheet. | D21: No - click it
B23: ANATOMY OF A TOOL SHEET
B25: Every sheet in blocks E, L, H and G follows the same structure, in the same order, so that the decision rule is always in the same place.
B27: Block | C27: What it contains | D27: Why it is there
B28: Title bar (rows 1-3) | C28: Sheet ID, full title, phase chip, back link and the metadata strip. | D28: Tells you in one glance what the sheet needs and what it gives back.
B29: 1. Quick Card | C29: Three lines: what question it answers, when you would reach for it, what it gives you. | D29: The block you read when scanning for the right tool.
B30: 2. Concept | C30: Four to eight lines of plain English before any symbol appears. | D30: Understanding the logic prevents the classic misuse of the tool.
B31: 3. When to use / not use / assumptions | C31: Two short lists, then an assumption table: assumption, how to check it, what to do if it fails. | D31: Most wrong conclusions come from a violated assumption, not from arithmetic.
B32: 4. Formula and derivation | C32: The formula in readable notation, every symbol defined, degrees of freedom stated. | D32: This block serves the examination.
B33: 5. Excel implementation | C33: The exact functions used on the sheet and what each argument means. | D33: So you can rebuild the calculation in your own file.
B34: 6. Worked example (interactive) | C34: A realistic PET or keg scenario, yellow inputs, green live formulas. | D34: This block serves the factory floor.
B35: 7. Decision rule and interpretation | C35: A verdict cell driven by a formula, a numeric criteria table, and common mistakes. | D35: A number without a decision rule changes nothing.
B36: 8. Self-check | C36: Three exam-style questions, answers hidden in white font in column N. | D36: Select the cell in column N to reveal the answer.
B37: 9. Related sheets | C37: Previous tool, next tool, and the alternative if assumptions fail. | D37: Keeps you moving along a route instead of hunting.
B39: FOUR WAYS TO NAVIGATE
B41: Start from | C41: Use this sheet | D41: Best when
B42: A DMAIC phase | C42: N-03 Index DMAIC | D42: You are running a project and need the phase toolset.
B43: A question in plain language | C43: N-04 Index by Question | D43: You know what you want to know but not what it is called.
B44: Your data types | C44: N-05 Test Selector | D44: You need the correct statistical test and its alternative.
B45: A problem on the line | C45: N-06 Index by Problem | D45: Something is wrong today and you need a route, not a catalogue.
B47: Two further routes: N-07 Tollgates tells you whether you may close a phase, and N-08 Fast Track Routes tells you whether a full DMAIC is the right vehicle at all.
B50: TECHNICAL NOTES
B52: • All calculations are live Excel formulas. There are no macros and no VBA, so the file opens and recalculates on any machine, including a locked-down plant PC.
B53: • There are no external links and no Power Query connections. The workbook is self-contained.
B54: • No sheet is protected. Everything is editable - which also means every formula is deletable. Keep a clean master copy and work on duplicates for live projects.
B55: • Legacy statistical function names are used throughout (TTEST, CHITEST, NORMSDIST) because they are supported by every spreadsheet engine, including LibreOffice and older Excel builds.
B56: • Cell A1 of every sheet carries the author attribution in white font.

Sheet N-03 Index DMAIC
A1: Made by Jose Zapatero, jmazsantos@gmail.com
B2: N-03 — Master Index by DMAIC Phase | K2: TRANSVERSAL
B3: ← Back to Index | D3: Phase: TRANSVERSAL / EXAM | Data required: None | Min. sample: n/a | Complexity: 1/5 | Typical output: Filterable master list of 130 sheets
B5: ID | C5: Tool | D5: Block | E5: Phase | F5: What question it answers | G5: Data required | H5: Min. sample | I5: Complexity 1-5 | J5: Output produced | K5: Go
B6: DEFINE (9 sheets)
B7: H-01 | C7: Project Charter | D7: H | E7: D | F7: What exactly am I solving, why and by when? | G7: Problem, goal, scope, benefit | H7: n/a | I7: 2 | J7: Signed one-page charter | K7: Go →
B8: H-02 | C8: SIPOC | D8: H | E8: D | F8: What are the boundaries of my process? | G8: Process walk | H8: n/a | I8: 1 | J8: High-level SIPOC map | K8: Go →
B9: H-03 | C9: Voice of the Customer and CTQ Tree | D9: H | E9: D | F9: What does the customer need, in measurable terms? | G9: Customer statements | H9: n/a | I9: 2 | J9: CTQ tree with measurable specs | K9: Go →
B10: H-04 | C10: Kano Model | D10: H | E10: D | F10: Which features delight and which are expected? | G10: Customer survey | H10: n/a | I10: 2 | J10: Kano classification of attributes | K10: Go →
B11: G-01 | C11: Project Selection and Portfolio Prioritisation | D11: G | E11: D | F11: Which project should we do first? | G11: Candidate projects and criteria | H11: n/a | I11: 2 | J11: Scored and ranked project portfolio | K11: Go →
B12: G-02 | C12: Business Case and Cost of Poor Quality | D12: G | E12: D | F12: What is this problem costing us? | G12: Loss volumes and unit costs | H12: n/a | I12: 3 | J12: COPQ by category and business case | K12: Go →
B13: G-03 | C13: Stakeholder Analysis | D13: G | E13: D | F13: Who can block or accelerate this project? | G13: Stakeholder list | H13: n/a | I13: 2 | J13: Power-interest grid and engagement plan | K13: Go →
B14: G-04 | C14: RACI Matrix | D14: G | E14: D | F14: Who is responsible for each deliverable? | G14: Deliverables and roles | H14: n/a | I14: 1 | J14: Validated RACI with conflict check | K14: Go →
B15: G-05 | C15: Communication Plan | D15: G | E15: D | F15: Who hears what, how often, from whom? | G15: Audiences and messages | H15: n/a | I15: 1 | J15: Communication calendar | K15: Go →
B16: MEASURE (31 sheets)
B17: E-01 | C17: Data Types and Measurement Scales | D17: E | E17: M | F17: What kind of data am I holding and what may I do with it? | G17: Any variable list | H17: n/a | I17: 1 | J17: Data classification and permitted statistics | K17: Go →
B18: E-02 | C18: Population, Sample and Sampling Error | D18: E | E18: M | F18: How far can my sample be from the truth? | G18: Sample values | H18: 5 | I18: 1 | J18: Sampling error estimate | K18: Go →
B19: E-03 | C19: Descriptive Statistics: Centre and Spread | D19: E | E19: M | F19: Where is my process centred and how wide is it? | G19: Continuous measurements | H19: 10 | I19: 1 | J19: Mean, median, StDev, range, quartiles, histogram | K19: Go →
B20: E-04 | C20: Distribution Shape: Skewness and Kurtosis | D20: E | E20: M | F20: Is my distribution symmetric and how heavy are the tails? | G20: Continuous measurements | H20: 25 | I20: 2 | J20: Skewness and kurtosis with interpretation | K20: Go →
B21: E-05 | C21: Sampling Strategies and Rational Subgrouping | D21: E | E21: M | F21: How and when should I take my samples? | G21: Process timeline and sources | H21: n/a | I21: 3 | J21: Sampling plan and subgroup definition | K21: Go →
B22: E-06 | C22: Operational Definitions and Data Collection Plan | D22: E | E22: M | F22: Will two people record the same thing the same way? | G22: Process and metric list | H22: n/a | I22: 2 | J22: Operational definitions and collection plan | K22: Go →
B23: E-07 | C23: The Normal Distribution and Z Scores | D23: E | E23: M | F23: What proportion of output falls beyond this limit? | G23: Mean, StDev, limit | H23: n/a | I23: 2 | J23: Z score, tail probability, PPM | K23: Go →
B24: E-08 | C24: Central Limit Theorem (Live Simulation) | D24: E | E24: M | F24: Why can I use normal theory on non-normal data? | G24: None (simulated) | H24: n/a | I24: 3 | J24: Raw vs sample-mean histograms | K24: Go →
B25: E-09 | C25: The t, Chi-Square and F Distributions | D25: E | E25: M | F25: Which reference distribution does my test use? | G25: Degrees of freedom, alpha | H25: n/a | I25: 3 | J25: Critical values and tail areas | K25: Go →
B26: E-10 | C26: Binomial Distribution (Defective Units) | D26: E | E26: M | F26: What is the chance of x defective bottles in n? | G26: n, p, x | H26: n/a | I26: 2 | J26: Binomial probabilities and cumulative curve | K26: Go →
B27: E-11 | C27: Poisson Distribution (Defects per Unit) | D27: E | E27: M | F27: What is the chance of x micro-stops in a shift? | G27: Mean rate, exposure | H27: n/a | I27: 2 | J27: Poisson probabilities and rate comparison | K27: Go →
B28: E-12 | C28: Weibull, Exponential and Lognormal | D28: E | E28: M | F28: How do I model time to failure or skewed data? | G28: Times to event | H28: 15 | I28: 4 | J28: Fitted shape and scale, reliability estimate | K28: Go →
B29: E-13 | C29: Identifying the Distribution of Your Data | D29: E | E29: M | F29: Which distribution actually fits my data? | G29: Continuous measurements | H29: 25 | I29: 4 | J29: Ranked candidate distributions | K29: Go →
B30: E-14 | C30: Standard Error vs Standard Deviation | D30: E | E30: M | F30: How precise is my estimate of the mean? | G30: StDev and n | H30: 5 | I30: 2 | J30: Standard error and precision statement | K30: Go →
B31: E-15 | C31: Confidence Intervals for the Mean | D31: E | E31: M | F31: Within what range does the true mean sit? | G31: Sample mean, StDev, n | H31: 5 | I31: 2 | J31: Confidence interval for the mean | K31: Go →
B32: E-16 | C32: Confidence Intervals for Proportion and Std Dev | D32: E | E32: M | F32: Within what range sits my true defect rate or spread? | G32: x, n or StDev, n | H32: 20 | I32: 3 | J32: Confidence intervals for p and sigma | K32: Go →
B33: E-20 | C33: Sample Size Determination | D33: E | E33: M | F33: How many samples do I actually need? | G33: Alpha, power, delta, sigma | H33: n/a | I33: 3 | J33: Required n for four scenarios | K33: Go →
B34: E-57 | C34: Cp, Cpk, Pp, Ppk and Cpm | D34: E | E34: M | F34: Can my process meet the specification? | G34: Measurements plus spec limits | H34: 30 | I34: 3 | J34: Capability indices, PPM, capability histogram | K34: Go →
B35: E-58 | C35: Non-Normal and Attribute Capability, Z-bench | D35: E | E35: M | F35: How do I state capability when data is not normal? | G35: Non-normal or attribute data | H35: 30 | I35: 4 | J35: Z-bench, sigma level, PPM | K35: Go →
B36: E-59 | C36: Gage R&R: ANOVA and Range Methods | D36: E | E36: M | F36: Can I trust my measurement system? | G36: 10 parts x 3 operators x 2 trials | H36: 60 | I36: 5 | J36: %GRR, ndc and AIAG verdict | K36: Go →
B37: E-60 | C37: MSA: Bias, Linearity, Stability, Attribute Agreement | D37: E | E37: M | F37: Is my gauge biased, drifting or disagreeing? | G37: Reference standards, repeat readings | H37: 30 | I37: 4 | J37: Bias, linearity, stability, Cohen's Kappa | K37: Go →
B38: L-02 | C38: Value Stream Map - Current State | D38: L | E38: M | F38: What does the whole flow look like today? | G38: Cycle times, inventories, uptime | H38: n/a | I38: 4 | J38: Current state map and lead time ladder | K38: Go →
B39: L-04 | C39: Process Mapping and Swimlane Flowcharts | D39: L | E39: M | F39: What are the real steps and handoffs? | G39: Process walk notes | H39: n/a | I39: 2 | J39: Swimlane map with decision points | K39: Go →
B40: L-05 | C40: Spaghetti Diagram | D40: L | E40: M | F40: How far do people and materials actually travel? | G40: Layout and movement log | H40: n/a | I40: 2 | J40: Distance total and travel map | K40: Go →
B41: L-07 | C41: Takt Time, Cycle Time and Lead Time | D41: L | E41: M | F41: Is my line fast enough for demand? | G41: Demand, available time, cycle times | H41: n/a | I41: 2 | J41: Takt vs cycle comparison | K41: Go →
B42: L-11 | C42: Overall Equipment Effectiveness | D42: L | E42: M | F42: Where is my equipment time really going? | G42: Downtime, speed, quality log | H42: n/a | I42: 3 | J42: OEE with six big losses breakdown | K42: Go →
B43: L-22 | C43: Gemba Walk | D43: L | E43: M | F43: What is really happening where the work is done? | G43: Walk route and questions | H43: n/a | I43: 1 | J43: Structured observation record | K43: Go →
B44: H-05 | C44: Check Sheets and Data Collection Forms | D44: H | E44: M | F44: How do operators record data reliably? | G44: Defect categories | H44: n/a | I44: 1 | J44: Ready-to-print check sheet | K44: Go →
B45: H-06 | C45: Pareto Analysis | D45: H | E45: M | F45: Which few causes drive most of the loss? | G45: Counts or cost by category | H45: n/a | I45: 1 | J45: Pareto chart with cumulative line | K45: Go →
B46: H-07 | C46: Histogram and Box Plot | D46: H | E46: M | F46: What is the shape and spread of my data? | G46: Continuous measurements | H46: 25 | I46: 2 | J46: Histogram and box plot by group | K46: Go →
B47: H-08 | C47: Run Chart and Trend Analysis | D47: H | E47: M | F47: Is there a trend or shift over time? | G47: Time-ordered data | H47: 20 | I47: 2 | J47: Run chart with runs rules | K47: Go →
B48: ANALYZE (32 sheets)
B49: E-17 | C49: The Hypothesis Testing Framework | D49: E | E49: A | F49: How do I turn a question into a testable hypothesis? | G49: Claim to be tested | H49: n/a | I49: 2 | J49: H0, H1, alpha and decision rule | K49: Go →
B50: E-18 | C50: Understanding the p-Value (and What It Is Not) | D50: E | E50: A | F50: What does this p-value really tell me? | G50: Test statistic and df | H50: n/a | I50: 2 | J50: Correct interpretation and common errors | K50: Go →
B51: E-19 | C51: Type I Error, Type II Error and Power | D51: E | E51: A | F51: What is the risk of missing a real difference? | G51: Alpha, effect size, n, sigma | H51: n/a | I51: 3 | J51: Power curve and beta risk | K51: Go →
B52: E-21 | C52: Statistical vs Practical Significance | D52: E | E52: A | F52: Is this difference worth acting on? | G52: Test result and cost data | H52: n/a | I52: 2 | J52: Effect size and business relevance verdict | K52: Go →
B53: E-22 | C53: Hypothesis Test Selection Roadmap | D53: E | E53: A | F53: Which test do I run, step by step? | G53: Data types and design | H53: n/a | I53: 2 | J53: Routed test recommendation | K53: Go →
B54: E-23 | C54: One-Sample t-Test | D54: E | E54: A | F54: Is my process mean different from target? | G54: Continuous sample and target | H54: 10 | I54: 2 | J54: t, p-value, CI and verdict | K54: Go →
B55: E-24 | C55: Two-Sample t-Test (Welch and Pooled) | D55: E | E55: A | F55: Do these two shifts or machines differ in mean? | G55: Two independent samples | H55: 10 | I55: 3 | J55: Welch and pooled t, p-value, CI | K55: Go →
B56: E-25 | C56: Paired t-Test | D56: E | E56: A | F56: Did the change move the same units? | G56: Before/after pairs | H56: 10 | I56: 2 | J56: Mean difference, t, p-value, CI | K56: Go →
B57: E-26 | C57: One-Way ANOVA with Tukey HSD | D57: E | E57: A | F57: Do three or more groups differ in mean? | G57: Continuous Y, one categorical X | H57: 15 | I57: 4 | J57: ANOVA table, eta-squared, Tukey pairs | K57: Go →
B58: E-27 | C58: Two-Way ANOVA and Interactions | D58: E | E58: A | F58: Do two factors interact? | G58: Continuous Y, two categorical X | H58: 24 | I58: 5 | J58: Two-way ANOVA table and interaction plot | K58: Go →
B59: E-28 | C59: Tests for Variance: F, Levene, Bartlett | D59: E | E59: A | F59: Is one group more variable than another? | G59: Two or more samples | H59: 10 | I59: 3 | J59: F, Levene, Bartlett statistics and verdict | K59: Go →
B60: E-29 | C60: One and Two Proportion Tests | D60: E | E60: A | F60: Has my defect rate really changed? | G60: x and n per group | H60: 30 | I60: 3 | J60: Z statistic, p-value, CI on difference | K60: Go →
B61: E-30 | C61: Chi-Square Tests and Fisher Exact | D61: E | E61: A | F61: Are these two categorical variables related? | G61: Contingency table | H61: 20 | I61: 3 | J61: Chi-square, p-value, expected counts | K61: Go →
B62: E-31 | C62: Nonparametric Tests | D62: E | E62: A | F62: What do I run when normality fails? | G62: Ordinal or non-normal data | H62: 10 | I62: 4 | J62: Mann-Whitney, Kruskal-Wallis, sign test | K62: Go →
B63: E-32 | C63: Normality Testing and Probability Plots | D63: E | E63: A | F63: Can I assume normality? | G63: Continuous measurements | H63: 20 | I63: 3 | J63: Anderson-Darling style verdict and probability plot | K63: Go →
B64: E-33 | C64: When Assumptions Fail: Transformations and Alternatives | D64: E | E64: A | F64: My assumptions failed - now what? | G64: The failing dataset | H64: 20 | I64: 4 | J64: Box-Cox lambda and alternative test route | K64: Go →
B65: E-34 | C65: Scatter Plots and Correlation | D65: E | E65: A | F65: Do these two variables move together? | G65: Paired continuous data | H65: 25 | I65: 2 | J65: Pearson r, Spearman rho, p-value, scatter | K65: Go →
B66: E-35 | C66: Correlation, Causation and Confounding | D66: E | E66: A | F66: Does X cause Y or is something else driving both? | G66: Correlation result and context | H66: n/a | I66: 2 | J66: Causality checklist and confounder list | K66: Go →
B67: E-36 | C67: Simple Linear Regression | D67: E | E67: A | F67: How much does Y change when X changes? | G67: Paired continuous data | H67: 25 | I67: 3 | J67: Slope, intercept, R-squared, prediction | K67: Go →
B68: E-37 | C68: Residual Analysis and Model Diagnostics | D68: E | E68: A | F68: Is my model trustworthy? | G68: Fitted model residuals | H68: 25 | I68: 4 | J68: Four residual plots and diagnosis | K68: Go →
B69: E-38 | C69: Multiple Regression and Multicollinearity | D69: E | E69: A | F69: Which of several inputs really drive Y? | G69: Y plus several continuous X | H69: 40 | I69: 5 | J69: Coefficients, adjusted R-squared, VIF | K69: Go →
B70: E-39 | C70: Binary Logistic Regression | D70: E | E70: A | F70: What drives pass/fail outcomes? | G70: Binary Y plus continuous X | H70: 50 | I70: 5 | J70: Odds ratios and fitted probabilities | K70: Go →
B71: E-40 | C71: Multi-Vari Analysis | D71: E | E71: A | F71: Where does my variation live: within, between or over time? | G71: Nested sampling data | H71: 30 | I71: 4 | J71: Multi-vari chart and dominant family | K71: Go →
B72: L-01 | C72: The Eight Wastes (DOWNTIME) | D72: L | E72: A | F72: Where is the waste in this process? | G72: Process observation | H72: n/a | I72: 1 | J72: Waste inventory by category | K72: Go →
B73: L-06 | C73: Value-Added / Non-Value-Added Analysis | D73: L | E73: A | F73: How much of my lead time adds value? | G73: Step times and classification | H73: n/a | I73: 2 | J73: VA ratio and NVA target list | K73: Go →
B74: L-08 | C74: Little's Law and Work in Process | D74: L | E74: A | F74: How much WIP explains my lead time? | G74: WIP and throughput | H74: n/a | I74: 2 | J74: Lead time from WIP and exit rate | K74: Go →
B75: L-09 | C75: Theory of Constraints and Bottleneck Analysis | D75: L | E75: A | F75: Which machine truly limits my output? | G75: Capacity by station | H75: n/a | I75: 3 | J75: Identified constraint and exploitation plan | K75: Go →
B76: H-09 | C76: Stratification | D76: H | E76: A | F76: Does the problem hide inside a subgroup? | G76: Data with stratifying factors | H76: 30 | I76: 2 | J76: Stratified comparison table | K76: Go →
B77: H-10 | C77: Ishikawa / Fishbone Diagram | D77: H | E77: A | F77: What are all the candidate causes? | G77: Team knowledge | H77: n/a | I77: 1 | J77: 6M cause tree | K77: Go →
B78: H-11 | C78: 5 Whys | D78: H | E78: A | F78: What is the true root cause? | G78: Verified failure chain | H78: n/a | I78: 1 | J78: Causal chain to root cause | K78: Go →
B79: H-12 | C79: Cause and Effect (X-Y) Matrix | D79: H | E79: A | F79: Which process inputs matter most to my outputs? | G79: Inputs, outputs, weights | H79: n/a | I79: 2 | J79: Ranked inputs by weighted score | K79: Go →
B80: H-13 | C80: FMEA (AIAG-VDA 2019, Action Priority) | D80: H | E80: A | F80: Which failure modes must I act on first? | G80: Failure modes with S, O, D | H80: n/a | I80: 4 | J80: Action Priority High/Medium/Low | K80: Go →
B81: IMPROVE (20 sheets)
B82: E-41 | C82: DOE Fundamentals and Terminology | D82: E | E82: I | F82: What is a designed experiment and why beat one-factor-at-a-time? | G82: Factor list | H82: n/a | I82: 3 | J82: Design vocabulary and planning sheet | K82: Go →
B83: E-42 | C83: Full Factorial Designs (2^k) | D83: E | E83: I | F83: Which factors and interactions move my response? | G83: Runs of a 2^k design | H83: 8 | I83: 4 | J83: Effects, main effects and interaction plots | K83: Go →
B84: E-43 | C84: Fractional Factorial, Resolution and Aliasing | D84: E | E84: I | F84: How do I test many factors in few runs? | G84: Runs of a fractional design | H84: 8 | I84: 5 | J84: Generator, alias structure, resolution | K84: Go →
B85: E-44 | C85: Screening Designs (Plackett-Burman) | D85: E | E85: I | F85: Which of many candidate factors matter at all? | G85: Screening runs | H85: 12 | I85: 4 | J85: Ranked factor effects | K85: Go →
B86: E-45 | C86: Centre Points and Curvature Detection | D86: E | E86: I | F86: Is my response surface curved? | G86: Factorial plus centre points | H86: 11 | I86: 4 | J86: Curvature test and verdict | K86: Go →
B87: E-46 | C87: Response Surface Methods and Optimisation | D87: E | E87: I | F87: What settings optimise my response? | G87: RSM design runs | H87: 13 | I87: 5 | J87: Fitted surface and optimum settings | K87: Go →
B88: L-03 | C88: Value Stream Map - Future State | D88: L | E88: I | F88: What should the flow look like? | G88: Current state map plus takt | H88: n/a | I88: 4 | J88: Future state map and kaizen bursts | K88: Go →
B89: L-10 | C89: Line Balancing and Yamazumi | D89: L | E89: I | F89: How do I level the work across stations? | G89: Task times and precedence | H89: n/a | I89: 3 | J89: Balanced allocation and efficiency | K89: Go →
B90: L-12 | C90: 5S and Workplace Organisation | D90: L | E90: I | F90: Is the workplace organised and sustainable? | G90: Area audit | H90: n/a | I90: 1 | J90: 5S audit score and action list | K90: Go →
B91: L-15 | C91: SMED and Quick Changeover | D91: L | E91: I | F91: How do I cut changeover time? | G91: Timed changeover elements | H91: n/a | I91: 3 | J91: Internal/external split and time reduction | K91: Go →
B92: L-16 | C92: TPM and Autonomous Maintenance | D92: L | E92: I | F92: How do I stop the same breakdowns recurring? | G92: Failure history and CLARI tasks | H92: n/a | I92: 3 | J92: AM step plan and pillar scorecard | K92: Go →
B93: L-17 | C93: Poka-Yoke (Mistake Proofing) | D93: L | E93: I | F93: How do I make the error impossible? | G93: Error modes list | H93: n/a | I93: 2 | J93: Mistake-proofing device concepts | K93: Go →
B94: L-19 | C94: Pull Systems and Kanban | D94: L | E94: I | F94: How much inventory should sit between steps? | G94: Demand, lead time, variability | H94: n/a | I94: 3 | J94: Kanban card quantity | K94: Go →
B95: L-20 | C95: Heijunka (Level Loading) | D95: L | E95: I | F95: How do I smooth an uneven schedule? | G95: Product mix and volumes | H95: n/a | I95: 3 | J95: Levelled production pattern (EPEI) | K95: Go →
B96: L-21 | C96: Kaizen Event Planning and Execution | D96: L | E96: I | F96: How do I run a one-week improvement event? | G96: Scope and team | H96: n/a | I96: 2 | J96: Event charter and daily agenda | K96: Go →
B97: L-23 | C97: PDCA / PDSA Cycle | D97: L | E97: I | F97: How do I test a change safely? | G97: Change idea and metric | H97: n/a | I97: 1 | J97: PDCA cycle record | K97: Go →
B98: L-24 | C98: Idea Generation: Brainwriting, SCAMPER | D98: L | E98: I | F98: How do I generate solutions beyond the obvious? | G98: Problem statement | H98: n/a | I98: 1 | J98: Structured idea list | K98: Go →
B99: L-25 | C99: Pugh Matrix, Impact-Effort, Weighted Criteria | D99: L | E99: I | F99: Which solution should I pick? | G99: Solution options and criteria | H99: n/a | I99: 2 | J99: Ranked solutions with scores | K99: Go →
B100: L-26 | C100: Pilot Design and Confirmation Run | D100: L | E100: I | F100: Did the improvement actually work? | G100: Before/after data | H100: 20 | I100: 3 | J100: Confirmation test and hold decision | K100: Go →
B101: G-06 | C101: Change Management and Resistance (ADKAR) | D101: G | E101: I | F101: Why is the team resisting and what closes the gap? | G101: ADKAR assessment | H101: n/a | I101: 3 | J101: ADKAR gap score and intervention plan | K101: Go →
...

Sheet N-04 Index by Question
A1: Made by Jose Zapatero, jmazsantos@gmail.com
B2: N-04 — Index by Type of Question | K2: TRANSVERSAL
B3: ← Back to Index | D3: Phase: TRANSVERSAL / EXAM | Data required: None | Min. sample: n/a | Complexity: 1/5 | Typical output: Tools grouped under nine questions
B5: You rarely know the name of the tool you need. You do know the question. Find your question below and work down the list.
B7: 1. What is my process actually doing?
B8: ID | C8: Tool | D8: Why this tool answers the question | E8: Phase
B9: H-02 | C9: SIPOC | D9: Fixes the boundaries before anyone argues about scope | E9: D
B10: L-04 | C10: Process Mapping and Swimlane Flowcharts | D10: Shows the real steps, handoffs and rework loops | E10: M
B11: L-22 | C11: Gemba Walk | D11: Confirms on the floor what the map claims | E11: M
B12: E-03 | C12: Descriptive Statistics: Centre and Spread | D12: Quantifies centre and spread of the key output | E12: M
B13: H-07 | C13: Histogram and Box Plot | D13: Shows the shape of the distribution | E13: M
B14: H-08 | C14: Run Chart and Trend Analysis | D14: Shows behaviour over time before any limits are drawn | E14: M
B15: L-11 | C15: Overall Equipment Effectiveness | D15: Converts calendar time into OEE and the six big losses | E15: M
B17: 2. Can I trust my data?
B18: ID | C18: Tool | D18: Why this tool answers the question | E18: Phase
B19: E-06 | C19: Operational Definitions and Data Collection Plan | D19: Operational definitions: two people, same reading | E19: M
B20: E-01 | C20: Data Types and Measurement Scales | D20: Confirms which statistics the data type permits | E20: M
B21: E-05 | C21: Sampling Strategies and Rational Subgrouping | D21: Rational subgrouping: sample so that the chart can work | E21: M
B22: E-59 | C22: Gage R&R: ANOVA and Range Methods | D22: Gage R&R: how much of the observed variation is the gauge | E22: M
B23: E-60 | C23: MSA: Bias, Linearity, Stability, Attribute Agreement | D23: Bias, linearity, stability and attribute agreement | E23: M
B24: E-20 | C24: Sample Size Determination | D24: Confirms the sample is large enough to conclude anything | E24: M
B26: 3. Is my process stable?
B27: ID | C27: Tool | D27: Why this tool answers the question | E27: Phase
B28: E-47 | C28: Common Cause vs Special Cause Variation | D28: Common cause vs special cause before you react | E28: C
B29: E-48 | C29: Control Chart Selection Tree | D29: Selects the correct chart for your data type | E29: C
B30: E-49 | C30: Individuals and Moving Range Chart | D30: I-MR for individual measurements | E30: C
B31: E-50 | C31: Xbar-R Chart | D31: Xbar-R for small subgroups | E31: C
B32: E-51 | C32: Xbar-S Chart | D32: Xbar-S for subgroups of nine or more | E32: C
B33: E-52 | C33: p and np Charts | D33: p and np for defective units | E33: C
B34: E-53 | C34: c and u Charts | D34: c and u for defects per unit | E34: C
B35: E-54 | C35: Laney p' and u' Charts (Overdispersion) | D35: Laney p' and u' when subgroups are very large | E35: C
B36: E-55 | C36: CUSUM and EWMA Charts | D36: CUSUM and EWMA for small sustained shifts | E36: C
B37: E-56 | C37: Western Electric and Nelson Rules | D37: Western Electric and Nelson pattern rules | E37: C
B39: 4. Is my process capable?
B40: ID | C40: Tool | D40: Why this tool answers the question | E40: Phase
B41: E-57 | C41: Cp, Cpk, Pp, Ppk and Cpm | D41: Cp, Cpk, Pp, Ppk, Cpm and PPM against specification | E41: M
B42: E-58 | C42: Non-Normal and Attribute Capability, Z-bench | D42: Capability when the data is not normal or is attribute | E42: M
B43: E-07 | C43: The Normal Distribution and Z Scores | D43: Z scores and tail probabilities behind the indices | E43: M
B44: E-21 | C44: Statistical vs Practical Significance | D44: Whether the gap matters commercially, not just statistically | E44: A
B46: 5. Are these groups different?
B47: ID | C47: Tool | D47: Why this tool answers the question | E47: Phase
B48: N-05 | C48: Statistical Test Selector (Y vs X Matrix) | D48: Start here: the Y vs X selector grid | E48: X
B49: E-23 | C49: One-Sample t-Test | D49: One sample against a target | E49: A
B50: E-24 | C50: Two-Sample t-Test (Welch and Pooled) | D50: Two independent groups | E50: A
B51: E-25 | C51: Paired t-Test | D51: Paired before/after on the same units | E51: A
B52: E-26 | C52: One-Way ANOVA with Tukey HSD | D52: Three or more groups, plus Tukey pairwise | E52: A
B53: E-28 | C53: Tests for Variance: F, Levene, Bartlett | D53: Difference in variability rather than in mean | E53: A
B54: E-29 | C54: One and Two Proportion Tests | D54: Difference in proportion defective | E54: A
B55: E-30 | C55: Chi-Square Tests and Fisher Exact | D55: Association between two categorical variables | E55: A
B56: E-31 | C56: Nonparametric Tests | D56: Nonparametric alternatives when normality fails | E56: A
B58: 6. Are these variables related?
B59: ID | C59: Tool | D59: Why this tool answers the question | E59: Phase
B60: E-34 | C60: Scatter Plots and Correlation | D60: Scatter plot and correlation coefficient | E60: A
B61: E-35 | C61: Correlation, Causation and Confounding | D61: Whether the relationship can be called causal | E61: A
B62: E-36 | C62: Simple Linear Regression | D62: Simple linear regression and prediction | E62: A
B63: E-37 | C63: Residual Analysis and Model Diagnostics | D63: Residual diagnostics before you trust the model | E63: A
B64: E-38 | C64: Multiple Regression and Multicollinearity | D64: Several predictors at once, with VIF | E64: A
B65: E-39 | C65: Binary Logistic Regression | D65: Binary outcomes such as pass/fail | E65: A
B67: 7. Which inputs matter most?
B68: ID | C68: Tool | D68: Why this tool answers the question | E68: Phase
B69: H-12 | C69: Cause and Effect (X-Y) Matrix | D69: Cause and effect matrix: cheap first pass | E69: A
B70: E-40 | C70: Multi-Vari Analysis | D70: Multi-vari: which family of variation dominates | E70: A
B71: E-41 | C71: DOE Fundamentals and Terminology | D71: DOE fundamentals and planning | E71: I
B72: E-44 | C72: Screening Designs (Plackett-Burman) | D72: Screening many candidate factors | E72: I
B73: E-42 | C73: Full Factorial Designs (2^k) | D73: Full factorial with interactions | E73: I
B74: E-43 | C74: Fractional Factorial, Resolution and Aliasing | D74: Fractional factorial, aliasing and resolution | E74: I
B75: E-46 | C75: Response Surface Methods and Optimisation | D75: Response surface optimisation | E75: I
B77: 8. What is the root cause?
B78: ID | C78: Tool | D78: Why this tool answers the question | E78: Phase
B79: H-10 | C79: Ishikawa / Fishbone Diagram | D79: Fishbone: generate the candidate causes | E79: A
B80: H-11 | C80: 5 Whys | D80: 5 Whys: drive the chain to something actionable | E80: A
B81: H-09 | C81: Stratification | D81: Stratification: split the data until the cause shows | E81: A
B82: H-06 | C82: Pareto Analysis | D82: Pareto: attack the vital few | E82: M
B83: H-13 | C83: FMEA (AIAG-VDA 2019, Action Priority) | D83: FMEA: rank failure modes by Action Priority | E83: A
B84: H-15 | C84: 8D Problem Solving | D84: 8D: formal route for a customer or safety event | E84: X
B85: H-14 | C85: A3 Problem Solving | D85: A3: one page from problem to countermeasure | E85: X
B87: 9. How do I hold the gain?
B88: ID | C88: Tool | D88: Why this tool answers the question | E88: Phase
B89: H-16 | C89: Control Plan and Reaction Plan (OCAP) | D89: Control plan and three-level reaction plan | E89: C
B90: L-14 | C90: Standard Work and Combination Sheet | D90: Standard work so the new way is the only way | E90: C
B91: L-13 | C91: Visual Management | D91: Visual management: status visible in 30 seconds | E91: C
B92: L-17 | C92: Poka-Yoke (Mistake Proofing) | D92: Poka-yoke: make the error physically impossible | E92: I
B93: L-18 | C93: Jidoka and Andon | D93: Jidoka and Andon: stop and escalate on defect | E93: C
B94: E-56 | C94: Western Electric and Nelson Rules | D94: Rules that tell the operator when to react | E94: C
B95: G-09 | C95: Financial Benefit Validation (Hard vs Soft) | D95: Financial validation of the benefit | E95: C
B96: G-10 | C96: Closure, Handover, Lessons Learned, Replication | D96: Handover, lessons learned and replication | E96: C

Sheet N-05 Test Selector
A1: Made by Jose Zapatero, jmazsantos@gmail.com
B2: N-05 — Statistical Test Selector (Y vs X Matrix) | K2: TRANSVERSAL
B3: ← Back to Index | D3: Phase: TRANSVERSAL / EXAM | Data required: Type of Y and type of X | Min. sample: n/a | Complexity: 2/5 | Typical output: Named test plus nonparametric alternative
B5: THE Y VERSUS X GRID
B7: Rows: the type of your Y (the output you measure). Columns: the type of your X (what you think changes it).
B8: Upper line in each cell = the standard test. Lower line = the alternative when its assumptions fail. Both are hyperlinks.
B10: Y \ X | C10: X = none (compare with a target) | D10: X = two groups | E10: X = three or more groups | F10: X = continuous
B11: Y continuous (fill volume, torque, PU) | C11: 1-Sample t-Test | D11: 2-Sample t-Test (Welch) Paired t if same units | E11: One-Way ANOVA + Tukey | F11: Correlation then Regression
C12: NP: Wilcoxon signed rank | D12: NP: Mann-Whitney | E12: NP: Kruskal-Wallis | F12: NP: Spearman rho
B13: Y binary (pass/fail, leaking keg) | C13: 1-Proportion Test | D13: 2-Proportion Test | E13: Chi-Square test of independence | F13: Binary Logistic Regression
C14: Exact binomial | D14: Fisher exact if counts are small | E14: Fisher exact | F14: Stratify and use Chi-Square
B15: Y count (micro-stops, label defects) | C15: 1-Sample Poisson rate test | D15: 2-Sample Poisson rate test | E15: Chi-Square on a count table | F15: Regression on the rate (log link approx.)
C16: u-chart against a standard rate | D16: Chi-Square on counts | E16: Compare u-charts by group | F16: Bin X and use Chi-Square
B17: Y ordinal (taste panel score, severity 1-5) | C17: Sign test / Wilcoxon signed rank | D17: Mann-Whitney | E17: Kruskal-Wallis | F17: Spearman rank correlation
C18: Treat as continuous with caution | D18: Chi-Square on collapsed categories | E18: Chi-Square on collapsed categories | F18: Ordinal logistic (out of scope)
B20: DECISION LADDER
B22: START: name the Y (the output you care about) and the X (what you suspect changes it).
B23: Is the Y continuous, binary, a count, or ordinal? -> choose the row in the grid above.
B24: Is the X absent, two groups, three or more groups, or continuous? -> choose the column.
B25: IF Y IS CONTINUOUS, three questions remain before you run the test:
B26: Q1. Is the data approximately normal? Test it on E-32.
B27: Yes -> continue to Q2.
B28: No -> transform on E-33, or jump straight to the nonparametric alternative on E-31.
B29: Q2. Are the group variances comparable? Test it on E-28.
B30: Yes -> pooled t-test or standard ANOVA is available.
B31: No -> use Welch on E-24, or Welch ANOVA / Kruskal-Wallis.
B32: Q3. Are the observations paired (same bottle, same keg, same mould cavity before and after)?
... B43: ASSUMPTION FOOTER STRIP
B45: Check | C45: Sheet | D45: What it tells you
B46: Normality | C46: E-32 Normality Testing and Probability Plots | D46: Whether the parametric test is legitimate at all
B47: Equality of variance | C47: E-28 Tests for Variance: F, Levene, Bartlett | D47: Whether to pool or to use Welch
B48: Assumption failure route | C48: E-33 When Assumptions Fail: Transformations and Alternatives | D48: Transformation or nonparametric alternative
B49: Sample size and power | C49: E-20 Sample Size Determination | D49: Whether a non-significant result means anything

Sheet N-06 Index by Problem
A1: Made by Jose Zapatero, jmazsantos@gmail.com
B2: N-06 — Index by Problem Archetype | K2: TRANSVERSAL
B3: ← Back to Index | D3: Phase: TRANSVERSAL / EXAM | Data required: Problem statement | Min. sample: n/a | Complexity: 2/5 | Typical output: Numbered tool route with expected outputs
B5: Twelve problem archetypes taken from this operation. Find yours, then follow the numbered route.
B6: Each step names the sheet to use and the output you should hold before moving on to the next step.
B8: No. | C8: Archetype | D8: Typical symptom on the floor | E8: Typical duration
B9: 1 | C9: Excessive variability in a measured characteristic | D9: Fill volumes swing from 495 to 508 ml on the same SKU within one shift. | E9: 6-10 weeks
B10: 2 | C10: Process off-target / centring problem | D10: Average fill sits at 503 ml against a 500 ml target: three millilitres given away per bottle. | E10: 3-6 weeks
B11: 3 | C11: High defect or rejection rate (attribute) | D11: Innocheck FBI rejects 1.8% of bottles; target is below 0.5%. | E11: 6-10 weeks
B12: 4 | C12: Unplanned downtime and micro-stops | D12: Innopal and Robopac produce 40 to 60 micro-stops per shift, none longer than two minutes. | E12: 8-12 weeks
B13: 5 | C13: Slow changeover between formats | D13: A 1.5 L to 0.5 L change takes 95 minutes and varies by 30 minutes between shifts. | E13: 4-6 weeks (Kaizen)
B14: 6 | C14: Material loss / yield / shrinkage | D14: PET preform consumption runs 2.4% above theoretical; label loss above 3%. | E14: 8-12 weeks
B15: 7 | C15: Long cycle time or low throughput | D15: Nominal 18,000 BPH but the real average over a week is 13,400 BPH. | E15: 8-12 weeks
B16: 8 | C16: Customer complaint or market incident | D16: Distributor reports flat product and low CO2 in a specific batch. | E16: 1 day containment, 60 days closure
B17: 9 | C17: Difference between shifts, machines or operators | D17: Shift C consistently fills 1.5 ml higher than Shift A on the same SKU. | E17: 4-8 weeks
B18: 10 | C18: Measurement disagreement between operators or instruments | D18: Laboratory and line CO2 readings differ by 0.3 g/L on the same sample. | E18: 3-5 weeks
B19: 11 | C19: Safety incident or near miss | D19: Operator near miss during a manual jam clearance on the Innoket with the guard defeated. | E19: 24 h containment, 30-60 days closure
B20: 12 | C20: Cost overrun on a consumable | D20: Glue, film and CO2 consumption per 1,000 bottles is 12% above standard. | E20: 6-8 weeks
B23: ARCHETYPE 1 — Excessive variability in a measured characteristic
B24: What it is: The average is fine but the spread is too wide to hold the specification.
B25: How it shows up: Fill volumes swing from 495 to 508 ml on the same SKU within one shift.
B26: Typical duration: 6-10 weeks | Steps: 10
B28: Step | C28: Tool (click to open) | D28: Output you should hold before moving on | E28: Phase
B29: 1 | C29: H-02 SIPOC | D29: Process boundaries and the exact characteristic agreed | E29: D
B30: 2 | C30: E-06 Operational Definitions and Data Collection Plan | D30: Operational definition and a sampling plan that can detect the shift | E30: M
B31: 3 | C31: E-59 Gage R&R: ANOVA and Range Methods | D31: %GRR: proof the spread is the process, not the gauge | E31: M
B32: 4 | C32: E-03 Descriptive Statistics: Centre and Spread | D32: Baseline mean, StDev and shape | E32: M
B33: 5 | C33: E-50 Xbar-R Chart | D33: Chart showing whether the spread is stable or erratic | E33: C
B34: 6 | C34: E-57 Cp, Cpk, Pp, Ppk and Cpm | D34: Cp vs Cpk: separates spread problems from centring problems | E34: M
B35: 7 | C35: E-40 Multi-Vari Analysis | D35: Dominant family of variation: valve, cavity, shift or time | E35: A
B36: 8 | C36: E-26 One-Way ANOVA with Tukey HSD | D36: Statistical confirmation of the difference between valves or cavities | E36: A
B37: 9 | C37: E-42 Full Factorial Designs (2^k) | D37: Settings that reduce the spread, tested rather than argued | E37: I
B38: 10 | C38: H-16 Control Plan and Reaction Plan (OCAP) | D38: Control plan and reaction plan that hold the new sigma | E38: C
C39: ↑ Back to the archetype list
B41: ARCHETYPE 2 — Process off-target / centring problem
B42: What it is: The spread is acceptable but the average sits away from the nominal value.
B43: How it shows up: Average fill sits at 503 ml against a 500 ml target: three millilitres given away per bottle.
B44: Typical duration: 3-6 weeks | Steps: 10
B46: Step | C46: Tool (click to open) | D46: Output you should hold before moving on | E46: Phase
B47: 1 | C47: E-06 Operational Definitions and Data Collection Plan | D47: Agreed measurement method and sampling frequency | E47: M
B48: 2 | C48: E-59 Gage R&R: ANOVA and Range Methods | D48: Confirmation that the gauge is not biased | E48: M
B49: 3 | C49: E-03 Descriptive Statistics: Centre and Spread | D49: Current mean and standard deviation | E49: M
B50: 4 | C50: E-15 Confidence Intervals for the Mean | D50: Confidence interval: is the offset real or noise? | E50: M
B51: 5 | C51: E-23 One-Sample t-Test | D51: 1-sample t-test against target with a p-value | E51: A
B52: 6 | C52: E-57 Cp, Cpk, Pp, Ppk and Cpm | D52: Cpk vs Cp: quantifies the cost of the offset | E52: M
B53: 7 | C53: G-02 Business Case and Cost of Poor Quality | D53: Annual value of the give-away, in currency | E53: D
B54: 8 | C54: L-14 Standard Work and Combination Sheet | D54: Standard work for setting and verifying the setpoint | E54: C
B55: 9 | C55: E-49 Individuals and Moving Range Chart | D55: Chart proving the new centre holds | E55: C
B56: 10 | C56: H-16 Control Plan and Reaction Plan (OCAP) | D56: Reaction plan for the next drift | E56: C
C57: ↑ Back to the archetype list
B59: ARCHETYPE 3 — High defect or rejection rate (attribute)
B60: What it is: Units are rejected at inspection or by the customer at an unacceptable rate.
B61: How it shows up: Innocheck FBI rejects 1.8% of bottles; target is below 0.5%.
B62: Typical duration: 6-10 weeks | Steps: 10
B64: Step | C64: Tool (click to open) | D64: Output you should hold before moving on | E64: Phase
B65: 1 | C65: H-05 Check Sheets and Data Collection Forms | D65: Check sheet capturing defect type, time, machine and operator | E65: M
B66: 2 | C66: H-06 Pareto Analysis | D66: Pareto: the two or three defect types worth attacking | E66: M
B67: 3 | C67: H-09 Stratification | D67: Stratification by shift, cavity, supplier and speed | E67: A
B68: 4 | C68: E-52 p and np Charts | D68: p chart: is the rate stable or driven by events? | E68: C
B69: 5 | C69: E-29 One and Two Proportion Tests | D69: Proportion test confirming a real difference between strata | E69: A
B70: 6 | C70: H-10 Ishikawa / Fishbone Diagram | D70: Structured cause list for the leading defect | E70: A
B71: 7 | C71: H-11 5 Whys | D71: Root cause verified, not assumed | E71: A
B72: 8 | C72: H-13 FMEA (AIAG-VDA 2019, Action Priority) | D72: Failure modes ranked by Action Priority | E72: A
B73: 9 | C73: L-17 Poka-Yoke (Mistake Proofing) | D73: Mistake-proofing so the defect cannot be made | E73: I
B74: 10 | C74: H-16 Control Plan and Reaction Plan (OCAP) | D74: Control plan with the new rejection limit | E74: C
C75: ↑ Back to the archetype list
B77: ARCHETYPE 4 — Unplanned downtime and micro-stops
B78: What it is: The line is available on paper but stops constantly for short periods.
B79: How it shows up: Innopal and Robopac produce 40 to 60 micro-stops per shift, none longer than two minutes.
B80: Typical duration: 8-12 weeks | Steps: 10
B82: Step | C82: Tool (click to open) | D82: Output you should hold before moving on | E82: Phase
B83: 1 | C83: L-11 Overall Equipment Effectiveness | D83: OEE split showing how much is availability loss | E83: M
B84: 2 | C84: H-05 Check Sheets and Data Collection Forms | D84: Stop log with cause, duration, machine and shift | E84: M
B85: 3 | C85: H-06 Pareto Analysis | D85: Pareto of stops by cause and by lost minutes (they rank differently) | E85: M
B86: 4 | C86: E-11 Poisson Distribution (Defects per Unit) | D86: Poisson baseline rate of stops per shift | E86: M
B87: 5 | C87: E-53 c and u Charts | D87: u chart: is the stop rate stable? | E87: C
B88: 6 | C88: H-09 Stratification | D88: Stratification by shift, product and speed | E88: A
B89: 7 | C89: E-30 Chi-Square Tests and Fisher Exact | D89: Chi-square confirming a shift or machine effect | E89: A
B90: 8 | C90: H-11 5 Whys | D90: Root cause of the leading stop mode | E90: A
B91: 9 | C91: L-16 TPM and Autonomous Maintenance | D91: Autonomous maintenance standards on the failing component | E91: I
B92: 10 | C92: L-18 Jidoka and Andon | D92: Andon and escalation so stops surface instead of hiding | E92: C
C93: ↑ Back to the archetype list
B95: ARCHETYPE 5 — Slow changeover between formats
B96: What it is: Format or SKU changes consume production time and discourage smaller batches.
B97: How it shows up: A 1.5 L to 0.5 L change takes 95 minutes and varies by 30 minutes between shifts.
B98: Typical duration: 4-6 weeks (Kaizen) | Steps: 10
B100: Step | C100: Tool (click to open) | D100: Output you should hold before moving on | E100: Phase
B101: 1 | C101: L-15 SMED and Quick Changeover | D101: Timed element list split into internal and external | E101: I
B102: 2 | C102: L-05 Spaghetti Diagram | D102: Spaghetti diagram showing walking and tool hunting | E102: M
B103: 3 | C103: L-22 Gemba Walk | D103: Direct observation of two full changeovers | E103: M
B104: 4 | C104: E-03 Descriptive Statistics: Centre and Spread | D104: Baseline mean and StDev of changeover time | E104: M
B105: 5 | C105: L-25 Pugh Matrix, Impact-Effort, Weighted Criteria | D105: Prioritised countermeasures by impact and effort | E105: I
B106: 6 | C106: L-14 Standard Work and Combination Sheet | D106: Standard work sheet with the new sequence and roles | E106: C
B107: 7 | C107: E-24 Two-Sample t-Test (Welch and Pooled) | D107: Before vs after t-test proving the reduction | E107: A
B108: 8 | C108: E-49 Individuals and Moving Range Chart | D108: I-MR chart holding changeover time under the new limit | E108: C
B109: 9 | C109: L-21 Kaizen Event Planning and Execution | D109: Kaizen record and follow-up actions | E109: I
B110: 10 | C110: H-16 Control Plan and Reaction Plan (OCAP) | D110: Control plan entry for changeover time | E110: C
C111: ↑ Back to the archetype list
B113: ARCHETYPE 6 — Material loss / yield / shrinkage
B114: What it is: Material consumed exceeds material shipped by more than the accepted allowance.
...

Sheet N-07 Tollgates
A1: Made by Jose Zapatero, jmazsantos@gmail.com
B2: N-07 — Phase Tollgate Checklists | K2: TRANSVERSAL
B3: ← Back to Index | D3: Phase: TRANSVERSAL / EXAM | Data required: Project deliverables | Min. sample: n/a | Complexity: 2/5 | Typical output: Percentage complete per phase and readiness
B5: A tollgate is not a formality. It is the moment the Champion asks whether the phase produced what it was supposed to produce.
B6: Answer Yes or No in the yellow column. The percentage complete and the verdict update themselves.
B8: YELLOW = overwrite with your data | C8: GREEN = calculated automatically
B10: DEFINE TOLLGATE
B11: Deliverable | C11: Produced on | D11: Acceptance question the Champion will ask | E11: Done?
B12: Approved project charter | C12: H-01 Project Charter | D12: Is the problem statement free of causes and solutions? | E12: No
B13: Business case with COPQ | C13: G-02 Business Case and Cost of Poor Quality | D13: Has Finance agreed the size of the prize? | E13: No
B14: Process boundaries agreed | C14: H-02 SIPOC | D14: Do we know where the project starts and stops? | E14: No
B15: Customer needs translated to CTQ | C15: H-03 Voice of the Customer and CTQ Tree | D15: Is every CTQ measurable with a specification? | E15: No
B16: Stakeholders mapped and engaged | C16: G-03 Stakeholder Analysis | D16: Does anyone with veto power still oppose this? | E16: No
B17: RACI agreed | C17: G-04 RACI Matrix | D17: Does every deliverable have exactly one Accountable? | E17: No
B18: Risks identified | C18: G-07 Project Risk Register | D18: Do we know what would kill this project? | E18: No
B19: Phase complete | D19: =IF(E19=1,"TOLLGATE PASSED - phase may be closed",IF(E19>=0.8,"NEARLY THERE - close the remaining gaps","NOT READY - do not book the review yet")) -> NOT READY - do not book the review yet | E19: =IFERROR(COUNTIF(E12:E18,"Yes")/COUNTA(E12:E18),0) -> 0
B21: MEASURE TOLLGATE
B22: Deliverable | C22: Produced on | D22: Acceptance question the Champion will ask | E22: Done?
B23: Detailed process map | C23: L-04 Process Mapping and Swimlane Flowcharts | D23: Does the map show the process as it is, not as designed? | E23: No
B24: Operational definitions and data collection plan | C24: E-06 Operational Definitions and Data Collection Plan | D24: Would two operators record the same value? | E24: No
B25: Measurement system validated | C25: E-59 Gage R&R: ANOVA and Range Methods | D25: Is %GRR below 10% of study variation (30% is the limit)? | E25: No
B26: Sample size justified | C26: E-20 Sample Size Determination | D26: Is the sample large enough to detect the effect we care about? | E26: No
B27: Baseline data collected | C27: E-03 Descriptive Statistics: Centre and Spread | D27: Do we have at least 25 stable subgroups? | E27: No
B28: Process stability assessed | C28: E-49 Individuals and Moving Range Chart | D28: Is the baseline free of unexplained special causes? | E28: No
B29: Baseline capability stated | C29: E-57 Cp, Cpk, Pp, Ppk and Cpm | D29: Do we have a Cpk or a sigma level everyone accepts? | E29: No
B30: Phase complete | D30: =IF(E30=1,"TOLLGATE PASSED - phase may be closed",IF(E30>=0.8,"NEARLY THERE - close the remaining gaps","NOT READY - do not book the review yet")) -> NOT READY - do not book the review yet | E30: =IFERROR(COUNTIF(E23:E29,"Yes")/COUNTA(E23:E29),0) -> 0
B32: ANALYZE TOLLGATE
B33: Deliverable | C33: Produced on | D33: Acceptance question the Champion will ask | E33: Done?
B34: Potential causes generated | C34: H-10 Ishikawa / Fishbone Diagram | D34: Did the list come from the people who run the process? | E34: No
B35: Causes screened and ranked | C35: H-12 Cause and Effect (X-Y) Matrix | D35: Are the vital few X's named and prioritised? | E35: No
B36: Data stratified | C36: H-09 Stratification | D36: Have we looked inside every obvious subgroup? | E36: No
B37: Hypotheses tested statistically | C37: E-22 Hypothesis Test Selection Roadmap | D37: Is each root cause supported by a p-value or a chart? | E37: No
B38: Assumptions verified | C38: E-32 Normality Testing and Probability Plots | D38: Was normality and equal variance checked before the test? | E38: No
B39: Root cause validated, not assumed | C39: H-11 5 Whys | D39: Can we turn the problem on and off at will? | E39: No
B40: Practical significance confirmed | C40: E-21 Statistical vs Practical Significance | D40: Is the effect large enough to justify a solution? | E40: No
B41: Phase complete | D41: =IF(E41=1,"TOLLGATE PASSED - phase may be closed",IF(E41>=0.8,"NEARLY THERE - close the remaining gaps","NOT READY - do not book the review yet")) -> NOT READY - do not book the review yet | E41: =IFERROR(COUNTIF(E34:E40,"Yes")/COUNTA(E34:E40),0) -> 0
B43: IMPROVE TOLLGATE
B44: Deliverable | C44: Produced on | D44: Acceptance question the Champion will ask | E44: Done?
B45: Solutions generated | C45: L-24 Idea Generation: Brainwriting, SCAMPER | D45: Did we go beyond the first obvious idea? | E45: No
B46: Solutions selected with criteria | C46: L-25 Pugh Matrix, Impact-Effort, Weighted Criteria | D46: Was the choice scored rather than argued? | E46: No
B47: Optimum settings determined | C47: E-42 Full Factorial Designs (2^k) | D47: Were the settings tested experimentally? | E47: No
B48: Risk of the new process assessed | C48: H-13 FMEA (AIAG-VDA 2019, Action Priority) | D48: Has the FMEA been re-scored after the change? | E48: No
B49: Pilot run completed | C49: L-26 Pilot Design and Confirmation Run | D49: Did the pilot reproduce the predicted improvement? | E49: No
B50: Improvement confirmed statistically | C50: E-24 Two-Sample t-Test (Welch and Pooled) | D50: Is the before/after difference significant and material? | E50: No
B51: Change management plan executed | C51: G-06 Change Management and Resistance (ADKAR) | D51: Do the operators want the new way, or merely tolerate it? | E51: No
B52: Phase complete | D52: =IF(E52=1,"TOLLGATE PASSED - phase may be closed",IF(E52>=0.8,"NEARLY THERE - close the remaining gaps","NOT READY - do not book the review yet")) -> NOT READY - do not book the review yet | E52: =IFERROR(COUNTIF(E45:E51,"Yes")/COUNTA(E45:E51),0) -> 0
B54: CONTROL TOLLGATE
B55: Deliverable | C55: Produced on | D55: Acceptance question the Champion will ask | E55: Done?
B56: Control plan issued | C56: H-16 Control Plan and Reaction Plan (OCAP) | D56: Does every critical X have a control and a reaction? | E56: No
B57: Reaction plan understood by operators | C57: H-16 Control Plan and Reaction Plan (OCAP) | D57: Can a night-shift operator name the first action? | E57: No
B58: Standard work updated and trained | C58: L-14 Standard Work and Combination Sheet | D58: Is the new method the documented method? | E58: No
B59: Control charts live on the floor | C59: E-48 Control Chart Selection Tree | D59: Is the correct chart being maintained by the operator? | E59: No
B60: Visual management in place | C60: L-13 Visual Management | D60: Can a visitor see the status in 30 seconds? | E60: No
B61: Benefit validated by Finance | C61: G-09 Financial Benefit Validation (Hard vs Soft) | D61: Has the saving been signed, not estimated? | E61: No
B62: Handover, lessons learned and replication | C62: G-10 Closure, Handover, Lessons Learned, Replication | D62: Does the process owner accept ownership in writing? | E62: No
B63: Phase complete | D63: =IF(E63=1,"TOLLGATE PASSED - phase may be closed",IF(E63>=0.8,"NEARLY THERE - close the remaining gaps","NOT READY - do not book the review yet")) -> NOT READY - do not book the review yet | E63: =IFERROR(COUNTIF(E56:E62,"Yes")/COUNTA(E56:E62),0) -> 0
B65: OVERALL PROJECT READINESS
B67: Deliverables complete (of 35) | E67: =COUNTIF(E12:E18,"Yes")+COUNTIF(E23:E29,"Yes")+COUNTIF(E34:E40,"Yes")+COUNTIF(E45:E51,"Yes")+COUNTIF(E56:E62,"Yes") -> 0
B68: Overall readiness | D68: =IF(E68=1,"PROJECT COMPLETE - proceed to closure on G-10",IF(E68>=0.6,"ON TRACK - keep the tollgate discipline","EARLY STAGE - do not skip Measure to reach Improve faster")) -> EARLY STAGE - do not skip Measure to reach Improve faster | E68: =IFERROR((COUNTIF(E12:E18,"Yes")+COUNTIF(E23:E29,"Yes")+COUNTIF(E34:E40,"Yes")+COUNTIF(E45:E51,"Yes")+COUNTIF(E56:E62,"Yes"))/35,0) -> 0
B70: A tollgate answered honestly with a No is more valuable than a project that reaches Improve without a validated measurement system.

Sheet N-08 Fast Track Routes
A1: Made by Jose Zapatero, jmazsantos@gmail.com
B2: N-08 — When Not To Run a Full DMAIC | K2: TRANSVERSAL
B3: ← Back to Index | D3: Phase: TRANSVERSAL / EXAM | Data required: Five screening answers | Min. sample: n/a | Complexity: 2/5 | Typical output: Recommended methodology route
B5: Knowing when NOT to run a full DMAIC is a Black Belt judgement.
B6: A four-month project aimed at a problem whose cause is already known destroys credibility faster than any failed hypothesis test.
B9: THE FIVE ROUTES COMPARED
B10: Route | C10: When to use it | D10: Typical duration | E10: Data requirement | F10: Who leads it | G10: Link
B11: Full DMAIC | C11: Root cause is unknown and the answer needs data and statistics | D11: 3-6 months | E11: High: baseline, MSA, hypothesis tests, capability | F11: Black Belt or trained Green Belt | G11: Open →
B12: Kaizen Event | C12: Cause is understood, the solution is known or close, and the work is hands-on | D12: 1 week plus 30 days follow-up | E12: Medium: time studies and before/after data | F12: Facilitator with a cross-functional team | G12: Open →
B13: A3 | C13: A single well-bounded problem needing structured thinking and alignment | D13: 2-6 weeks | E13: Low to medium: enough data to prove the current condition | F13: The process owner, coached | G13: Open →
B14: 8D | C14: Customer complaint, safety event or regulatory issue requiring containment | D14: 24 h containment, 30-60 days to close | E14: Medium: containment evidence and root cause proof | F14: Quality lead with the process owner | G14: Open →
B15: Just Do It | C15: Cause and solution are both obvious, cost is low and risk is low | D15: Same day to two weeks | E15: Minimal: confirm the before and after | F15: Supervisor or operator | G15: Open →
B18: FIVE-QUESTION SCREENING
B20: YELLOW = overwrite with your data | C20: GREEN = calculated automatically
B22: No. | C22: Screening question | F22: Answer
B23: 1 | C23: Is a customer complaint, safety event or regulatory issue driving this? | F23: No
B24: 2 | C24: Is the root cause already known and agreed with evidence? | F24: No
B25: 3 | C25: Is the solution obvious, cheap (no capital) and low risk? | F25: No
B26: 4 | C26: Would answering this require statistical analysis of collected data? | F26: Yes
B27: 5 | C27: Could a cross-functional team finish the work in one focused week? | F27: No
B29: RECOMMENDED ROUTE | C29: =IF(F23="Yes","8D - contain within 24 hours, then close formally (H-15)",IF(F25="Yes","JUST DO IT - implement, verify the before and after, move on (L-23)",IF(AND(F24="Yes",F27="Yes"),"KAIZEN EVENT - one focused week with the team (L-21)",IF(AND(F24="Yes",F27="No"),"A3 - structured single-page project (H-14)",IF(F26="Yes","FULL DMAIC - the cause needs data and statistics (N-03)","A3 - start here and escalate to DMAIC only if the cause resists"))))) -> FULL DMAIC - the cause needs data and statistics (N-03)
B31: WHY THIS MATTERS
B33: • DMAIC earns its cost when the cause is genuinely unknown and the answer lives in data. That is the only condition under which four months of Measure and Analyze is cheaper than guessing.
B34: • If the cause is known and the fix is known, the value is in execution speed, not in analysis. Run a Kaizen event or simply do it, and spend the saved months on the next problem.
B35: • A customer or safety event overrides everything: contain first, analyse second. 8D exists because the customer needs protection before you need certainty.
B36: • The commonest failure is the reverse one: launching a Just Do It on a problem whose cause was never verified, then repeating the same fix three times in a year. If the fix has already failed once, escalate to a route with a validated root cause.

Sheet E-01 Data Types
A1: Made by Jose Zapatero, jmazsantos@gmail.com
B2: E-01 — Data Types and Measurement Scales | K2: MEASURE
B3: ← Back to Index | D3: Phase: MEASURE | Data required: Any variable list | Min. sample: n/a | Complexity: 1/5 | Typical output: Data classification and permitted statistics
B5: BLOCK 1 — QUICK CARD
B6: What question does this answer? | C6: What kind of data am I holding, and which statistics am I allowed to use on it?
B7: When you would reach for it | C7: Before any chart, test or capability study. It is the first decision of every project.
B8: What it gives you | C8: A classification and the list of tools that classification permits.
B10: BLOCK 2 — CONCEPT
B11: Every statistical method carries a hidden entry requirement: the measurement scale of your data.
B12: There are four scales. Nominal data only labels (machine 1, machine 2) - the numbers carry no order.
B13: Ordinal data has order but no fixed distance (taste panel 1 to 5; the gap 1-2 is not the gap 4-5).
B14: Interval data has fixed distances but an arbitrary zero (degrees Celsius: 40 C is not twice 20 C).
B15: Ratio data has fixed distances and a true zero (fill volume, torque, PU, dissolved oxygen).
B16: In practice the working split is simpler: attribute (nominal, ordinal) versus continuous (interval, ratio).
B17: Continuous data carries far more information per observation, which is why a capability study on 30 fill volumes tells you more than a p chart built from 30,000 pass/fail decisions.
B20: BLOCK 3 — WHEN TO USE / WHEN NOT TO USE / ASSUMPTIONS
B21: WHEN TO USE IT | E21: WHEN NOT TO USE IT
B22: ✓ At the start of every project, on every metric in the data collection plan. | E22: ✗ It is not a test - it produces no p-value.
B23: ✓ Whenever someone proposes averaging a score that is really a rank. | E23: ✗ It does not tell you whether the data is accurate, only what kind it is.
B24: ✓ When choosing between a variables chart and an attribute chart. | E24: ✗ Do not use it to justify converting continuous data into pass/fail: that destroys information.
B25: ✓ When deciding how much data you will need to collect.
B27: Assumption | C27: How to check it | D27: What to do if it fails | E27: Go to
B28: The measurement genuinely has the scale you claim | C28: Ask whether the zero is real and whether the gaps are equal | D28: Downgrade to the safer scale; treating ordinal as continuous inflates significance | E28: E-06 Operational Definitions and Data Collection Plan
B29: The variable is recorded at the resolution the scale implies | C29: Check the number of distinct values in the data | D29: If fewer than ten distinct values, treat as discrete regardless of the instrument | E29: E-59 Gage R&R: ANOVA and Range Methods
B30: Categories are mutually exclusive and exhaustive | C30: Check that no unit can be counted in two categories | D30: Redefine the categories in the operational definition | E30: E-06 Operational Definitions and Data Collection Plan
B32: BLOCK 4 — FORMULA AND DERIVATION
B33: No formula. The rule is a permission table.
B34: Nominal -> mode, counts, proportions. Mean is meaningless.
B35: Ordinal -> median, mode, percentiles. Mean is questionable.
B36: Interval -> mean, median, mode, standard deviation. Ratios are meaningless.
B37: Ratio -> everything, including coefficient of variation and geometric mean.
B38: Information content per observation, from lowest to highest:
B39: binary < nominal < ordinal < count < continuous
B41: BLOCK 5 — EXCEL IMPLEMENTATION
B42: Function used | C42: Syntax | D42: What the arguments mean
B43: INDEX | C43: INDEX(array, row_number) | D43: Returns the item in position row_number of the permission table
B44: MATCH | C44: MATCH(lookup_value, lookup_array, 0) | D44: Finds the row of the selected scale; 0 forces an exact match
B45: OR | C45: OR(test1, test2) | D45: TRUE if either test is TRUE - used to group the two attribute scales
B46: COUNTA | C46: COUNTA(range) | D46: Counts non-empty cells when auditing the plan
B47: Legacy function names are used throughout (STDEV, TDIST, NORMSDIST). They are accepted by every Excel version and by LibreOffice, and they avoid the unresolved-function name-resolution errors produced by the newer dotted names on some engines.
B49: BLOCK 6 — WORKED EXAMPLE (INTERACTIVE)
B50: Ten variables recorded on the PET line. Select the scale for the variable in the yellow cell and the sheet returns what you are allowed to do with it.
B52: YELLOW = overwrite with your data | C52: GREEN = calculated automatically
B54: Scale | C54: Example on this line | D54: Centre | E54: Spread | F54: Typical chart | G54: Typical test
B55: Nominal | C55: Machine number, defect type, supplier | D55: Mode | E55: Counts and proportions | F55: p chart or np chart (E-52) | G55: Chi-square (E-30)
B56: Ordinal | C56: Taste panel 1-5, FMEA severity | D56: Median and mode | E56: Range and percentiles | F56: Run chart of medians (H-08) | G56: Mann-Whitney (E-31)
B57: Interval | C57: Oven temperature in degrees Celsius | D57: Mean, median, mode | E57: Standard deviation | F57: I-MR or Xbar-R (E-49/E-50) | G57: t-test and ANOVA (E-24/E-26)
B58: Ratio | C58: Fill volume, torque, PU, CO2, wall thickness | D58: Mean and geometric mean | E58: StDev and coefficient of variation | F58: Xbar-R plus capability (E-57) | G58: t, ANOVA, regression (E-36)
B60: Variable you are classifying | C60: Fill volume (ml)
B61: Measurement scale (choose) | C61: Ratio
B63: Permitted measure of centre | C63: =INDEX($D$55:$D$58,MATCH($C$61,$B$55:$B$58,0)) -> Mean and geometric mean
B64: Permitted measure of spread | C64: =INDEX($E$55:$E$58,MATCH($C$61,$B$55:$B$58,0)) -> StDev and coefficient of variation
B65: Chart you should be using | C65: =INDEX($F$55:$F$58,MATCH($C$61,$B$55:$B$58,0)) -> Xbar-R plus capability (E-57)
B66: Test you would normally run | C66: =INDEX($G$55:$G$58,MATCH($C$61,$B$55:$B$58,0)) -> t, ANOVA, regression (E-36)
B68: BLOCK 7 — DECISION RULE AND INTERPRETATION
B69: VERDICT | C69: =IF(OR($C$61="Nominal",$C$61="Ordinal"),"ATTRIBUTE DATA - counts and proportions only. Expect to need 10 to 100 times more samples.","CONTINUOUS DATA - the full parametric toolkit is available, including capability indices.") -> CONTINUOUS DATA - the full parametric toolkit is available, including capability indices.
B71: Criterion | C71: Numeric rule | D71: What it means in practice
B72: Distinct values in the data | C72: Fewer than 10 | D72: Treat as discrete even if the gauge reads decimals
B73: Zero is a true zero | C73: Yes | D73: Ratio scale: coefficient of variation is meaningful
B74: Equal gaps between values | C74: Yes | D74: Interval or ratio: the mean is meaningful
B75: Categories only, no order | C75: Yes | D75: Nominal: only the mode and proportions are meaningful
B77: COMMON MISTAKES
B78: • Averaging an ordinal score. A mean FMEA severity of 6.4 has no physical meaning.
B79: • Converting a perfectly good continuous measurement into pass/fail to make the report simpler. You throw away roughly 90% of the information and then need a far larger sample.
B80: • Treating a count as continuous. Counts are bounded below by zero and are usually skewed; see E-11.
B81: • Assuming that because the gauge shows three decimals the data is continuous. Resolution is not scale.
B82: • Classifying once at the start of the project and never revisiting it when the metric is redefined.
B84: BLOCK 8 — SELF-CHECK
B85: Answer in your head, then select the cell in column N on the same row to reveal the answer (the text is white, not hidden). | N85: ANSWERS → select the cell to read the white text
B86: Q1. An operator records bottle appearance as 1 = perfect, 2 = minor, 3 = reject. Is the average of those numbers meaningful? | N86: A1. No. The scale is ordinal: the distance between 1 and 2 is not the same as between 2 and 3. Report the median and the distribution of counts, and compare groups with a nonparametric test (E-31).
B87: Q2. Why does attribute data require a much larger sample than continuous data for the same conclusion? | N87: A2. Each attribute observation carries only one bit of information (pass or fail), whereas a continuous measurement locates the unit on a scale. Detecting a small change in a proportion therefore needs hundreds or thousands of units, while 30 continuous measurements often suffice.
B88: Q3. Dissolved oxygen is measured in ppb. Which scale is it, and does that permit a coefficient of variation? | N88: A3. Ratio, because zero ppb means genuinely no oxygen. A true zero permits ratios, so the coefficient of variation (StDev divided by the mean) is meaningful.
B90: BLOCK 9 — RELATED SHEETS
B91: Previous tool | C91: Next tool | D91: If the definition is the problem
B92: N-05 Statistical Test Selector (Y vs X Matrix) | C92: E-02 Population, Sample and Sampling Error | D92: E-06 Operational Definitions and Data Collection Plan

Sheet E-02 Population vs Sample
A1: Made by Jose Zapatero, jmazsantos@gmail.com
B2: E-02 — Population, Sample and Sampling Error | K2: MEASURE
B3: ← Back to Index | D3: Phase: MEASURE | Data required: Sample values | Min. sample: 5 | Complexity: 1/5 | Typical output: Sampling error estimate
B5: BLOCK 1 — QUICK CARD
B6: What question does this answer? | C6: How far can my sample be from the truth simply because it is a sample?
B7: When you would reach for it | C7: Whenever someone reacts to a difference between a sample average and a target.
B8: What it gives you | C8: The expected size of pure sampling noise, so you can tell it from a real shift.
B10: BLOCK 2 — CONCEPT
B11: You never measure the population. You measure a handful of bottles and hope they represent the shift.
B12: Two different samples from the same stable process will give two different averages. That difference is sampling error, and it is not a mistake: it is an unavoidable consequence of sampling.
B14: The size of that error is predictable. It shrinks with the square root of the sample size, which is why going from 4 to 16 bottles halves it, but going from 16 to 32 improves it by only 29 per cent.
B16: The practical consequence is blunt: if the observed gap between your sample mean and the target is smaller than the expected sampling error, you have no evidence of anything and adjusting the machine will make the process worse, not better. This is over-adjustment, and it is the commonest error on any line.
B20: BLOCK 3 — WHEN TO USE / WHEN NOT TO USE / ASSUMPTIONS
B21: WHEN TO USE IT | E21: WHEN NOT TO USE IT
B22: ✓ Before reacting to a single sample average that looks off target. | E22: ✗ Not a substitute for a hypothesis test when you need a formal p-value: use E-23.
B23: ✓ When explaining to a supervisor why two shifts 'always' differ slightly. | E23: ✗ Not valid if the sample was not taken at random from the population of interest.
B24: ✓ When sizing a sample so that the noise is smaller than the effect you care about. | E24: ✗ Does not detect bias: a badly calibrated gauge is wrong on every sample equally.
B26: Assumption | C26: How to check it | D26: What to do if it fails | E26: Go to
B27: The sample is representative of the population you want to describe | C27: Ask how the units were selected; convenience samples are not random | D27: Redesign the sampling plan before trusting any number | E27: E-05 Sampling Strategies and Rational Subgrouping
B28: Observations are independent | C28: Check that consecutive bottles are not from the same mould cavity | D28: Use rational subgrouping so that within-subgroup variation is short-term only | E28: E-05 Sampling Strategies and Rational Subgrouping
B29: The population standard deviation is stable | C29: Plot the data over time on a control chart | D29: If sigma is drifting, no single estimate of sampling error applies | E29: E-49 Individuals and Moving Range Chart
B31: BLOCK 4 — FORMULA AND DERIVATION
B32: Standard error of the mean (population sigma known):
B33: SE = sigma / SQRT(n)
B34: Estimated standard error (sigma unknown, estimated by s):
B35: SE = s / SQRT(n)
B36: Expected maximum sampling error at 95% confidence:
B37: E(max) = 1.96 * SE
B38: Observed sampling error expressed in standard error units:
B39: Z = (xbar - mu) / SE
B40: where mu = population mean (or the target), xbar = sample mean, n = sample size.
B42: BLOCK 5 — EXCEL IMPLEMENTATION
B43: Function used | C43: Syntax | D43: What the arguments mean
B44: AVERAGE | C44: AVERAGE(range) | D44: Sample mean of the measurements
B45: STDEV | C45: STDEV(range) | D45: Sample standard deviation, denominator n-1
B46: COUNT | C46: COUNT(range) | D46: Number of numeric observations
B47: SQRT | C47: SQRT(number) | D47: Square root, used in sigma divided by root n
B48: NORMSINV | C48: NORMSINV(probability) | D48: Standard normal quantile; NORMSINV(0.975) returns 1.96
B49: ABS | C49: ABS(number) | D49: Absolute value, so the comparison ignores the direction of the error
B50: Legacy function names are used throughout (STDEV, TDIST, NORMSDIST). They are accepted by every Excel version and by LibreOffice, and they avoid the unresolved-function name-resolution errors produced by the newer dotted names on some engines.
B52: BLOCK 6 — WORKED EXAMPLE (INTERACTIVE)
B53: Ten bottles taken from the Innofil filler during one hour. The SKU target is 500.0 ml and the historical process standard deviation, from the last capability study, is 1.10 ml.
B55: YELLOW = overwrite with your data | C55: GREEN = calculated automatically
B57: Ten fill volumes (ml) | C57: 500.4 | D57: 499.1 | E57: 501.2 | F57: 500.8 | G57: 498.7
C58: 500.1 | D58: 502.3 | E58: 499.6 | F58: 500.9 | G58: 501.5
B60: Population mean / target, mu (ml) | C60: 500
B61: Known population sigma (ml) | C61: 1.1
B62: Confidence level | C62: 0.95
B64: Sample size n | C64: =COUNT($C$57:$G$58) -> 10
B65: Sample mean xbar (ml) | C65: =AVERAGE($C$57:$G$58) -> 500.46
B66: Sample StDev s (ml) | C66: =STDEV($C$57:$G$58) -> 1.1127543
B67: Standard error, sigma known (ml) | C67: =C61/SQRT(C64) -> 0.34785054
B68: Standard error, sigma estimated (ml) | C68: =C66/SQRT(C64) -> 0.35188382
B69: Z multiplier for the confidence level | C69: =NORMSINV(1-(1-C62)/2) -> 1.959964
B70: Expected maximum sampling error (ml) | C70: =C69*C67 -> 0.68177454
B71: Observed error xbar - mu (ml) | C71: =C65-C60 -> 0.46
B72: Observed error in standard errors | C72: =IFERROR((C65-C60)/C67,0) -> 1.322407
B74: BLOCK 7 — DECISION RULE AND INTERPRETATION
B75: VERDICT | C75: =IF(ABS(C71)<=C70,"WITHIN SAMPLING NOISE - no evidence the process has moved. Do not adjust the filler.","BEYOND SAMPLING NOISE - the offset is larger than sampling alone explains. Confirm with E-23.") -> WITHIN SAMPLING NOISE - no evidence the process has moved. Do not adjust the filler.
B77: Criterion | C77: Numeric rule | D77: What it means in practice
B78: Observed error vs expected | C78: |xbar - mu| <= 1.96 x SE | D78: Noise. Leave the process alone.
B79: Observed error in SE units | C79: |Z| < 2 | D79: Unremarkable for a stable process.
B80: Observed error in SE units | C80: |Z| > 3 | D80: Very unlikely by chance. Investigate.
B81: Effect of quadrupling n | C81: SE halves | D81: Precision is expensive: cost grows as the square of precision.
B83: COMMON MISTAKES
B84: • Adjusting the machine on a single sample. Deming's funnel experiment shows this doubles the variance.
B85: • Comparing a sample mean with a target using the process StDev instead of the standard error. The standard error is the StDev divided by the square root of n, and it is always smaller.
B86: • Assuming a large sample removes bias. It removes noise, not bias; a miscalibrated gauge stays wrong.
B87: • Treating consecutive bottles from the same valve as independent observations of the whole filler.
B89: BLOCK 8 — SELF-CHECK
B90: Answer in your head, then select the cell in column N on the same row to reveal the answer (the text is white, not hidden). | N90: ANSWERS → select the cell to read the white text
B91: Q1. The process StDev is 1.1 ml and you sample 4 bottles. What is the standard error, and what happens if you sample 16? | N91: A1. SE = 1.1 / sqrt(4) = 0.55 ml. With 16 bottles SE = 1.1 / sqrt(16) = 0.275 ml. Four times the sample halves the standard error.
B92: Q2. A supervisor sees a sample mean of 500.6 against a target of 500.0 and adjusts the filler down. The standard error is 0.35 ml. Was that a good decision? | N92: A2. No. The expected sampling error at 95% is 1.96 x 0.35 = 0.69 ml, which is larger than the 0.6 ml observed offset. The reading is ordinary noise; adjusting adds variation to a stable process.
B93: Q3. Why does sampling error not tell you whether the gauge is accurate? | N93: A3. Sampling error describes the spread of sample means around the true population mean. If the gauge is biased, the true population mean it estimates is itself displaced. Bias is assessed in MSA on E-60.
B95: BLOCK 9 — RELATED SHEETS
B96: Previous tool | C96: Next tool | D96: Alternative if assumptions fail
B97: E-01 Data Types and Measurement Scales | C97: E-03 Descriptive Statistics: Centre and Spread | D97: E-14 Standard Error vs Standard Deviation

Sheet E-03 Descriptive Stats
A1: Made by Jose Zapatero, jmazsantos@gmail.com
B2: E-03 — Descriptive Statistics: Centre and Spread | K2: MEASURE
B3: ← Back to Index | D3: Phase: MEASURE | Data required: Continuous measurements | Min. sample: 10 | Complexity: 1/5 | Typical output: Mean, median, StDev, range, quartiles, histogram
B5: BLOCK 1 — QUICK CARD
B6: What question does this answer? | C6: Where is my process centred, how wide is it, and what shape is it?
B7: When you would reach for it | C7: The first numerical step of every Measure phase, before any chart or test.
B8: What it gives you | C8: Mean, median, standard deviation, range, quartiles, CV and a histogram.
B10: BLOCK 2 — CONCEPT
B11: Three questions describe any batch of measurements: where is it, how spread out is it, and what shape is it.
B12: Centre is usually the mean, but the median is the honest answer when the data is skewed or contains outliers:
B13: one bottle recorded at 540 ml because of a valve fault moves the mean and leaves the median untouched.
B14: Spread matters more than centre in packaging. A filler that is off target can be adjusted in a minute;
B15: a filler that is too variable is a project. Cp and Cpk on E-57 separate exactly these two problems.
B16: The coefficient of variation expresses spread as a percentage of the mean, which makes it the only fair way to compare the variability of a 500 ml SKU with that of a 1,500 ml SKU.
B18: Always plot the data before quoting a statistic. Two data sets with identical means and standard deviations can look completely different, and only the histogram will tell you.
B21: BLOCK 3 — WHEN TO USE / WHEN NOT TO USE / ASSUMPTIONS
B22: WHEN TO USE IT | E22: WHEN NOT TO USE IT
B23: ✓ Establishing the baseline of any project metric. | E23: ✗ Not a stability assessment: a stable and an unstable process can share the same mean and StDev.
B24: ✓ Before a capability study, to confirm the data is sensible. | E24: ✗ Do not quote Cp or Cpk from these numbers until the process is shown stable on E-49 or E-50.
B25: ✓ When comparing the spread of two SKUs of different nominal size (use the CV). | E25: ✗ Not meaningful on ordinal data: use the median and percentiles only.
B26: ✓ Whenever an outlier is suspected: compare mean against median.
B28: Assumption | C28: How to check it | D28: What to do if it fails | E28: Go to
B29: The data comes from one process, not several mixed together | C29: Look for two peaks in the histogram, and stratify by shift and cavity | D29: Split the data and describe each stream separately | E29: H-09 Stratification
B30: The measurement system is adequate | C30: Run a Gage R&R before trusting any spread statistic | D30: Fix the gauge first; the observed StDev includes the gauge StDev | E30: E-59 Gage R&R: ANOVA and Range Methods
B31: No outliers from a different cause | C31: Compare mean with median, and inspect the extreme values | D31: Investigate the cause before deleting anything, and never delete silently | E31: E-47 Common Cause vs Special Cause Variation
B33: BLOCK 4 — FORMULA AND DERIVATION
B34: Centre
B35: mean xbar = SUM(xi) / n
B36: median = middle value once sorted (average of the two middle values if n is even)
B37: Spread
B38: variance s^2 = SUM((xi - xbar)^2) / (n - 1)
B39: std dev s = SQRT(s^2)
B40: range R = max - min
B41: IQR = Q3 - Q1
B42: CV = s / xbar, expressed as a percentage
B43: Why n - 1 and not n:
B44: the deviations are taken from the sample mean rather than the unknown population mean, which uses up one degree of freedom. Dividing by n would under-estimate sigma.
B47: BLOCK 5 — EXCEL IMPLEMENTATION
B48: Function used | C48: Syntax | D48: What the arguments mean
B49: AVERAGE / MEDIAN / MODE | C49: AVERAGE(range) | D49: Three measures of centre
B50: STDEV / VAR | C50: STDEV(range) | D50: Sample StDev and variance, denominator n-1
B51: STDEVP / VARP | C51: STDEVP(range) | D51: Population versions, denominator n. Rarely correct for sampled data
B52: QUARTILE | C52: QUARTILE(range, quart) | D52: quart = 1 for Q1, 2 for the median, 3 for Q3
B53: MIN / MAX / COUNT | C53: MIN(range) | D53: Extremes and the number of observations
B54: COUNTIFS | C54: COUNTIFS(range,">="&lo, range,"<"&hi) | D54: Counts the observations falling in one histogram bin
B55: TEXT | C55: TEXT(value, "0.0") | D55: Builds the bin label shown on the chart axis
B56: Legacy function names are used throughout (STDEV, TDIST, NORMSDIST). They are accepted by every Excel version and by LibreOffice, and they avoid the unresolved-function name-resolution errors produced by the newer dotted names on some engines.
B58: BLOCK 6 — WORKED EXAMPLE (INTERACTIVE)
B59: Thirty consecutive fill volumes from the 500 ml SKU, one bottle every two minutes over one hour.
B60: Overwrite the yellow grid with your own measurements; every statistic and the histogram follow.
B61: YELLOW = overwrite with your data | C61: GREEN = calculated automatically
B63: Fill volumes (ml) - 30 measurements | C63: 500.4 | D63: 499.1 | E63: 501.2 | F63: 500.8 | G63: 498.7 | H63: 500.1
C64: 502.3 | D64: 499.6 | E64: 500.9 | F64: 501.5 | G64: 498.9 | H64: 500.2
C65: 499.4 | D65: 501.8 | E65: 500.6 | F65: 499.9 | G65: 500.3 | H65: 502.1
C66: 498.5 | D66: 500.7 | E66: 501.1 | F66: 499.2 | G66: 500.5 | H66: 500
C67: 501.6 | D67: 499.7 | E67: 500.8 | F67: 498.8 | G67: 501.3 | H67: 500.1
B69: Upper specification limit (ml) | C69: 504
B70: Lower specification limit (ml) | C70: 496
B71: Number of histogram bins (8 rows are drawn below) | C71: 8
B73: RESULTS
B74: n (count) | C74: =COUNT($C$63:$H$67) -> 30
B75: Mean xbar (ml) | C75: =AVERAGE($C$63:$H$67) -> 500.33667
B76: Median (ml) | C76: =MEDIAN($C$63:$H$67) -> 500.35
B77: Mode (ml) | C77: =IFERROR(MODE($C$63:$H$67),"no repeated value") -> 500.1
B78: Standard deviation s (ml) | C78: =STDEV($C$63:$H$67) -> 1.0313979
B79: Variance s^2 | C79: =VAR($C$63:$H$67) -> 1.0637816
B80: Minimum (ml) | C80: =MIN($C$63:$H$67) -> 498.5
B81: Maximum (ml) | C81: =MAX($C$63:$H$67) -> 502.3
B82: Range (ml) | C82: =C81-C80 -> 3.8
B83: First quartile Q1 (ml) | C83: =QUARTILE($C$63:$H$67,1) -> 499.625
B84: Third quartile Q3 (ml) | C84: =QUARTILE($C$63:$H$67,3) -> 501.05
B85: Interquartile range IQR (ml) | C85: =C84-C83 -> 1.425
B86: Coefficient of variation | C86: =IFERROR(C78/C75,0) -> 0.0020614078
B87: Mean minus median (skewness signal) | C87: =C75-C76 -> -0.013333333
B88: Observations outside specification | C88: =COUNTIF($C$63:$H$67,">"&C69)+COUNTIF($C$63:$H$67,"<"&C70) -> 0
B90: HISTOGRAM
B91: Bin | C91: Lower | D91: Upper | E91: Count
B92: =TEXT(C92,"0.0")&" - "&TEXT(D92,"0.0") -> 498.5 - 499.0 | C92: =C80+(0)*(C81-C80)/C71 -> 498.5 | D92: =C80+(1)*(C81-C80)/C71 -> 498.975 | E92: =COUNTIFS($C$63:$H$67,">="&C92,$C$63:$H$67,"<"&D92) -> 4
B93: =TEXT(C93,"0.0")&" - "&TEXT(D93,"0.0") -> 499.0 - 499.5 | C93: =C80+(1)*(C81-C80)/C71 -> 498.975 | D93: =C80+(2)*(C81-C80)/C71 -> 499.45 | E93: =COUNTIFS($C$63:$H$67,">="&C93,$C$63:$H$67,"<"&D93) -> 3
B94: =TEXT(C94,"0.0")&" - "&TEXT(D94,"0.0") -> 499.5 - 499.9 | C94: =C80+(2)*(C81-C80)/C71 -> 499.45 | D94: =C80+(3)*(C81-C80)/C71 -> 499.925 | E94: =COUNTIFS($C$63:$H$67,">="&C94,$C$63:$H$67,"<"&D94) -> 3
B95: =TEXT(C95,"0.0")&" - "&TEXT(D95,"0.0") -> 499.9 - 500.4 | C95: =C80+(3)*(C81-C80)/C71 -> 499.925 | D95: =C80+(4)*(C81-C80)/C71 -> 500.4 | E95: =COUNTIFS($C$63:$H$67,">="&C95,$C$63:$H$67,"<"&D95) -> 5
B96: =TEXT(C96,"0.0")&" - "&TEXT(D96,"0.0") -> 500.4 - 500.9 | C96: =C80+(4)*(C81-C80)/C71 -> 500.4 | D96: =C80+(5)*(C81-C80)/C71 -> 500.875 | E96: =COUNTIFS($C$63:$H$67,">="&C96,$C$63:$H$67,"<"&D96) -> 6
B97: =TEXT(C97,"0.0")&" - "&TEXT(D97,"0.0") -> 500.9 - 501.4 | C97: =C80+(5)*(C81-C80)/C71 -> 500.875 | D97: =C80+(6)*(C81-C80)/C71 -> 501.35 | E97: =COUNTIFS($C$63:$H$67,">="&C97,$C$63:$H$67,"<"&D97) -> 4
B98: =TEXT(C98,"0.0")&" - "&TEXT(D98,"0.0") -> 501.4 - 501.8 | C98: =C80+(6)*(C81-C80)/C71 -> 501.35 | D98: =C80+(7)*(C81-C80)/C71 -> 501.825 | E98: =COUNTIFS($C$63:$H$67,">="&C98,$C$63:$H$67,"<"&D98) -> 3
B99: =TEXT(C99,"0.0")&" - "&TEXT(D99,"0.0") -> 501.8 - 502.3 | C99: =C80+(7)*(C81-C80)/C71 -> 501.825 | D99: =C80+(8)*(C81-C80)/C71 -> 502.3 | E99: =COUNTIFS($C$63:$H$67,">="&C99,$C$63:$H$67,"<="&D99) -> 2
B101: BLOCK 7 — DECISION RULE AND INTERPRETATION
B102: VERDICT | C102: =IF(ABS(C87)>0.5*C78,"SKEWED OR OUTLIER PRESENT - report the median, and investigate the extreme values before using the mean",IF(C88>0,"OUT-OF-SPECIFICATION UNITS IN THE SAMPLE - contain first, then continue the study","SYMMETRIC AND IN SPECIFICATION - the mean and standard deviation describe this data fairly")) -> SYMMETRIC AND IN SPECIFICATION - the mean and standard deviation describe this data fairly
B104: Criterion | C104: Numeric rule | D104: What it means in practice
B105: Mean versus median | C105: Difference < 0.5 x s | D105: Roughly symmetric; the mean is a fair summary
B106: Coefficient of variation | C106: CV < 5% | D106: Tight process for a filling operation
B107: Range versus StDev | C107: R is about 4 to 5 x s for n = 30 | D107: A much larger ratio points to an outlier
B108: Bins with zero count in the middle | C108: None | D108: A gap in the middle suggests two mixed streams
B110: COMMON MISTAKES
B111: • Quoting a standard deviation from data that is not stable. Compute it, but do not build capability on it.
B112: • Using STDEVP instead of STDEV. On sampled data the population form under-estimates sigma.
B113: • Deleting outliers because they spoil the picture. Investigate first; an outlier is usually the cheapest root cause you will ever be handed.
B114: • Comparing the standard deviation of a 500 ml SKU with that of a 1,500 ml SKU. Compare the CV instead.
B115: • Reporting the mean of a bimodal distribution. The mean will sit in the valley where nothing is produced.
B117: BLOCK 8 — SELF-CHECK
B118: Answer in your head, then select the cell in column N on the same row to reveal the answer (the text is white, not hidden). | N118: ANSWERS → select the cell to read the white text
...

Sheet E-04 Skewness Kurtosis
A1: Made by Jose Zapatero, jmazsantos@gmail.com
B2: E-04 — Distribution Shape: Skewness and Kurtosis | K2: MEASURE
B3: ← Back to Index | D3: Phase: MEASURE | Data required: Continuous measurements | Min. sample: 25 | Complexity: 2/5 | Typical output: Skewness and kurtosis with interpretation
B5: BLOCK 1 — QUICK CARD
B6: What question does this answer? | C6: Is my distribution symmetric, and how heavy are its tails?
B7: When you would reach for it | C7: Before choosing between normal-theory capability and a non-normal method.
B8: What it gives you | C8: Skewness and kurtosis with their standard errors and a verdict on symmetry.
B10: BLOCK 2 — CONCEPT
B11: Skewness measures asymmetry. Zero means symmetric; positive means a long right tail; negative a long left tail.
B12: Filling processes are often slightly right skewed because a valve can stick open and overfill, but rarely under-fills by the same amount: the physical mechanisms are not symmetric.
B14: Kurtosis measures tail weight relative to a normal distribution. Excel reports excess kurtosis, so a normal distribution returns zero. Positive values mean heavier tails and more extreme values than normal theory expects.
B16: Neither statistic is a test on its own. Each is compared with its own standard error, which depends heavily on n: with 30 observations the standard error of skewness is about 0.43, so a skewness of 0.4 means nothing.
B18: This is why judging normality from skewness alone with a small sample is unreliable; use E-32 for a formal test.
B20: BLOCK 3 — WHEN TO USE / WHEN NOT TO USE / ASSUMPTIONS
B21: WHEN TO USE IT | E21: WHEN NOT TO USE IT
B22: ✓ Before a capability study, to anticipate whether normal theory will hold. | E22: ✗ Not a formal normality test: use E-32 for that.
B23: ✓ When a histogram looks lopsided and you need a number to support the impression. | E23: ✗ Unreliable below about 25 observations: the standard errors are enormous.
B24: ✓ When heavy tails are suspected because occasional extreme values appear. | E24: ✗ Do not use on data that mixes two streams; stratify first on H-09.
B26: Assumption | C26: How to check it | D26: What to do if it fails | E26: Go to
B27: Sample size is adequate | C27: n of at least 25, preferably 50 or more | D27: Collect more data before drawing conclusions about shape | E27: E-20 Sample Size Determination
B28: Data comes from a single process stream | C28: Stratify by shift, cavity and SKU and compare | D28: Split the data; a mixture can look skewed when both streams are symmetric | E28: H-09 Stratification
B29: Extreme values are genuine process output | C29: Trace each extreme value back to its production record | D29: Investigate the special cause rather than reporting the shape statistic | E29: E-47 Common Cause vs Special Cause Variation
B31: BLOCK 4 — FORMULA AND DERIVATION
B32: Skewness (Fisher-Pearson, the form Excel uses):
B33: g1 = n / ((n-1)(n-2)) * SUM( ((xi - xbar) / s)^3 )
B34: Excess kurtosis:
B35: g2 = n(n+1) / ((n-1)(n-2)(n-3)) * SUM( ((xi - xbar)/s)^4 ) - 3(n-1)^2 / ((n-2)(n-3))
B36: Standard errors:
B37: SE(skew) = SQRT( 6n(n-1) / ((n-2)(n+1)(n+3)) )
B38: SE(kurt) = 2 * SE(skew) * SQRT( (n^2 - 1) / ((n-3)(n+5)) )
B39: Test statistic for each:
B40: Z = statistic / its standard error. |Z| > 2 is evidence of departure from normality.
B42: BLOCK 5 — EXCEL IMPLEMENTATION
B43: Function used | C43: Syntax | D43: What the arguments mean
B44: SKEW | C44: SKEW(range) | D44: Fisher-Pearson sample skewness; requires at least three values
B45: KURT | C45: KURT(range) | D45: Excess kurtosis; returns 0 for a normal distribution, not 3
B46: COUNT | C46: COUNT(range) | D46: n, which drives both standard errors
B47: SQRT | C47: SQRT(number) | D47: Used in both standard error expressions
B48: ABS | C48: ABS(number) | D48: Compares the magnitude of Z against 2 regardless of sign
B49: Legacy function names are used throughout (STDEV, TDIST, NORMSDIST). They are accepted by every Excel version and by LibreOffice, and they avoid the unresolved-function name-resolution errors produced by the newer dotted names on some engines.
B51: BLOCK 6 — WORKED EXAMPLE (INTERACTIVE)
B52: The same thirty fill volumes used on E-03. Replace them with your own data and the shape statistics, their standard errors and the verdict all update.
B54: YELLOW = overwrite with your data | C54: GREEN = calculated automatically
B56: Fill volumes (ml) - 30 measurements | C56: 500.4 | D56: 499.1 | E56: 501.2 | F56: 500.8 | G56: 498.7 | H56: 500.1
C57: 502.3 | D57: 499.6 | E57: 500.9 | F57: 501.5 | G57: 498.9 | H57: 500.2
C58: 499.4 | D58: 501.8 | E58: 500.6 | F58: 499.9 | G58: 500.3 | H58: 502.1
C59: 498.5 | D59: 500.7 | E59: 501.1 | F59: 499.2 | G59: 500.5 | H59: 500
C60: 501.6 | D60: 499.7 | E60: 500.8 | F60: 498.8 | G60: 501.3 | H60: 500.1
B62: n | C62: =COUNT($C$56:$H$60) -> 30
B63: Skewness g1 | C63: =SKEW($C$56:$H$60) -> 0.0014162269
B64: Excess kurtosis g2 | C64: =KURT($C$56:$H$60) -> -0.74535132
B65: Standard error of skewness | C65: =SQRT(6*C62*(C62-1)/((C62-2)*(C62+1)*(C62+3))) -> 0.4268924
B66: Standard error of kurtosis | C66: =2*C65*SQRT((C62^2-1)/((C62-3)*(C62+5))) -> 0.83274562
B67: Z for skewness | C67: =IFERROR(C63/C65,0) -> 0.0033175266
B68: Z for kurtosis | C68: =IFERROR(C64/C66,0) -> -0.89505283
B70: BLOCK 7 — DECISION RULE AND INTERPRETATION
B71: VERDICT | C71: =IF(AND(ABS(C67)<2,ABS(C68)<2),"SHAPE CONSISTENT WITH NORMAL - normal-theory capability and t-tests are defensible",IF(ABS(C67)>=2,"SIGNIFICANT SKEW - use the median, transform on E-33, or use non-normal capability on E-58","HEAVY OR LIGHT TAILS - normal theory will misstate the tail probabilities that capability depends on")) -> SHAPE CONSISTENT WITH NORMAL - normal-theory capability and t-tests are defensible
B73: Criterion | C73: Numeric rule | D73: What it means in practice
B74: Skewness | C74: |g1| < 0.5 | D74: Practically symmetric for most purposes
B75: Skewness Z | C75: |Z| < 2 | D75: Not statistically distinguishable from symmetric
B76: Excess kurtosis | C76: |g2| < 1 | D76: Tail weight close enough to normal
B77: Sample size | C77: n >= 25, ideally 50 | D77: Below this the standard errors make the statistics uninformative
B79: COMMON MISTAKES
B80: • Quoting skewness from 15 observations. The standard error is about 0.6, so almost any value is plausible.
B81: • Confusing Excel's excess kurtosis with the classical kurtosis. Excel already subtracts 3.
B82: • Concluding non-normality from shape statistics alone and skipping the probability plot on E-32.
B83: • Treating a mixture of two shifts as one skewed distribution instead of stratifying it.
B84: • Transforming the data to fix skewness before checking whether an outlier caused it.
B86: BLOCK 8 — SELF-CHECK
B87: Answer in your head, then select the cell in column N on the same row to reveal the answer (the text is white, not hidden). | N87: ANSWERS → select the cell to read the white text
B88: Q1. Excel returns a kurtosis of 0.2 for your data. Does that mean the tails are lighter than normal? | N88: A1. No. Excel's KURT reports excess kurtosis, which is already zero for a normal distribution. A value of 0.2 means very slightly heavier tails than normal, and with a typical sample size it is well within sampling noise.
B89: Q2. Why does a right-skewed fill distribution matter more for capability than for the mean? | N89: A2. Capability indices convert a Z score into a defect rate through the normal tail. If the real distribution has a longer right tail than normal, the predicted PPM beyond the upper specification will be badly under-estimated, even though the mean is unaffected.
B90: Q3. Skewness is 0.35 with n = 30. Is the process skewed? | N90: A3. Not demonstrably. SE(skew) is about 0.43, so Z is about 0.8, far below 2. There is no statistical evidence of asymmetry; collect more data if the question matters.
B92: BLOCK 9 — RELATED SHEETS
B93: Previous tool | C93: Next tool | D93: Alternative if assumptions fail
B94: E-03 Descriptive Statistics: Centre and Spread | C94: E-05 Sampling Strategies and Rational Subgrouping | D94: E-32 Normality Testing and Probability Plots

Sheet E-05 Sampling Subgroups
A1: Made by Jose Zapatero, jmazsantos@gmail.com
B2: E-05 — Sampling Strategies and Rational Subgrouping | K2: MEASURE
B3: ← Back to Index | D3: Phase: MEASURE | Data required: Process timeline and sources | Min. sample: n/a | Complexity: 3/5 | Typical output: Sampling plan and subgroup definition
B5: BLOCK 1 — QUICK CARD
B6: What question does this answer? | C6: How and when should I take my samples so that the chart can actually detect a problem?
B7: When you would reach for it | C7: When designing a control plan, an SPC scheme or the baseline data collection.
B8: What it gives you | C8: Subgroup size, sampling interval, and how long a shift would run before a shift is detected.
B10: BLOCK 2 — CONCEPT
B11: Rational subgrouping is the single most misunderstood idea in SPC, and it decides whether your chart works.
B12: The rule is simple to state: take the units inside a subgroup so close together that only common cause variation can act between them. Five consecutive bottles from the same filler over ten seconds is a rational subgroup. Five bottles taken one per hour across a shift is not: shift change, temperature drift and cavity differences all act inside that group.
B16: Why it matters: the within-subgroup spread sets the control limits. If you let long-term variation leak inside the subgroup, the limits become wide, the chart flags nothing, and everybody concludes SPC does not work.
B18: The opposite error is equally common. Taking all five bottles from valve 3 makes the subgroup so homogeneous that limits become absurdly tight and the chart flags constantly. Sample across all valves in rotation instead.
B20: The interval between subgroups is a separate decision, driven by how quickly you need to detect a shift and by how much product would be at risk in the meantime.
B23: BLOCK 3 — WHEN TO USE / WHEN NOT TO USE / ASSUMPTIONS
B24: WHEN TO USE IT | E24: WHEN NOT TO USE IT
B25: ✓ Designing any control chart scheme for the PET or keg line. | E25: ✗ Not applicable to one-off studies where all data is already collected.
B26: ✓ When an existing chart never signals, or signals constantly. | E26: ✗ Does not replace a measurement system analysis: sampling well from a bad gauge still fails.
B27: ✓ Setting the sampling frequency in the control plan on H-16. | E27: ✗ The detection calculation assumes the shift is sustained, not a single spike.
B28: ✓ Deciding how much product is at risk between two samples.
B30: Assumption | C30: How to check it | D30: What to do if it fails | E30: Go to
B31: Only common cause acts within a subgroup | C31: Ask what could change between the first and last unit of the subgroup | D31: Shorten the collection window or restructure the subgroup | E31: E-47 Common Cause vs Special Cause Variation
B32: Subgroups are representative of all streams | C32: Check that all valves, cavities or heads are sampled in rotation | D32: Rotate the sampling point, or chart each stream separately | E32: E-40 Multi-Vari Analysis
B33: The process is not being adjusted between samples | C33: Ask operators whether they tweak settings after each reading | D33: Stop the over-adjustment first; otherwise the chart measures the operator | E33: E-02 Population, Sample and Sampling Error
B35: BLOCK 4 — FORMULA AND DERIVATION
B36: Subgroups per shift:
B37: k = shift length in minutes / sampling interval in minutes
B38: Fraction of production actually measured:
B39: f = (k * n) / (line speed per hour * shift length in hours)
B40: Probability that one subgroup detects a sustained shift of delta sigma, with limits at +/- L sigma:
B41: p = 1 - NORMSDIST(L - delta*SQRT(n)) + NORMSDIST(-L - delta*SQRT(n))
B42: Average run length to signal, and the exposure it implies:
B43: ARL = 1 / p
B44: time to detect = ARL * sampling interval
B45: units at risk = time to detect / 60 * line speed per hour
B47: BLOCK 5 — EXCEL IMPLEMENTATION
B48: Function used | C48: Syntax | D48: What the arguments mean
B49: NORMSDIST | C49: NORMSDIST(z) | D49: Standard normal cumulative probability, used for both tails
B50: SQRT | C50: SQRT(n) | D50: Subgroup size enters the detection power through its square root
B51: IFERROR | C51: IFERROR(value, fallback) | D51: Guards the division when the detection probability is zero
B52: ROUND | C52: ROUND(number, digits) | D52: Presents subgroup counts as whole numbers
B53: Legacy function names are used throughout (STDEV, TDIST, NORMSDIST). They are accepted by every Excel version and by LibreOffice, and they avoid the unresolved-function name-resolution errors produced by the newer dotted names on some engines.
B55: BLOCK 6 — WORKED EXAMPLE (INTERACTIVE)
B56: PET line at 18,000 bottles per hour, eight-hour shift, five bottles per subgroup taken in rotation across the filling valves, one subgroup every 30 minutes. How quickly would a 1.5 sigma shift be caught?
B58: YELLOW = overwrite with your data | C58: GREEN = calculated automatically
B60: Line speed (bottles per hour) | C60: 18000
B61: Shift length (hours) | C61: 8
B62: Subgroup size n | C62: 5
B63: Sampling interval (minutes) | C63: 30
B64: Control limits at L sigma | C64: 3
B65: Shift you want to detect (in sigma) | C65: 1.5
B67: Subgroups per shift | C67: =C61*60/C63 -> 16
B68: Bottles measured per shift | C68: =C67*C62 -> 80
B69: Bottles produced per shift | C69: =C60*C61 -> 144000
B70: Fraction of production measured | C70: =IFERROR(C68/C69,0) -> 0.00055555556
B71: Probability one subgroup signals | C71: =1-NORMSDIST(C64-C65*SQRT(C62))+NORMSDIST(-C64-C65*SQRT(C62)) -> 0.63836877
B72: Average run length to signal (subgroups) | C72: =IFERROR(1/C71,9999) -> 1.5664927
B73: Time to detect (minutes) | C73: =C72*C63 -> 46.99478
B74: Bottles produced before detection | C74: =C73/60*C60 -> 14098.434
B75: False alarm run length (in-control ARL) | C75: =IFERROR(1/(2*(1-NORMSDIST(C64))),9999) -> 370.39835
B77: BLOCK 7 — DECISION RULE AND INTERPRETATION
B78: VERDICT | C78: =IF(C74<=5000,"SAMPLING PLAN ADEQUATE - a sustained shift is caught before a pallet of product is at risk",IF(C74<=20000,"MARGINAL - consider a shorter interval or a larger subgroup","INADEQUATE - too much product is produced before the chart reacts. Shorten the interval or increase n.")) -> MARGINAL - consider a shorter interval or a larger subgroup
B80: Criterion | C80: Numeric rule | D80: What it means in practice
B81: Subgroup size for Xbar-R | C81: n between 4 and 6 | D81: Below 4 the chart is slow; above 8 use Xbar-S (E-51)
B82: Within-subgroup window | C82: Seconds to a few minutes | D82: Long enough only for common cause to act
B83: Detection of a 1.5 sigma shift | C83: ARL below 3 subgroups | D83: Reacts within about one hour on a 30 minute interval
B84: False alarm run length | C84: About 370 subgroups at 3 sigma | D84: Roughly one false alarm every 15 shifts at 2 per hour
B86: COMMON MISTAKES
B87: • Building a subgroup from bottles spread across a whole shift. The limits widen and the chart stops working.
B88: • Sampling always from the same valve. The limits become unrealistically tight and the chart cries wolf.
B89: • Choosing the interval by convenience rather than by how much product is exposed between samples.
B90: • Increasing the subgroup size to improve detection when the real problem is that samples are taken too rarely.
B91: • Forgetting that the operator adjusting the machine between samples destroys the rational subgroup.
B93: BLOCK 8 — SELF-CHECK
B94: Answer in your head, then select the cell in column N on the same row to reveal the answer (the text is white, not hidden). | N94: ANSWERS → select the cell to read the white text
B95: Q1. Why do control limits become too wide when a subgroup spans a whole shift? | N95: A1. Control limits are computed from the within-subgroup variation. If shift change, temperature drift and cavity differences act inside the subgroup, that long-term variation is treated as common cause and inflates the limits, so genuine shifts no longer cross them.
B96: Q2. Doubling the subgroup size from 5 to 10 improves detection by how much, in rough terms? | N96: A2. Detection power depends on delta times the square root of n, so doubling n multiplies the effective shift by about 1.41. It helps, but sampling twice as often usually reduces the product at risk more, because exposure is driven by the interval, not by n.
B97: Q3. The chart signals on nearly every subgroup. What are the two most likely causes? | N97: A3. Either the subgroups are too homogeneous, for example always taken from one valve, so the limits are far too tight; or the process genuinely contains multiple streams that should be charted separately or analysed on E-40.
B99: BLOCK 9 — RELATED SHEETS
B100: Previous tool | C100: Next tool | D100: Alternative if assumptions fail
B101: E-04 Distribution Shape: Skewness and Kurtosis | C101: E-06 Operational Definitions and Data Collection Plan | D101: E-49 Individuals and Moving Range Chart

Sheet E-06 Data Collection Plan
A1: Made by Jose Zapatero, jmazsantos@gmail.com
B2: E-06 — Operational Definitions and Data Collection Plan | K2: MEASURE
B3: ← Back to Index | D3: Phase: MEASURE | Data required: Process and metric list | Min. sample: n/a | Complexity: 2/5 | Typical output: Operational definitions and collection plan
B5: BLOCK 1 — QUICK CARD
B6: What question does this answer? | C6: Will two different people, on two different shifts, record the same thing in the same way?
B7: When you would reach for it | C7: Before a single number is collected, in every project without exception.
B8: What it gives you | C8: An operational definition per metric and a completeness score for the plan.
B10: BLOCK 2 — CONCEPT
B11: An operational definition converts a word into a procedure. 'Label defect' is a word. 'A label whose leading edge deviates more than 2 mm from the reference mark, measured with the gauge at station 4, on a bottle taken from the discharge conveyor' is an operational definition.
B14: The test is simple and unforgiving: could two people, working independently on different shifts, follow the written text and reach the same number? If not, every statistic built on that data is decoration.
B16: Most measurement system failures on a packaging line are not instrument failures. They are definition failures:
B17: two operators counting the same pallet and disagreeing because one counted scuffs and the other did not.
B18: The data collection plan then answers the practical questions: what, who, when, how many, where recorded, and how it will be stratified later. The last one is the most frequently forgotten and the most expensive:
B20: if you did not record shift, valve and SKU at the time, you cannot stratify afterwards, and the study is lost.
B22: BLOCK 3 — WHEN TO USE / WHEN NOT TO USE / ASSUMPTIONS
B23: WHEN TO USE IT | E23: WHEN NOT TO USE IT
B24: ✓ At the start of Measure, before collecting anything. | E24: ✗ Not a substitute for a Gage R&R: a perfect definition with a bad gauge still fails.
B25: ✓ Whenever two sources report different numbers for the same metric. | E25: ✗ Not needed for data that already exists and cannot be re-collected - but state its limitations.
B26: ✓ When an existing report has been argued about more than once. | E26: ✗ Does not fix historical data whose definition is unknown.
B27: ✓ Before any Gage R&R study, because the study needs the definition first.
B29: Assumption | C29: How to check it | D29: What to do if it fails | E29: Go to
B30: The definition can be executed without judgement | C30: Have two operators apply it independently to the same ten units | D30: Rewrite until agreement is reached, then run an attribute agreement study | E30: E-60 MSA: Bias, Linearity, Stability, Attribute Agreement
B31: Stratification factors are captured at the moment of measurement | C31: Check the form has fields for shift, machine, valve, SKU and time | D31: Add the fields before collection starts; they cannot be reconstructed | E31: H-09 Stratification
B32: Sample size is planned, not improvised | C32: Confirm the number of observations was calculated | D32: Calculate it before starting rather than stopping when the data looks convincing | E32: E-20 Sample Size Determination
B34: BLOCK 4 — FORMULA AND DERIVATION
B35: No statistical formula. Two arithmetic checks keep the plan honest.
B36: completeness = COUNTA(fields filled) / (rows * columns) readiness = number of Yes answers / number of checklist questions
B38: The five questions every operational definition must answer:
B39: 1. What exactly is being measured, in physical terms?
B40: 2. With what instrument, at what setting, at what point in the process?
B41: 3. Under what conditions, and by whom?
B42: 4. What is the decision rule that turns the observation into a value?
B43: 5. To what resolution is the result recorded?
B45: BLOCK 5 — EXCEL IMPLEMENTATION
B46: Function used | C46: Syntax | D46: What the arguments mean
B47: COUNTA | C47: COUNTA(range) | D47: Counts non-empty cells to score plan completeness
B48: COUNTIF | C48: COUNTIF(range, "Yes") | D48: Counts the checklist questions answered Yes
B49: IFERROR | C49: IFERROR(value, fallback) | D49: Prevents a division by zero on an empty plan
B50: ROWS / COLUMNS | C50: ROWS(range) | D50: Gives the denominator for the completeness ratio
B51: Legacy function names are used throughout (STDEV, TDIST, NORMSDIST). They are accepted by every Excel version and by LibreOffice, and they avoid the unresolved-function name-resolution errors produced by the newer dotted names on some engines.
B53: BLOCK 6 — WORKED EXAMPLE (INTERACTIVE)
B54: Five metrics from a fill volume project. Overwrite every yellow cell with your own plan;
B55: the completeness score and the readiness verdict update as you type.
B56: YELLOW = overwrite with your data | C56: GREEN = calculated automatically
B58: Metric | C58: Operational definition | D58: Data type | E58: Who and when | F58: Sample size | G58: Stratification captured
B59: Fill volume (ml) | C59: Net content by weight, balance at station 2, tare from the same preform lot | D59: Continuous | E59: Line QA, 5 bottles every 30 min | F59: 5 per subgroup | G59: Shift, valve, SKU, time
B60: Cap torque (Nm) | C60: Removal torque, digital torquemeter, within 5 min of capping | D60: Continuous | E60: Line QA, 3 bottles per hour | F60: 3 per hour | G60: Shift, capping head, SKU
B61: Label deviation (mm) | C61: Leading edge deviation from the reference mark, gauge at station 4 | D61: Continuous | E61: Line QA, 5 bottles per hour | F61: 5 per hour | G61: Shift, labeller lane, SKU
B62: Micro-stops (count) | C62: Any stop under 2 min recorded automatically by the line PLC | D62: Count | E62: PLC, continuous | F62: All events | G62: Shift, machine, SKU, cause code
B63: Leaking kegs (count) | C63: Keg failing the pressure hold test at the Monobloc 80 outlet | D63: Attribute | E63: Operator, every keg | F63: 100% | G63: Shift, filling head, keg age
B65: Plan completeness | C65: =IFERROR(COUNTA($B$59:$G$63)/(ROWS($B$59:$G$63)*COLUMNS($B$59:$G$63)),0) -> 1
B67: Readiness checklist | C67: Answer
B68: Two operators applied the definition independently and reached the same value | C68: No
B69: The instrument, its setting and the measurement point are named | C69: No
B70: Shift, machine, valve or head, SKU and time are recorded with every observation | C70: No
B71: The sample size was calculated on E-20, not chosen by habit | C71: No
B72: The recording form has been used on the floor at least once as a trial | C72: No
B73: The person who will collect the data has been trained on the definition | C73: No
B75: Readiness score | C75: =IFERROR(COUNTIF($C$68:$C$73,"Yes")/COUNTA($C$68:$C$73),0) -> 0
B77: BLOCK 7 — DECISION RULE AND INTERPRETATION
B78: VERDICT | C78: =IF(AND(C65=1,C75=1),"READY TO COLLECT - the plan is complete and every readiness question is answered Yes",IF(C75>=0.8,"ALMOST READY - close the remaining checklist gaps before the first shift of collection","NOT READY - collecting now will produce data nobody will be able to defend")) -> NOT READY - collecting now will produce data nobody will be able to defend
B80: Criterion | C80: Numeric rule | D80: What it means in practice
B81: Plan completeness | C81: 100% | D81: Every field of every metric is defined
B82: Readiness score | C82: 100% | D82: All six checklist questions answered Yes
B83: Independent agreement test | C83: Two operators, ten units, identical results | D83: The definition is executable
B84: Stratification fields | C84: Shift, machine, stream, SKU, time | D84: Analysis on H-09 and E-40 remains possible
B86: COMMON MISTAKES
B87: • Starting collection because the deadline is close. Two weeks of undefendable data costs more than two days of definition.
B88: • Omitting the stratification fields. You cannot add shift or valve to the data after the fact.
B89: • Writing a definition that requires judgement, such as 'obvious scuffing', and then wondering why operators disagree.
B90: • Defining the metric but not the measurement conditions: temperature, time since filling, and settling time all matter.
B91: • Assuming the automatic PLC count needs no definition. Ask what the PLC counts as a stop, and at what threshold.
B93: BLOCK 8 — SELF-CHECK
B94: Answer in your head, then select the cell in column N on the same row to reveal the answer (the text is white, not hidden). | N94: ANSWERS → select the cell to read the white text
B95: Q1. What is the practical test of whether an operational definition is good enough? | N95: A1. Two people who have not spoken to each other follow the written definition on the same ten units and record identical values. If they disagree, the definition, not the operator, is at fault.
B96: Q2. Why must stratification fields be decided before collection rather than during analysis? | N96: A2. Because shift, valve, cavity and SKU cannot be reconstructed after the fact. Data without those fields can only be described in aggregate, and almost every root cause in packaging is found by splitting the data along exactly those factors.
B97: Q3. The PLC already counts micro-stops automatically. Does that metric still need an operational definition? | N97: A3. Yes. You need to know what duration threshold the PLC uses, whether it counts a stop per machine or per line, whether it merges consecutive stops, and how it treats planned stops. Two lines with different PLC settings are not comparable.
B99: BLOCK 9 — RELATED SHEETS
B100: Previous tool | C100: Next tool | D100: Alternative if assumptions fail
B101: E-05 Sampling Strategies and Rational Subgrouping | C101: E-07 The Normal Distribution and Z Scores | D101: E-59 Gage R&R: ANOVA and Range Methods

Sheet E-07 Normal Distribution
A1: Made by Jose Zapatero, jmazsantos@gmail.com
B2: E-07 — The Normal Distribution and Z Scores | K2: MEASURE
B3: ← Back to Index | D3: Phase: MEASURE | Data required: Mean, StDev, limit | Min. sample: n/a | Complexity: 2/5 | Typical output: Z score, tail probability, PPM
B5: BLOCK 1 — QUICK CARD
B6: What question does this answer? | C6: What proportion of my output falls beyond this limit?
B7: When you would reach for it | C7: Whenever a specification limit, a target or a rejection threshold is involved.
B8: What it gives you | C8: A Z score, the tail probability, and the expected PPM outside specification.
B10: BLOCK 2 — CONCEPT
B11: The normal distribution is not a law of nature; it is a useful model that fits many stable measured processes because their variation is the sum of many small independent effects.
B13: Its power is that it needs only two numbers, the mean and the standard deviation, to predict the proportion of output beyond any limit. That prediction is the whole basis of capability indices on E-57.
B15: The Z score is the translation device. It expresses a distance from the mean in standard deviations, which converts any normal distribution into the one standard table: Z = (x - mean) / sigma.
B17: A Z of 3 leaves 1,350 parts per million in that tail. A Z of 4 leaves 32 ppm. A Z of 6 leaves 2 parts per billion, which is where the name six sigma comes from - before the traditional 1.5 sigma long-term shift is applied.
B19: The critical warning: these tail predictions are extremely sensitive to the normality assumption. Being slightly wrong about the shape barely affects the mean, but can be wrong by a factor of ten in the tail.
B22: BLOCK 3 — WHEN TO USE / WHEN NOT TO USE / ASSUMPTIONS
B23: WHEN TO USE IT | E23: WHEN NOT TO USE IT
B24: ✓ Predicting the fraction outside specification from mean and StDev. | E24: ✗ Not valid on strongly skewed or bounded data: use E-58.
B25: ✓ Converting a defect rate into a sigma level and back. | E25: ✗ Do not use it on an unstable process; the mean and sigma have no single value to insert.
B26: ✓ Setting a target mean that balances give-away against under-fill risk. | E26: ✗ Not appropriate for count or attribute data: use E-10 and E-11.
B27: ✓ As the engine behind capability indices and control limits.
B29: Assumption | C29: How to check it | D29: What to do if it fails | E29: Go to
B30: The data is approximately normal | C30: Probability plot and a formal test on E-32 | D30: Transform on E-33 or use non-normal capability on E-58 | E30: E-32 Normality Testing and Probability Plots
B31: The process is stable | C31: Control chart with at least 25 subgroups | D31: Stabilise first; predictions from an unstable process are meaningless | E31: E-49 Individuals and Moving Range Chart
B32: The mean and sigma are well estimated | C32: n of at least 30, ideally 100 for tail work | D32: Widen the estimate with a confidence interval on E-15 and E-16 | E32: E-16 Confidence Intervals for Proportion and Std Dev
B34: BLOCK 4 — FORMULA AND DERIVATION
B35: Standardisation:
B36: Z = (x - mu) / sigma
B37: Probability below a value:
B38: P(X < x) = NORMSDIST(Z)
B39: Probability outside a two-sided specification:
B40: P(out) = NORMSDIST((LSL - mu)/sigma) + (1 - NORMSDIST((USL - mu)/sigma))
B41: Parts per million defective:
B42: PPM = P(out) * 1,000,000
B43: Density used to draw the curve:
B44: f(x) = 1 / (sigma*SQRT(2*PI)) * EXP( -(x - mu)^2 / (2*sigma^2) )
B46: BLOCK 5 — EXCEL IMPLEMENTATION
B47: Function used | C47: Syntax | D47: What the arguments mean
B48: NORMSDIST | C48: NORMSDIST(z) | D48: Cumulative probability below z for the standard normal
B49: NORMSINV | C49: NORMSINV(p) | D49: The inverse: the z that leaves probability p below it
B50: NORMDIST | C50: NORMDIST(x, mean, sd, cumulative) | D50: FALSE returns the density, used to draw the curve
B51: NORMINV | C51: NORMINV(p, mean, sd) | D51: The value of x that leaves probability p below it
B52: ABS | C52: ABS(number) | D52: Used when only the magnitude of the Z score matters
B53: Legacy function names are used throughout (STDEV, TDIST, NORMSDIST). They are accepted by every Excel version and by LibreOffice, and they avoid the unresolved-function name-resolution errors produced by the newer dotted names on some engines.
B55: BLOCK 6 — WORKED EXAMPLE (INTERACTIVE)
B56: The 500 ml SKU is running with a mean of 500.5 ml and a standard deviation of 1.10 ml. The specification is 496.0 to 504.0 ml. How much product falls outside, and what does the give-away cost?
B58: YELLOW = overwrite with your data | C58: GREEN = calculated automatically
B60: Process mean mu (ml) | C60: 500.5
B61: Process StDev sigma (ml) | C61: 1.1
B62: Lower specification limit (ml) | C62: 496
B63: Upper specification limit (ml) | C63: 504
B64: Value of interest x (ml) | C64: 503
B66: Z at the lower limit | C66: =(C62-C60)/C61 -> -4.0909091
B67: Z at the upper limit | C67: =(C63-C60)/C61 -> 3.1818182
B68: Proportion below the lower limit | C68: =NORMSDIST(C66) -> 2.1484278e-05
B69: Proportion above the upper limit | C69: =1-NORMSDIST(C67) -> 0.00073176832
B70: Total proportion out of specification | C70: =C68+C69 -> 0.0007532526
B71: Parts per million defective | C71: =C70*1000000 -> 753.2526
B72: Z bench (overall sigma level) | C72: =IFERROR(NORMSINV(1-C70),6) -> 3.1734275
B73: Z score of the value of interest | C73: =(C64-C60)/C61 -> 2.2727273
B74: Proportion below x | C74: =NORMSDIST(C73) -> 0.98847869
B75: Proportion above x | C75: =1-C74 -> 0.01152131
B76: Give-away versus nominal 500 ml (ml/bottle) | C76: =C60-500 -> 0.5
B78: NORMAL CURVE
B79: x (ml) | C79: Density
B80: =C60+(-20)*C61/5 -> 496.1 | C80: =NORMDIST(B80,C60,C61,FALSE()) -> 0.00012166384
B81: =C60+(-19)*C61/5 -> 496.32 | C81: =NORMDIST(B81,C60,C61,FALSE()) -> 0.0002654063
B82: =C60+(-18)*C61/5 -> 496.54 | C82: =NORMDIST(B82,C60,C61,FALSE()) -> 0.00055627448
B83: =C60+(-17)*C61/5 -> 496.76 | C83: =NORMDIST(B83,C60,C61,FALSE()) -> 0.0011201992
B84: =C60+(-16)*C61/5 -> 496.98 | C84: =NORMDIST(B84,C60,C61,FALSE()) -> 0.0021673529
B85: =C60+(-15)*C61/5 -> 497.2 | C85: =NORMDIST(B85,C60,C61,FALSE()) -> 0.0040289531
B86: =C60+(-14)*C61/5 -> 497.42 | C86: =NORMDIST(B86,C60,C61,FALSE()) -> 0.0071958651
B87: =C60+(-13)*C61/5 -> 497.64 | C87: =NORMDIST(B87,C60,C61,FALSE()) -> 0.012348154
B88: =C60+(-12)*C61/5 -> 497.86 | C88: =NORMDIST(B88,C60,C61,FALSE()) -> 0.020358664
B89: =C60+(-11)*C61/5 -> 498.08 | C89: =NORMDIST(B89,C60,C61,FALSE()) -> 0.03224963
B90: =C60+(-10)*C61/5 -> 498.3 | C90: =NORMDIST(B90,C60,C61,FALSE()) -> 0.049082697
B91: =C60+(-9)*C61/5 -> 498.52 | C91: =NORMDIST(B91,C60,C61,FALSE()) -> 0.071772871
B92: =C60+(-8)*C61/5 -> 498.74 | C92: =NORMDIST(B92,C60,C61,FALSE()) -> 0.10083712
B93: =C60+(-7)*C61/5 -> 498.96 | C93: =NORMDIST(B93,C60,C61,FALSE()) -> 0.13611588
B94: =C60+(-6)*C61/5 -> 499.18 | C94: =NORMDIST(B94,C60,C61,FALSE()) -> 0.17653278
B95: =C60+(-5)*C61/5 -> 499.4 | C95: =NORMDIST(B95,C60,C61,FALSE()) -> 0.21997339
B96: =C60+(-4)*C61/5 -> 499.62 | C96: =NORMDIST(B96,C60,C61,FALSE()) -> 0.26335596
B97: =C60+(-3)*C61/5 -> 499.84 | C97: =NORMDIST(B97,C60,C61,FALSE()) -> 0.30293146
B98: =C60+(-2)*C61/5 -> 500.06 | C98: =NORMDIST(B98,C60,C61,FALSE()) -> 0.33479104
B99: =C60+(-1)*C61/5 -> 500.28 | C99: =NORMDIST(B99,C60,C61,FALSE()) -> 0.35549336
B100: =C60+(0)*C61/5 -> 500.5 | C100: =NORMDIST(B100,C60,C61,FALSE()) -> 0.3626748
B101: =C60+(1)*C61/5 -> 500.72 | C101: =NORMDIST(B101,C60,C61,FALSE()) -> 0.35549336
B102: =C60+(2)*C61/5 -> 500.94 | C102: =NORMDIST(B102,C60,C61,FALSE()) -> 0.33479104
B103: =C60+(3)*C61/5 -> 501.16 | C103: =NORMDIST(B103,C60,C61,FALSE()) -> 0.30293146
B104: =C60+(4)*C61/5 -> 501.38 | C104: =NORMDIST(B104,C60,C61,FALSE()) -> 0.26335596
B105: =C60+(5)*C61/5 -> 501.6 | C105: =NORMDIST(B105,C60,C61,FALSE()) -> 0.21997339
B106: =C60+(6)*C61/5 -> 501.82 | C106: =NORMDIST(B106,C60,C61,FALSE()) -> 0.17653278
B107: =C60+(7)*C61/5 -> 502.04 | C107: =NORMDIST(B107,C60,C61,FALSE()) -> 0.13611588
B108: =C60+(8)*C61/5 -> 502.26 | C108: =NORMDIST(B108,C60,C61,FALSE()) -> 0.10083712
B109: =C60+(9)*C61/5 -> 502.48 | C109: =NORMDIST(B109,C60,C61,FALSE()) -> 0.071772871
B110: =C60+(10)*C61/5 -> 502.7 | C110: =NORMDIST(B110,C60,C61,FALSE()) -> 0.049082697
B111: =C60+(11)*C61/5 -> 502.92 | C111: =NORMDIST(B111,C60,C61,FALSE()) -> 0.03224963
B112: =C60+(12)*C61/5 -> 503.14 | C112: =NORMDIST(B112,C60,C61,FALSE()) -> 0.020358664
B113: =C60+(13)*C61/5 -> 503.36 | C113: =NORMDIST(B113,C60,C61,FALSE()) -> 0.012348154
B114: =C60+(14)*C61/5 -> 503.58 | C114: =NORMDIST(B114,C60,C61,FALSE()) -> 0.0071958651
B115: =C60+(15)*C61/5 -> 503.8 | C115: =NORMDIST(B115,C60,C61,FALSE()) -> 0.0040289531
B116: =C60+(16)*C61/5 -> 504.02 | C116: =NORMDIST(B116,C60,C61,FALSE()) -> 0.0021673529
...

Sheet E-08 Central Limit Theorem
A1: Made by Jose Zapatero, jmazsantos@gmail.com
B2: E-08 — Central Limit Theorem (Live Simulation) | K2: MEASURE
B3: ← Back to Index | D3: Phase: MEASURE | Data required: None (simulated) | Min. sample: n/a | Complexity: 3/5 | Typical output: Raw vs sample-mean histograms
B5: BLOCK 1 — QUICK CARD
B6: What question does this answer? | C6: Why may I use normal theory on data that is clearly not normal?
B7: When you would reach for it | C7: When someone objects that the data is skewed and therefore no test can be run.
B8: What it gives you | C8: A live demonstration that sample means become normal even when the raw data is not. | P8: Raw data (min) | R8: Sample means
P9: Downtime | R9: Mean
B10: BLOCK 2 — CONCEPT | P10: 1.56 | R10: =IF(1<=INT(200/C59),AVERAGE(OFFSET($P$10,(1-1)*C59,0,C59,1)),"") -> 5.284
B11: The Central Limit Theorem is the reason the whole toolkit works. It states that the distribution of sample | P11: 5.24 | R11: =IF(2<=INT(200/C59),AVERAGE(OFFSET($P$10,(2-1)*C59,0,C59,1)),"") -> 5.296
B12: means approaches a normal distribution as the sample size grows, whatever the shape of the raw data. | P12: 4.66 | R12: =IF(3<=INT(200/C59),AVERAGE(OFFSET($P$10,(3-1)*C59,0,C59,1)),"") -> 7.25
B13: Two consequences follow, and both are used constantly on the factory floor. | P13: 9.61 | R13: =IF(4<=INT(200/C59),AVERAGE(OFFSET($P$10,(4-1)*C59,0,C59,1)),"") -> 3.206
B14: First, the Xbar chart is robust. Even if individual measurements are skewed, the averages plotted on the chart | P14: 5.35 | R14: =IF(5<=INT(200/C59),AVERAGE(OFFSET($P$10,(5-1)*C59,0,C59,1)),"") -> 3.544
B15: behave normally, so the standard control limits are valid. This is why the Xbar chart tolerates non-normality | P15: 1.88 | R15: =IF(6<=INT(200/C59),AVERAGE(OFFSET($P$10,(6-1)*C59,0,C59,1)),"") -> 3.184
B16: and the Individuals chart on E-49 does not. | P16: 2.26 | R16: =IF(7<=INT(200/C59),AVERAGE(OFFSET($P$10,(7-1)*C59,0,C59,1)),"") -> 3.846
B17: Second, t-tests and confidence intervals on means remain valid with modest samples even when the raw data | P17: 1.42 | R17: =IF(8<=INT(200/C59),AVERAGE(OFFSET($P$10,(8-1)*C59,0,C59,1)),"") -> 2.824
B18: is not normal, because they concern the mean rather than the individual value. | P18: 2.7 | R18: =IF(9<=INT(200/C59),AVERAGE(OFFSET($P$10,(9-1)*C59,0,C59,1)),"") -> 2.972
B19: The theorem does NOT say that your data becomes normal, and it does NOT rescue capability studies: Cpk is | P19: 18.22 | R19: =IF(10<=INT(200/C59),AVERAGE(OFFSET($P$10,(10-1)*C59,0,C59,1)),"") -> 3.512
B20: computed from individual values against specification limits, so the shape of the raw data matters there. | P20: 17.34 | R20: =IF(11<=INT(200/C59),AVERAGE(OFFSET($P$10,(11-1)*C59,0,C59,1)),"") -> 3.974
B21: The simulation below uses 200 deliberately skewed values. Change the sample size and watch the means tighten. | P21: 10.84 | R21: =IF(12<=INT(200/C59),AVERAGE(OFFSET($P$10,(12-1)*C59,0,C59,1)),"") -> 5.412
P22: 2.96 | R22: =IF(13<=INT(200/C59),AVERAGE(OFFSET($P$10,(13-1)*C59,0,C59,1)),"") -> 4.222
B23: BLOCK 3 — WHEN TO USE / WHEN NOT TO USE / ASSUMPTIONS | P23: 1.39 | R23: =IF(14<=INT(200/C59),AVERAGE(OFFSET($P$10,(14-1)*C59,0,C59,1)),"") -> 5.582
B24: WHEN TO USE IT | E24: WHEN NOT TO USE IT | P24: 3.72 | R24: =IF(15<=INT(200/C59),AVERAGE(OFFSET($P$10,(15-1)*C59,0,C59,1)),"") -> 7.716
B25: ✓ Justifying an Xbar chart on skewed data such as time to failure or downtime duration. | E25: ✗ Does not justify a capability study on non-normal individual data: use E-58. | P25: 1.75 | R25: =IF(16<=INT(200/C59),AVERAGE(OFFSET($P$10,(16-1)*C59,0,C59,1)),"") -> 4.622
B26: ✓ Explaining why a t-test on 30 observations survives moderate non-normality. | E26: ✗ Does not apply to the Individuals chart, which plots raw values, not means. | P26: 8.71 | R26: =IF(17<=INT(200/C59),AVERAGE(OFFSET($P$10,(17-1)*C59,0,C59,1)),"") -> 5.516
B27: ✓ Teaching why sample size drives the precision of an average. | E27: ✗ Convergence is slow for extremely skewed data; n of 30 is a rule of thumb, not a law. | P27: 1.8 | R27: =IF(18<=INT(200/C59),AVERAGE(OFFSET($P$10,(18-1)*C59,0,C59,1)),"") -> 4.988
P28: 1.82 | R28: =IF(19<=INT(200/C59),AVERAGE(OFFSET($P$10,(19-1)*C59,0,C59,1)),"") -> 3.094
B29: Assumption | C29: How to check it | D29: What to do if it fails | E29: Go to | P29: 1.95 | R29: =IF(20<=INT(200/C59),AVERAGE(OFFSET($P$10,(20-1)*C59,0,C59,1)),"") -> 3.406
B30: Observations are independent | C30: Check that the sampled units are not systematically related | D30: Redesign the sampling; autocorrelation breaks the theorem | E30: E-05 Sampling Strategies and Rational Subgrouping | P30: 7.17 | R30: =IF(21<=INT(200/C59),AVERAGE(OFFSET($P$10,(21-1)*C59,0,C59,1)),"") -> 5.5
B31: Sample size is large enough for the degree of skew | C31: Compare the histogram of means with a normal curve | D31: Increase n, or use a nonparametric method on E-31 | E31: E-31 Nonparametric Tests | P31: 1.56 | R31: =IF(22<=INT(200/C59),AVERAGE(OFFSET($P$10,(22-1)*C59,0,C59,1)),"") -> 3.2
B32: The population variance is finite | C32: True for any physical measurement in packaging | D32: Not a practical concern on a production line | P32: 2.82 | R32: =IF(23<=INT(200/C59),AVERAGE(OFFSET($P$10,(23-1)*C59,0,C59,1)),"") -> 6.392
P33: 4.35 | R33: =IF(24<=INT(200/C59),AVERAGE(OFFSET($P$10,(24-1)*C59,0,C59,1)),"") -> 5.894
B34: BLOCK 4 — FORMULA AND DERIVATION | P34: 1.82 | R34: =IF(25<=INT(200/C59),AVERAGE(OFFSET($P$10,(25-1)*C59,0,C59,1)),"") -> 4.486
B35: For a sample of size n drawn from any population with mean mu and standard deviation sigma: | P35: 5.47 | R35: =IF(26<=INT(200/C59),AVERAGE(OFFSET($P$10,(26-1)*C59,0,C59,1)),"") -> 6.214
B36: mean of the sample means = mu | P36: 1.79 | R36: =IF(27<=INT(200/C59),AVERAGE(OFFSET($P$10,(27-1)*C59,0,C59,1)),"") -> 3.174
B37: standard deviation of sample means = sigma / SQRT(n) <- the standard error | P37: 3.1 | R37: =IF(28<=INT(200/C59),AVERAGE(OFFSET($P$10,(28-1)*C59,0,C59,1)),"") -> 6.59
B38: shape of the sample means -> normal as n increases | P38: 1.27 | R38: =IF(29<=INT(200/C59),AVERAGE(OFFSET($P$10,(29-1)*C59,0,C59,1)),"") -> 4.408
B39: Practical rule of thumb: | P39: 4.29 | R39: =IF(30<=INT(200/C59),AVERAGE(OFFSET($P$10,(30-1)*C59,0,C59,1)),"") -> 2.558
B40: n >= 30 is usually enough for moderately skewed data | P40: 4.01 | R40: =IF(31<=INT(200/C59),AVERAGE(OFFSET($P$10,(31-1)*C59,0,C59,1)),"") -> 2.988
B41: n >= 5 is often enough for mildly skewed data, which is why Xbar-R with n=5 works so well | P41: 3.52 | R41: =IF(32<=INT(200/C59),AVERAGE(OFFSET($P$10,(32-1)*C59,0,C59,1)),"") -> 3
P42: 2.65 | R42: =IF(33<=INT(200/C59),AVERAGE(OFFSET($P$10,(33-1)*C59,0,C59,1)),"") -> 5.592
B43: BLOCK 5 — EXCEL IMPLEMENTATION | P43: 7.73 | R43: =IF(34<=INT(200/C59),AVERAGE(OFFSET($P$10,(34-1)*C59,0,C59,1)),"") -> 4.772
B44: Function used | C44: Syntax | D44: What the arguments mean | P44: 1.32 | R44: =IF(35<=INT(200/C59),AVERAGE(OFFSET($P$10,(35-1)*C59,0,C59,1)),"") -> 3.608
B45: AVERAGE | C45: AVERAGE(range) | D45: Computes each sample mean | P45: 2.38 | R45: =IF(36<=INT(200/C59),AVERAGE(OFFSET($P$10,(36-1)*C59,0,C59,1)),"") -> 7.334
B46: OFFSET | C46: OFFSET(anchor, rows, cols, height, width) | D46: Selects the block of n consecutive raw values that forms one sample | P46: 1.36 | R46: =IF(37<=INT(200/C59),AVERAGE(OFFSET($P$10,(37-1)*C59,0,C59,1)),"") -> 5.682
B47: STDEV | C47: STDEV(range) | D47: Standard deviation of the raw data and of the sample means | P47: 1.41 | R47: =IF(38<=INT(200/C59),AVERAGE(OFFSET($P$10,(38-1)*C59,0,C59,1)),"") -> 7.876
B48: COUNTIFS | C48: COUNTIFS(range,">="&lo, range,"<"&hi) | D48: Builds both histograms from the same bin edges | P48: 1.34 | R48: =IF(39<=INT(200/C59),AVERAGE(OFFSET($P$10,(39-1)*C59,0,C59,1)),"") -> 2.704
B49: INT | C49: INT(number) | D49: Number of complete samples available: INT(200 / n) | P49: 7.63 | R49: =IF(40<=INT(200/C59),AVERAGE(OFFSET($P$10,(40-1)*C59,0,C59,1)),"") -> 2.082
B50: IF | C50: IF(test, value_if_true, "") | D50: Leaves the cell blank when fewer samples are available | P50: 1.22
B51: Legacy function names are used throughout (STDEV, TDIST, NORMSDIST). They are accepted by every Excel version and by LibreOffice, and they avoid the unresolved-function name-resolution errors produced by the newer dotted names on some engines. | P51: 3.78
P52: 3.29
B53: BLOCK 6 — WORKED EXAMPLE (INTERACTIVE) | P53: 3.33
B54: Two hundred simulated downtime durations in minutes, deliberately right skewed, exactly the shape of | P54: 3.24
B55: real micro-stop data. The values are static so the sheet does not change every time it recalculates. | P55: 2.57
B56: Change only the sample size in the yellow cell and compare the two histograms. | P56: 6.53
B57: YELLOW = overwrite with your data | C57: GREEN = calculated automatically | P57: 4.81
P58: 2.11
B59: Sample size n (drives everything below) | C59: 5 | P59: 1.54
P60: 5.69
B61: The 200 raw values sit in column P and the sample means in column R, to the right of this block. | P61: 2.96
P62: 1.54
B63: Complete samples available | C63: =INT(200/C59) -> 40 | P63: 2.23
B64: Mean of the raw data (min) | C64: =AVERAGE($P$10:$P$209) -> 4.5876 | P64: 7.45
B65: StDev of the raw data (min) | C65: =STDEV($P$10:$P$209) -> 3.538594 | P65: 3.13
B66: Skewness of the raw data | C66: =SKEW($P$10:$P$209) -> 1.8563853 | P66: 1.8
B67: Mean of the sample means (min) | C67: =AVERAGE($R$10:$R$49) -> 4.5876 | P67: 6.76
B68: StDev of the sample means (min) | C68: =STDEV($R$10:$R$49) -> 1.5531891 | P68: 2.19
B69: Skewness of the sample means | C69: =SKEW($R$10:$R$49) -> 0.46047162 | P69: 13.18
B70: Predicted StDev of means = s / SQRT(n) | C70: =C65/SQRT(C59) -> 1.5825073 | P70: 7.37
B71: Observed divided by predicted | C71: =IFERROR(C68/C70,0) -> 0.98147354 | P71: 1.71
B72: Skewness reduction achieved | C72: =IFERROR(1-ABS(C69)/ABS(C66),0) -> 0.75195256 | P72: 3.08
P73: 1.93
B74: TWO HISTOGRAMS, SAME BIN EDGES | P74: 7.02
B75: Bin (min) | C75: Lower | D75: Upper | E75: Raw count | F75: Mean count | P75: 5.75
B76: =TEXT(C76,"0.0")&" - "&TEXT(D76,"0.0") -> 1.2 - 2.8 | C76: =MIN($P$10:$P$209)+(0)*(MAX($P$10:$P$209)-MIN($P$10:$P$209))/12 -> 1.21 | D76: =MIN($P$10:$P$209)+(1)*(MAX($P$10:$P$209)-MIN($P$10:$P$209))/12 -> 2.8441667 | E76: =COUNTIFS($P$10:$P$209,">="&C76,$P$10:$P$209,"<"&D76) -> 80 | F76: =COUNTIFS($R$10:$R$49,">="&C76,$R$10:$R$49,"<"&D76) -> 4 | P76: 7.95
B77: =TEXT(C77,"0.0")&" - "&TEXT(D77,"0.0") -> 2.8 - 4.5 | C77: =MIN($P$10:$P$209)+(1)*(MAX($P$10:$P$209)-MIN($P$10:$P$209))/12 -> 2.8441667 | D77: =MIN($P$10:$P$209)+(2)*(MAX($P$10:$P$209)-MIN($P$10:$P$209))/12 -> 4.4783333 | E77: =COUNTIFS($P$10:$P$209,">="&C77,$P$10:$P$209,"<"&D77) -> 47 | F77: =COUNTIFS($R$10:$R$49,">="&C77,$R$10:$R$49,"<"&D77) -> 16 | P77: 3.64
B78: =TEXT(C78,"0.0")&" - "&TEXT(D78,"0.0") -> 4.5 - 6.1 | C78: =MIN($P$10:$P$209)+(2)*(MAX($P$10:$P$209)-MIN($P$10:$P$209))/12 -> 4.4783333 | D78: =MIN($P$10:$P$209)+(3)*(MAX($P$10:$P$209)-MIN($P$10:$P$209))/12 -> 6.1125 | E78: =COUNTIFS($P$10:$P$209,">="&C78,$P$10:$P$209,"<"&D78) -> 23 | F78: =COUNTIFS($R$10:$R$49,">="&C78,$R$10:$R$49,"<"&D78) -> 13 | P78: 4.4
B79: =TEXT(C79,"0.0")&" - "&TEXT(D79,"0.0") -> 6.1 - 7.7 | C79: =MIN($P$10:$P$209)+(3)*(MAX($P$10:$P$209)-MIN($P$10:$P$209))/12 -> 6.1125 | D79: =MIN($P$10:$P$209)+(4)*(MAX($P$10:$P$209)-MIN($P$10:$P$209))/12 -> 7.7466667 | E79: =COUNTIFS($P$10:$P$209,">="&C79,$P$10:$P$209,"<"&D79) -> 19 | F79: =COUNTIFS($R$10:$R$49,">="&C79,$R$10:$R$49,"<"&D79) -> 6 | P79: 6.17
B80: =TEXT(C80,"0.0")&" - "&TEXT(D80,"0.0") -> 7.7 - 9.4 | C80: =MIN($P$10:$P$209)+(4)*(MAX($P$10:$P$209)-MIN($P$10:$P$209))/12 -> 7.7466667 | D80: =MIN($P$10:$P$209)+(5)*(MAX($P$10:$P$209)-MIN($P$10:$P$209))/12 -> 9.3808333 | E80: =COUNTIFS($P$10:$P$209,">="&C80,$P$10:$P$209,"<"&D80) -> 14 | F80: =COUNTIFS($R$10:$R$49,">="&C80,$R$10:$R$49,"<"&D80) -> 1 | P80: 8.03
B81: =TEXT(C81,"0.0")&" - "&TEXT(D81,"0.0") -> 9.4 - 11.0 | C81: =MIN($P$10:$P$209)+(5)*(MAX($P$10:$P$209)-MIN($P$10:$P$209))/12 -> 9.3808333 | D81: =MIN($P$10:$P$209)+(6)*(MAX($P$10:$P$209)-MIN($P$10:$P$209))/12 -> 11.015 | E81: =COUNTIFS($P$10:$P$209,">="&C81,$P$10:$P$209,"<"&D81) -> 5 | F81: =COUNTIFS($R$10:$R$49,">="&C81,$R$10:$R$49,"<"&D81) -> 0 | P81: 11.47
B82: =TEXT(C82,"0.0")&" - "&TEXT(D82,"0.0") -> 11.0 - 12.6 | C82: =MIN($P$10:$P$209)+(6)*(MAX($P$10:$P$209)-MIN($P$10:$P$209))/12 -> 11.015 | D82: =MIN($P$10:$P$209)+(7)*(MAX($P$10:$P$209)-MIN($P$10:$P$209))/12 -> 12.649167 | E82: =COUNTIFS($P$10:$P$209,">="&C82,$P$10:$P$209,"<"&D82) -> 3 | F82: =COUNTIFS($R$10:$R$49,">="&C82,$R$10:$R$49,"<"&D82) -> 0 | P82: 15.11
B83: =TEXT(C83,"0.0")&" - "&TEXT(D83,"0.0") -> 12.6 - 14.3 | C83: =MIN($P$10:$P$209)+(7)*(MAX($P$10:$P$209)-MIN($P$10:$P$209))/12 -> 12.649167 | D83: =MIN($P$10:$P$209)+(8)*(MAX($P$10:$P$209)-MIN($P$10:$P$209))/12 -> 14.283333 | E83: =COUNTIFS($P$10:$P$209,">="&C83,$P$10:$P$209,"<"&D83) -> 3 | F83: =COUNTIFS($R$10:$R$49,">="&C83,$R$10:$R$49,"<"&D83) -> 0 | P83: 1.6
B84: =TEXT(C84,"0.0")&" - "&TEXT(D84,"0.0") -> 14.3 - 15.9 | C84: =MIN($P$10:$P$209)+(8)*(MAX($P$10:$P$209)-MIN($P$10:$P$209))/12 -> 14.283333 | D84: =MIN($P$10:$P$209)+(9)*(MAX($P$10:$P$209)-MIN($P$10:$P$209))/12 -> 15.9175 | E84: =COUNTIFS($P$10:$P$209,">="&C84,$P$10:$P$209,"<"&D84) -> 2 | F84: =COUNTIFS($R$10:$R$49,">="&C84,$R$10:$R$49,"<"&D84) -> 0 | P84: 2.37
B85: =TEXT(C85,"0.0")&" - "&TEXT(D85,"0.0") -> 15.9 - 17.6 | C85: =MIN($P$10:$P$209)+(9)*(MAX($P$10:$P$209)-MIN($P$10:$P$209))/12 -> 15.9175 | D85: =MIN($P$10:$P$209)+(10)*(MAX($P$10:$P$209)-MIN($P$10:$P$209))/12 -> 17.551667 | E85: =COUNTIFS($P$10:$P$209,">="&C85,$P$10:$P$209,"<"&D85) -> 2 | F85: =COUNTIFS($R$10:$R$49,">="&C85,$R$10:$R$49,"<"&D85) -> 0 | P85: 2.32
B86: =TEXT(C86,"0.0")&" - "&TEXT(D86,"0.0") -> 17.6 - 19.2 | C86: =MIN($P$10:$P$209)+(10)*(MAX($P$10:$P$209)-MIN($P$10:$P$209))/12 -> 17.551667 | D86: =MIN($P$10:$P$209)+(11)*(MAX($P$10:$P$209)-MIN($P$10:$P$209))/12 -> 19.185833 | E86: =COUNTIFS($P$10:$P$209,">="&C86,$P$10:$P$209,"<"&D86) -> 1 | F86: =COUNTIFS($R$10:$R$49,">="&C86,$R$10:$R$49,"<"&D86) -> 0 | P86: 1.7
B87: =TEXT(C87,"0.0")&" - "&TEXT(D87,"0.0") -> 19.2 - 20.8 | C87: =MIN($P$10:$P$209)+(11)*(MAX($P$10:$P$209)-MIN($P$10:$P$209))/12 -> 19.185833 | D87: =MIN($P$10:$P$209)+(12)*(MAX($P$10:$P$209)-MIN($P$10:$P$209))/12 -> 20.82 | E87: =COUNTIFS($P$10:$P$209,">="&C87,$P$10:$P$209,"<="&D87) -> 1 | F87: =COUNTIFS($R$10:$R$49,">="&C87,$R$10:$R$49,"<="&D87) -> 0 | P87: 8.46
P88: 3.31
B89: BLOCK 7 — DECISION RULE AND INTERPRETATION | P89: 7.32
B90: VERDICT | C90: =IF(AND(ABS(C69)<0.5,C72>0.4),"CLT DEMONSTRATED - the raw data is strongly skewed yet the sample means are close to symmetric",IF(C59<5,"SAMPLE TOO SMALL - increase n; convergence is slow for data this skewed","PARTIAL CONVERGENCE - the means are tighter than the raw data but skew remains; increase n")) -> CLT DEMONSTRATED - the raw data is strongly skewed yet the sample means are close to symmetric | P90: 8.64
P91: 1.22
B92: Criterion | C92: Numeric rule | D92: What it means in practice | P92: 3.78
B93: Skewness of raw data | C93: Around 1.5 to 2 here | D93: Typical of downtime and time-to-failure data | P93: 5.22
B94: Skewness of the means | C94: |skew| < 0.5 | D94: Close enough to symmetric for normal theory on the mean | P94: 8.72
B95: StDev of means vs s/SQRT(n) | C95: Ratio close to 1 | D95: Confirms the standard error formula empirically | P95: 9.57
B96: Sample size | C96: n >= 30 for strong skew, n >= 5 for mild | D96: The rule of thumb, not a guarantee | P96: 6.38
P97: 5.45
B98: COMMON MISTAKES | P98: 1.98
B99: • Claiming the CLT makes the raw data normal. It does not; only the distribution of the means changes. | P99: 1.56
B100: • Using the CLT to justify a capability study. Cpk compares individual values with specification limits, so the shape of the raw data is exactly what matters there. Use E-58 instead. | P100: 1.55
B101: • Applying it to an Individuals chart. The I chart plots single values, so it enjoys no CLT protection. | P101: 1.34
...

Sheet E-09 t Chi2 F Distributions
A1: Made by Jose Zapatero, jmazsantos@gmail.com
B2: E-09 — The t, Chi-Square and F Distributions | K2: MEASURE
B3: ← Back to Index | D3: Phase: MEASURE | Data required: Degrees of freedom, alpha | Min. sample: n/a | Complexity: 3/5 | Typical output: Critical values and tail areas
B5: BLOCK 1 — QUICK CARD
B6: What question does this answer? | C6: Which reference distribution does my test use, and what is its critical value?
B7: When you would reach for it | C7: Whenever a test statistic must be compared with a table value, or a p-value interpreted.
B8: What it gives you | C8: Critical values and tail areas for the t, chi-square and F distributions.
B10: BLOCK 2 — CONCEPT
B11: Three distributions carry almost all of classical inference, and each answers a different question.
B12: The t distribution handles means when sigma is unknown. It looks like the normal curve but with heavier tails, because estimating sigma from the data adds uncertainty. With 5 degrees of freedom the two-sided 5% critical value is 2.57 rather than 1.96; by 30 degrees of freedom it is 2.04, and it converges to 1.96 as df grows.
B15: The chi-square distribution handles variances and counts. It is skewed right and bounded at zero, because a sum of squares cannot be negative. It drives variance confidence intervals and contingency table tests.
B17: The F distribution handles ratios of two variances, which is why it appears in ANOVA and in tests for equality of spread. It has two separate degrees of freedom, numerator and denominator, and the order matters.
B19: Degrees of freedom are simply the number of independent pieces of information left after estimating parameters.
B20: With n observations and one estimated mean, n - 1 remain.
B22: BLOCK 3 — WHEN TO USE / WHEN NOT TO USE / ASSUMPTIONS
B23: WHEN TO USE IT | E23: WHEN NOT TO USE IT
B24: ✓ Looking up a critical value without a printed table. | E24: ✗ Not a test in itself; it supplies the reference values other sheets consume.
B25: ✓ Checking a p-value reported by software. | E25: ✗ Do not use the t distribution when sigma is genuinely known: the normal applies.
B26: ✓ Understanding why a small sample needs a larger test statistic to reach significance. | E26: ✗ The F test for variances is very sensitive to non-normality; prefer Levene on E-28.
B27: ✓ Teaching the link between degrees of freedom and test sensitivity.
B29: Assumption | C29: How to check it | D29: What to do if it fails | E29: Go to
B30: Degrees of freedom are correctly counted | C30: n - 1 for one sample, n1 + n2 - 2 for pooled two-sample, k - 1 and N - k for ANOVA | D30: Recount; the wrong df silently produces the wrong p-value | E30: E-26 One-Way ANOVA with Tukey HSD
B31: The underlying data is approximately normal | C31: Probability plot on E-32 | D31: Chi-square and F are far less robust than t; switch to E-31 | E31: E-32 Normality Testing and Probability Plots
B32: The correct tail is being used | C32: Ask whether the alternative hypothesis is directional | D32: Halve or double the probability as appropriate | E32: E-17 The Hypothesis Testing Framework
B34: BLOCK 4 — FORMULA AND DERIVATION
B35: t distribution:
B36: t = (xbar - mu) / (s / SQRT(n)), df = n - 1
B37: Chi-square distribution:
B38: chi2 = (n - 1) * s^2 / sigma0^2, df = n - 1
B39: F distribution:
B40: F = s1^2 / s2^2, df1 = n1 - 1 (numerator), df2 = n2 - 1 (denominator)
B41: Relationships worth remembering:
B42: t^2 with df = F with (1, df) t with df -> infinity becomes the standard normal chi2 with df = 1 is the square of a standard normal variable
B45: BLOCK 5 — EXCEL IMPLEMENTATION
B46: Function used | C46: Syntax | D46: What the arguments mean
B47: TINV | C47: TINV(probability, df) | D47: TWO-TAILED critical t. For one tail use TINV(2*alpha, df)
B48: TDIST | C48: TDIST(t, df, tails) | D48: Tail area; t must be positive, tails is 1 or 2
B49: CHIINV | C49: CHIINV(probability, df) | D49: The chi-square value with that area in the RIGHT tail
B50: CHIDIST | C50: CHIDIST(x, df) | D50: Right tail area above x
B51: FINV | C51: FINV(probability, df1, df2) | D51: The F value with that area in the right tail
B52: FDIST | C52: FDIST(x, df1, df2) | D52: Right tail area above x
B53: NORMSINV | C53: NORMSINV(probability) | D53: Normal quantile, shown for comparison with t
B54: Legacy function names are used throughout (STDEV, TDIST, NORMSDIST). They are accepted by every Excel version and by LibreOffice, and they avoid the unresolved-function name-resolution errors produced by the newer dotted names on some engines.
B56: BLOCK 6 — WORKED EXAMPLE (INTERACTIVE)
B57: Set the degrees of freedom and alpha for the test you are running and read the critical values.
B58: The comparison table at the bottom shows how the t critical value converges on 1.96 as df grows.
B59: YELLOW = overwrite with your data | C59: GREEN = calculated automatically
B61: Significance level alpha | C61: 0.05
B62: Degrees of freedom df1 (numerator) | C62: 12
B63: Degrees of freedom df2 (denominator) | C63: 15
B64: Observed t (for the tail area) | C64: 2.31
B65: Observed chi-square | C65: 21.4
B66: Observed F | C66: 2.85
B68: t critical, two-tailed | C68: =TINV(C61,C62) -> 2.1788128
B69: t critical, one-tailed | C69: =TINV(2*C61,C62) -> 1.7822876
B70: Normal critical, two-tailed | C70: =NORMSINV(1-C61/2) -> 1.959964
B71: p-value for the observed t (two-tailed) | C71: =TDIST(ABS(C64),C62,2) -> 0.039476198
B72: Chi-square critical, upper tail | C72: =CHIINV(C61,C62) -> 21.02607
B73: Chi-square critical, lower tail | C73: =CHIINV(1-C61,C62) -> 5.2260295
B74: p-value for the observed chi-square | C74: =CHIDIST(C65,C62) -> 0.044821071
B75: F critical, upper tail | C75: =FINV(C61,C62,C63) -> 2.475313
B76: p-value for the observed F | C76: =FDIST(C66,C62,C63) -> 0.02923961
B78: HOW t CONVERGES ON THE NORMAL
B79: df | C79: t critical (two-tailed) | D79: Normal critical | E79: Excess over normal
B80: 2 | C80: =TINV(C61,2) -> 4.3026527 | D80: =NORMSINV(1-C61/2) -> 1.959964 | E80: =C80/D80-1 -> 1.1952713
B81: 5 | C81: =TINV(C61,5) -> 2.5705818 | D81: =NORMSINV(1-C61/2) -> 1.959964 | E81: =C81/D81-1 -> 0.31154544
B82: 10 | C82: =TINV(C61,10) -> 2.2281389 | D82: =NORMSINV(1-C61/2) -> 1.959964 | E82: =C82/D82-1 -> 0.13682643
B83: 15 | C83: =TINV(C61,15) -> 2.1314495 | D83: =NORMSINV(1-C61/2) -> 1.959964 | E83: =C83/D83-1 -> 0.087494241
B84: 20 | C84: =TINV(C61,20) -> 2.0859634 | D84: =NORMSINV(1-C61/2) -> 1.959964 | E84: =C84/D84-1 -> 0.064286621
B85: 30 | C85: =TINV(C61,30) -> 2.0422725 | D85: =NORMSINV(1-C61/2) -> 1.959964 | E85: =C85/D85-1 -> 0.04199489
B86: 60 | C86: =TINV(C61,60) -> 2.0002978 | D86: =NORMSINV(1-C61/2) -> 1.959964 | E86: =C86/D86-1 -> 0.020578867
B87: 120 | C87: =TINV(C61,120) -> 1.9799304 | D87: =NORMSINV(1-C61/2) -> 1.959964 | E87: =C87/D87-1 -> 0.010187136
B88: 1000 | C88: =TINV(C61,1000) -> 1.9623391 | D88: =NORMSINV(1-C61/2) -> 1.959964 | E88: =C88/D88-1 -> 0.0012118061
B90: BLOCK 7 — DECISION RULE AND INTERPRETATION
B91: VERDICT | C91: =IF(C71<C61,"OBSERVED t IS SIGNIFICANT at the chosen alpha","OBSERVED t IS NOT SIGNIFICANT at the chosen alpha - check the power on E-19 before concluding no effect") -> OBSERVED t IS SIGNIFICANT at the chosen alpha
B93: Criterion | C93: Numeric rule | D93: What it means in practice
B94: t critical at df = 5 | C94: About 2.57 | D94: A small sample demands a much larger effect to reach significance
B95: t critical at df = 30 | C95: About 2.04 | D95: Close to the normal 1.96; the penalty for estimating sigma has faded
B96: Chi-square | C96: Skewed right, bounded at zero | D96: Two different critical values are needed for a two-sided interval
B97: F | C97: Order of df matters | D97: F(12,15) is not F(15,12); the numerator is always the first argument
B99: COMMON MISTAKES
B100: • Using TINV as if it were one-tailed. In Excel TINV is two-tailed; for one tail use TINV(2*alpha, df).
B101: • Feeding a negative t into TDIST. It requires a positive value, so wrap it in ABS.
B102: • Swapping the numerator and denominator degrees of freedom in FINV.
B103: • Using a chi-square upper critical value for a two-sided variance interval and forgetting the lower one.
B104: • Treating df as the sample size. With one sample of 25 the df is 24, not 25.
B106: BLOCK 8 — SELF-CHECK
B107: Answer in your head, then select the cell in column N on the same row to reveal the answer (the text is white, not hidden). | N107: ANSWERS → select the cell to read the white text
B108: Q1. Why does the t distribution have heavier tails than the normal distribution? | N108: A1. Because sigma is estimated from the same small sample rather than known. That extra uncertainty makes extreme values of the statistic more likely, which widens the tails. As df grows, s becomes a reliable estimate of sigma and the t converges on the normal.
B109: Q2. In Excel, what does TINV(0.05, 20) return, and what would you use for a one-tailed test at 5%? | N109: A2. TINV(0.05, 20) returns 2.086, the TWO-tailed critical value. For a one-tailed test at 5% you need TINV(0.10, 20), which returns 1.725.
B110: Q3. You are comparing the variance of shift A with that of shift B, with 15 and 20 observations. What are the degrees of freedom for the F test? | N110: A3. df1 = 14 for the numerator and df2 = 19 for the denominator, taking A as the numerator. If you swap the shifts you must swap the degrees of freedom as well.
B112: BLOCK 9 — RELATED SHEETS
B113: Previous tool | C113: Next tool | D113: Printed tables
B114: E-08 Central Limit Theorem (Live Simulation) | C114: E-10 Binomial Distribution (Defective Units) | D114: U-01 Z, t, Chi-Square and F Tables

Sheet E-10 Binomial Distribution
A1: Made by Jose Zapatero, jmazsantos@gmail.com
B2: E-10 — Binomial Distribution (Defective Units) | K2: MEASURE
B3: ← Back to Index | D3: Phase: MEASURE | Data required: n, p, x | Min. sample: n/a | Complexity: 2/5 | Typical output: Binomial probabilities and cumulative curve
B5: BLOCK 1 — QUICK CARD
B6: What question does this answer? | C6: What is the chance of finding exactly x defective bottles in a sample of n?
B7: When you would reach for it | C7: When the outcome per unit is pass or fail and you sample a fixed number of units.
B8: What it gives you | C8: Exact probabilities, the mean and variance of the count, and a sampling plan check.
B10: BLOCK 2 — CONCEPT
B11: The binomial distribution counts successes in a fixed number of independent trials, each with the same probability. On the line that means defective bottles in a sample of n, leaking kegs in a batch, or pallets failing a wrap test out of a shift's production.
B14: Four conditions define it: a fixed number of trials, two possible outcomes per trial, a constant probability, and independence between trials. The third and fourth are the ones that fail in practice - a filler that starts drifting makes p change during the sample, and consecutive bottles from the same valve are not independent.
B17: The distinction from Poisson matters. Binomial counts defective UNITS out of a known total, and the count can never exceed n. Poisson on E-11 counts DEFECTS, where one unit can carry several and there is no natural maximum.
B19: A bottle either passes or fails the inspector: binomial. A pallet can have three, five or eleven label defects: Poisson.
B20: The binomial also underlies the p and np charts on E-52 and the acceptance sampling logic in any incoming plan.
B22: BLOCK 3 — WHEN TO USE / WHEN NOT TO USE / ASSUMPTIONS
B23: WHEN TO USE IT | E23: WHEN NOT TO USE IT
B24: ✓ Sample of fixed size, each unit passing or failing. | E24: ✗ Do not use when the count has no upper bound: that is Poisson on E-11.
B25: ✓ Assessing the risk that a sampling plan misses a bad lot. | E25: ✗ Not valid when p changes during the sample, for example while the filler is drifting.
B26: ✓ Computing the exact probability behind a p or np chart limit. | E26: ✗ Not valid when units are drawn without replacement from a small lot: that is hypergeometric.
B27: ✓ Small samples where the normal approximation would be unsafe.
B29: Assumption | C29: How to check it | D29: What to do if it fails | E29: Go to
B30: Fixed number of trials n | C30: Confirm the sample size was set before sampling started | D30: If sampling continued until a defect appeared, the model is different | E30: E-05 Sampling Strategies and Rational Subgrouping
B31: Constant probability p across the sample | C31: Plot the defect rate over time on a p chart | D31: Stratify by period; a drifting p invalidates the calculation | E31: E-52 p and np Charts
B32: Independent trials | C32: Check that units do not share a common short-term cause | D32: Use rational subgrouping, or model the overdispersion on E-54 | E32: E-54 Laney p' and u' Charts (Overdispersion)
B34: BLOCK 4 — FORMULA AND DERIVATION
B35: Probability of exactly x successes in n trials:
B36: P(X = x) = C(n, x) * p^x * (1 - p)^(n - x)
B37: where C(n, x) = n! / (x! * (n - x)!)
B38: Moments:
B39: mean = n * p
B40: variance = n * p * (1 - p)
B41: std dev = SQRT(n * p * (1 - p))
B42: Normal approximation is acceptable when:
B43: n*p >= 5 AND n*(1 - p) >= 5
B45: BLOCK 5 — EXCEL IMPLEMENTATION
B46: Function used | C46: Syntax | D46: What the arguments mean
B47: BINOMDIST | C47: BINOMDIST(x, n, p, cumulative) | D47: FALSE gives P(X = x); TRUE gives P(X <= x)
B48: COMBIN | C48: COMBIN(n, x) | D48: The binomial coefficient C(n, x), shown for the derivation
B49: 1 - BINOMDIST | C49: 1 - BINOMDIST(x, n, p, TRUE) | D49: P(X > x), the upper tail
B50: SQRT | C50: SQRT(n*p*(1-p)) | D50: Standard deviation of the count
B51: AND | C51: AND(test1, test2) | D51: Checks both normal approximation conditions at once
B52: Legacy function names are used throughout (STDEV, TDIST, NORMSDIST). They are accepted by every Excel version and by LibreOffice, and they avoid the unresolved-function name-resolution errors produced by the newer dotted names on some engines.
B54: BLOCK 6 — WORKED EXAMPLE (INTERACTIVE)
B55: A sample of 200 bottles is taken from a lot whose true defective rate is 1.5 per cent. What is the chance of finding exactly 5 defectives, at most 5, and more than 5?
B57: YELLOW = overwrite with your data | C57: GREEN = calculated automatically
B59: Sample size n | C59: 200
B60: Probability defective p | C60: 0.015
B61: Number of defectives x | C61: 5
B62: Acceptance number for the sampling plan | C62: 3
B64: P(X = x) exactly x | C64: =BINOMDIST(C61,C59,C60,FALSE()) -> 0.10106727
B65: P(X <= x) at most x | C65: =BINOMDIST(C61,C59,C60,TRUE()) -> 0.9176083
B66: P(X > x) more than x | C66: =1-BINOMDIST(C61,C59,C60,TRUE()) -> 0.082391698
B67: Mean number of defectives n*p | C67: =C59*C60 -> 3
B68: Variance n*p*(1-p) | C68: =C59*C60*(1-C60) -> 2.955
B69: Standard deviation | C69: =SQRT(C68) -> 1.7190113
B70: Probability the lot is accepted | C70: =BINOMDIST(C62,C59,C60,TRUE()) -> 0.64723615
B71: Consumer risk: bad lot accepted | C71: =C70 -> 0.64723615
B72: Normal approximation acceptable? | C72: =IF(AND(C59*C60>=5,C59*(1-C60)>=5),"Yes","No - use the exact binomial") -> No - use the exact binomial
B74: PROBABILITY DISTRIBUTION
B75: x | C75: P(X = x) | D75: P(X <= x)
B76: 0 | C76: =BINOMDIST(B76,C59,C60,FALSE()) -> 0.048668291 | D76: =BINOMDIST(B76,C59,C60,TRUE()) -> 0.048668291
B77: 1 | C77: =BINOMDIST(B77,C59,C60,FALSE()) -> 0.1482283 | D77: =BINOMDIST(B77,C59,C60,TRUE()) -> 0.19689659
B78: 2 | C78: =BINOMDIST(B78,C59,C60,FALSE()) -> 0.22459973 | D78: =BINOMDIST(B78,C59,C60,TRUE()) -> 0.42149632
B79: 3 | C79: =BINOMDIST(B79,C59,C60,FALSE()) -> 0.22573983 | D79: =BINOMDIST(B79,C59,C60,TRUE()) -> 0.64723615
B80: 4 | C80: =BINOMDIST(B80,C59,C60,FALSE()) -> 0.16930487 | D80: =BINOMDIST(B80,C59,C60,TRUE()) -> 0.81654103
B81: 5 | C81: =BINOMDIST(B81,C59,C60,FALSE()) -> 0.10106727 | D81: =BINOMDIST(B81,C59,C60,TRUE()) -> 0.9176083
B82: 6 | C82: =BINOMDIST(B82,C59,C60,FALSE()) -> 0.050020606 | D82: =BINOMDIST(B82,C59,C60,TRUE()) -> 0.96762891
B83: 7 | C83: =BINOMDIST(B83,C59,C60,FALSE()) -> 0.021110945 | D83: =BINOMDIST(B83,C59,C60,TRUE()) -> 0.98873985
B84: 8 | C84: =BINOMDIST(B84,C59,C60,FALSE()) -> 0.007755861 | D84: =BINOMDIST(B84,C59,C60,TRUE()) -> 0.99649571
B85: 9 | C85: =BINOMDIST(B85,C59,C60,FALSE()) -> 0.0025196706 | D85: =BINOMDIST(B85,C59,C60,TRUE()) -> 0.99901538
B86: 10 | C86: =BINOMDIST(B86,C59,C60,FALSE()) -> 0.0007328788 | D86: =BINOMDIST(B86,C59,C60,TRUE()) -> 0.99974826
B87: 11 | C87: =BINOMDIST(B87,C59,C60,FALSE()) -> 0.00019277384 | D87: =BINOMDIST(B87,C59,C60,TRUE()) -> 0.99994104
B88: 12 | C88: =BINOMDIST(B88,C59,C60,FALSE()) -> 4.6236366e-05 | D88: =BINOMDIST(B88,C59,C60,TRUE()) -> 0.99998727
B89: 13 | C89: =BINOMDIST(B89,C59,C60,FALSE()) -> 1.0182472e-05 | D89: =BINOMDIST(B89,C59,C60,TRUE()) -> 0.99999746
B90: 14 | C90: =BINOMDIST(B90,C59,C60,FALSE()) -> 2.0711989e-06 | D90: =BINOMDIST(B90,C59,C60,TRUE()) -> 0.99999953
B91: 15 | C91: =BINOMDIST(B91,C59,C60,FALSE()) -> 3.9110965e-07 | D91: =BINOMDIST(B91,C59,C60,TRUE()) -> 0.99999992
B93: BLOCK 7 — DECISION RULE AND INTERPRETATION
B94: VERDICT | C94: =IF(C70>=0.1,"HIGH CONSUMER RISK - this sampling plan accepts a lot at this defect rate more than one time in ten. Increase n or lower the acceptance number.",IF(C70>=0.05,"MODERATE CONSUMER RISK - acceptable only if the defect is not safety related","LOW CONSUMER RISK - the plan discriminates adequately at this defect rate")) -> HIGH CONSUMER RISK - this sampling plan accepts a lot at this defect rate more than one time in ten. Increase n or lower the acceptance number.
B96: Criterion | C96: Numeric rule | D96: What it means in practice
B97: Consumer risk (beta) | C97: Below 10% | D97: Standard target for a lot at the rejectable quality level
B98: Normal approximation | C98: n*p >= 5 and n*(1-p) >= 5 | D98: Below this, use exact binomial probabilities
B99: Mean count | C99: n*p | D99: If n*p is under 1, most samples will contain no defectives at all
B100: Variance versus mean | C100: Variance is always smaller than the mean | D100: If the observed variance exceeds the mean, the binomial model is wrong: see overdispersion on E-54
B102: COMMON MISTAKES
B103: • Using the binomial when one unit can carry several defects. That is Poisson.
B104: • Assuming a sample of 200 with p = 0.015 will 'usually' catch a problem. The mean count is only 3, so a clean sample is entirely ordinary and proves nothing.
B105: • Applying the normal approximation when n*p is below 5. The error in the tail is large exactly where the decision is made.
B106: • Sampling 200 consecutive bottles from one valve and treating them as 200 independent trials.
B107: • Forgetting that a sampling plan has two risks: the producer risk of rejecting a good lot, and the consumer risk of accepting a bad one.
B109: BLOCK 8 — SELF-CHECK
B110: Answer in your head, then select the cell in column N on the same row to reveal the answer (the text is white, not hidden). | N110: ANSWERS → select the cell to read the white text
B111: Q1. A lot is 1.5% defective and you sample 200 bottles. On average how many defectives will you find, and what is the chance of finding none? | N111: A1. The mean is n*p = 3 defectives. The probability of none is 0.985 raised to the power 200, which is about 4.8%. So finding a clean sample happens roughly one time in twenty even at this defect rate.
B112: Q2. What is the practical difference between the binomial and the Poisson model on a packaging line? | N112: A2. Binomial counts defective units out of a known sample size, so the count is bounded by n. Poisson counts defects, where a single unit can carry several and there is no natural upper bound. Bottles rejected by the inspector are binomial; label defects per pallet are Poisson.
B113: Q3. Your observed variance in defective counts is much larger than n*p*(1-p). What does that indicate? | N113: A3. Overdispersion: the assumption of a constant p across the sample is failing, usually because the defect rate drifts between subgroups or the units are not independent. A standard p chart will then flag constantly; use the Laney p prime chart on E-54.
B115: BLOCK 9 — RELATED SHEETS
B116: Previous tool | C116: Next tool | D116: Alternative if assumptions fail
B117: E-09 The t, Chi-Square and F Distributions | C117: E-11 Poisson Distribution (Defects per Unit) | D117: E-52 p and np Charts

Sheet E-11 Poisson Distribution
A1: Made by Jose Zapatero, jmazsantos@gmail.com
B2: E-11 — Poisson Distribution (Defects per Unit) | K2: MEASURE
B3: ← Back to Index | D3: Phase: MEASURE | Data required: Mean rate, exposure | Min. sample: n/a | Complexity: 2/5 | Typical output: Poisson probabilities and rate comparison
B5: BLOCK 1 — QUICK CARD
B6: What question does this answer? | C6: What is the chance of x micro-stops in a shift, and did the stop rate really change?
B7: When you would reach for it | C7: When counting events over a period or an area, with no natural upper bound.
B8: What it gives you | C8: Poisson probabilities, plus a formal two-rate comparison between shifts.
B10: BLOCK 2 — CONCEPT
B11: The Poisson distribution counts events in a fixed exposure: stops per shift, label defects per pallet, leaks per hundred kegs, near misses per month. Unlike the binomial there is no fixed number of trials and no natural maximum; a pallet can carry any number of label defects.
B14: It has one parameter only, lambda, which is both the mean and the variance. That single fact is the most useful diagnostic in the whole sheet: if your observed variance is much larger than your observed mean, the events are not occurring independently at a constant rate. Something is clustering them.
B17: On a packaging line that clustering is almost always real and worth finding: a bearing beginning to fail produces stops in bursts, not at a constant rate, and the excess variance is the first statistical signal.
B19: Exposure must be constant or explicitly accounted for. Comparing 96 stops in 8 shifts with 72 stops in 6 shifts requires rates, not counts, which is exactly what the comparison block below does.
B22: BLOCK 3 — WHEN TO USE / WHEN NOT TO USE / ASSUMPTIONS
B23: WHEN TO USE IT | E23: WHEN NOT TO USE IT
B24: ✓ Counting events per shift, per pallet, per thousand bottles or per month. | E24: ✗ Do not use when the count is bounded by a known sample size: that is binomial on E-10.
B25: ✓ Setting the centre line of a c or u chart on E-53. | E25: ✗ Not valid when events cluster, which shows up as variance far above the mean.
B26: ✓ Comparing the stop rate of two shifts or two machines over different exposures. | E26: ✗ Not appropriate when the exposure varies and has not been normalised into a rate.
B27: ✓ Estimating how often a rare event should occur if nothing has changed.
B29: Assumption | C29: How to check it | D29: What to do if it fails | E29: Go to
B30: Events occur independently | C30: Compare the observed variance with the observed mean | D30: If variance is much larger, investigate the clustering; use E-54 for the chart | E30: E-54 Laney p' and u' Charts (Overdispersion)
B31: Constant rate over the exposure | C31: Plot the count over time on a c or u chart | D31: Split the period; a rate that changes mid-shift breaks the model | E31: E-53 c and u Charts
B32: Exposure is correctly defined and measured | C32: Confirm what one unit of exposure is: a shift, a pallet, a thousand bottles | D32: Normalise counts into rates before any comparison | E32: E-53 c and u Charts
B34: BLOCK 4 — FORMULA AND DERIVATION
B35: Probability of exactly x events when the mean is lambda:
B36: P(X = x) = EXP(-lambda) * lambda^x / x!
B37: Moments - the defining property:
B38: mean = variance = lambda
B39: Comparing two rates with counts c1, c2 over exposures t1, t2:
B40: r1 = c1 / t1 r2 = c2 / t2
B41: Z = (r1 - r2) / SQRT( c1/t1^2 + c2/t2^2 )
B42: p = 2 * (1 - NORMSDIST(ABS(Z)))
B43: Dispersion check:
B44: observed variance / observed mean should be close to 1
B46: BLOCK 5 — EXCEL IMPLEMENTATION
B47: Function used | C47: Syntax | D47: What the arguments mean
B48: POISSON | C48: POISSON(x, mean, cumulative) | D48: FALSE gives P(X = x); TRUE gives P(X <= x)
B49: 1 - POISSON | C49: 1 - POISSON(x-1, mean, TRUE) | D49: P(X >= x), the upper tail including x
B50: EXP | C50: EXP(number) | D50: Used in the derivation of the probability mass function
B51: NORMSDIST | C51: NORMSDIST(z) | D51: Converts the two-rate Z statistic into a p-value
B52: SQRT | C52: SQRT(number) | D52: Standard error of the difference between two rates
B53: Legacy function names are used throughout (STDEV, TDIST, NORMSDIST). They are accepted by every Excel version and by LibreOffice, and they avoid the unresolved-function name-resolution errors produced by the newer dotted names on some engines.
B55: BLOCK 6 — WORKED EXAMPLE (INTERACTIVE)
B56: The Innopal palletiser averages 12 micro-stops per shift. Last night shift C recorded 18. Is that unusual? And over the last eight shifts, does shift A genuinely stop more often than shift B?
B58: YELLOW = overwrite with your data | C58: GREEN = calculated automatically
B60: Mean events per exposure lambda | C60: 12
B61: Observed count x | C61: 18
B63: P(X = x) exactly x | C63: =POISSON(C61,C60,FALSE()) -> 0.025549807
B64: P(X <= x) at most x | C64: =POISSON(C61,C60,TRUE()) -> 0.96258351
B65: P(X >= x) x or more | C65: =1-POISSON(C61-1,C60,TRUE()) -> 0.062966297
B66: Standard deviation SQRT(lambda) | C66: =SQRT(C60) -> 3.4641016
B67: Upper 3 sigma limit for a c chart | C67: =C60+3*SQRT(C60) -> 22.392305
B68: Lower 3 sigma limit for a c chart | C68: =MAX(0,C60-3*SQRT(C60)) -> 1.6076952
B70: COMPARING TWO SHIFTS
B71: Shift A - total stops | C71: 96
B72: Shift A - number of shifts | C72: 8
B73: Shift B - total stops | C73: 60
B74: Shift B - number of shifts | C74: 8
B75: Significance level alpha | C75: 0.05
B76: Shift A rate (stops per shift) | C76: =C71/C72 -> 12
B77: Shift B rate (stops per shift) | C77: =C73/C74 -> 7.5
B78: Rate ratio A / B | C78: =IFERROR(C76/C77,0) -> 1.6
B79: Z statistic | C79: =IFERROR((C76-C77)/SQRT(C71/C72^2+C73/C74^2),0) -> 2.8823068
B80: p-value (two-sided) | C80: =2*(1-NORMSDIST(ABS(C79))) -> 0.0039477519
B82: PROBABILITY DISTRIBUTION
B83: x | C83: P(X = x) | D83: P(X <= x)
B84: 0 | C84: =POISSON(B84,C60,FALSE()) -> 6.1442124e-06 | D84: =POISSON(B84,C60,TRUE()) -> 6.1442124e-06
B85: 1 | C85: =POISSON(B85,C60,FALSE()) -> 7.3730548e-05 | D85: =POISSON(B85,C60,TRUE()) -> 7.9874761e-05
B86: 2 | C86: =POISSON(B86,C60,FALSE()) -> 0.00044238329 | D86: =POISSON(B86,C60,TRUE()) -> 0.00052225805
B87: 3 | C87: =POISSON(B87,C60,FALSE()) -> 0.0017695332 | D87: =POISSON(B87,C60,TRUE()) -> 0.0022917912
B88: 4 | C88: =POISSON(B88,C60,FALSE()) -> 0.0053085995 | D88: =POISSON(B88,C60,TRUE()) -> 0.0076003907
B89: 5 | C89: =POISSON(B89,C60,FALSE()) -> 0.012740639 | D89: =POISSON(B89,C60,TRUE()) -> 0.020341029
B90: 6 | C90: =POISSON(B90,C60,FALSE()) -> 0.025481277 | D90: =POISSON(B90,C60,TRUE()) -> 0.045822307
B91: 7 | C91: =POISSON(B91,C60,FALSE()) -> 0.04368219 | D91: =POISSON(B91,C60,TRUE()) -> 0.089504497
B92: 8 | C92: =POISSON(B92,C60,FALSE()) -> 0.065523285 | D92: =POISSON(B92,C60,TRUE()) -> 0.15502778
B93: 9 | C93: =POISSON(B93,C60,FALSE()) -> 0.08736438 | D93: =POISSON(B93,C60,TRUE()) -> 0.24239216
B94: 10 | C94: =POISSON(B94,C60,FALSE()) -> 0.10483726 | D94: =POISSON(B94,C60,TRUE()) -> 0.34722942
B95: 11 | C95: =POISSON(B95,C60,FALSE()) -> 0.11436792 | D95: =POISSON(B95,C60,TRUE()) -> 0.46159733
B96: 12 | C96: =POISSON(B96,C60,FALSE()) -> 0.11436792 | D96: =POISSON(B96,C60,TRUE()) -> 0.57596525
B97: 13 | C97: =POISSON(B97,C60,FALSE()) -> 0.10557038 | D97: =POISSON(B97,C60,TRUE()) -> 0.68153563
B98: 14 | C98: =POISSON(B98,C60,FALSE()) -> 0.0904889 | D98: =POISSON(B98,C60,TRUE()) -> 0.77202453
B99: 15 | C99: =POISSON(B99,C60,FALSE()) -> 0.07239112 | D99: =POISSON(B99,C60,TRUE()) -> 0.84441565
B100: 16 | C100: =POISSON(B100,C60,FALSE()) -> 0.05429334 | D100: =POISSON(B100,C60,TRUE()) -> 0.89870899
B101: 17 | C101: =POISSON(B101,C60,FALSE()) -> 0.038324711 | D101: =POISSON(B101,C60,TRUE()) -> 0.9370337
B102: 18 | C102: =POISSON(B102,C60,FALSE()) -> 0.025549807 | D102: =POISSON(B102,C60,TRUE()) -> 0.96258351
B103: 19 | C103: =POISSON(B103,C60,FALSE()) -> 0.01613672 | D103: =POISSON(B103,C60,TRUE()) -> 0.97872023
B104: 20 | C104: =POISSON(B104,C60,FALSE()) -> 0.0096820322 | D104: =POISSON(B104,C60,TRUE()) -> 0.98840226
B105: 21 | C105: =POISSON(B105,C60,FALSE()) -> 0.0055325898 | D105: =POISSON(B105,C60,TRUE()) -> 0.99393485
B106: 22 | C106: =POISSON(B106,C60,FALSE()) -> 0.0030177763 | D106: =POISSON(B106,C60,TRUE()) -> 0.99695263
B107: 23 | C107: =POISSON(B107,C60,FALSE()) -> 0.001574492 | D107: =POISSON(B107,C60,TRUE()) -> 0.99852712
B108: 24 | C108: =POISSON(B108,C60,FALSE()) -> 0.00078724598 | D108: =POISSON(B108,C60,TRUE()) -> 0.99931437
B109: 25 | C109: =POISSON(B109,C60,FALSE()) -> 0.00037787807 | D109: =POISSON(B109,C60,TRUE()) -> 0.99969224
B111: BLOCK 7 — DECISION RULE AND INTERPRETATION
B112: VERDICT | C112: =IF(C80<C75,"RATES DIFFER SIGNIFICANTLY - shift A and shift B are not stopping at the same rate. Stratify further on H-09 before assuming it is the people.","NO EVIDENCE OF A DIFFERENCE - the gap between the two shift rates is within Poisson noise") -> RATES DIFFER SIGNIFICANTLY - shift A and shift B are not stopping at the same rate. Stratify further on H-09 before assuming it is the people.
B114: Criterion | C114: Numeric rule | D114: What it means in practice
B115: Two-rate p-value | C115: p < 0.05 | D115: The two rates differ by more than chance
B116: P(X >= observed) | C116: Below 0.01 | D116: The single high count is genuinely unusual, not routine variation
B117: Variance divided by mean | C117: Close to 1 | D117: Poisson holds; far above 1 means clustering
B118: c chart limits | C118: lambda +/- 3*SQRT(lambda) | D118: The control limits E-53 will use for this count
B120: COMMON MISTAKES
B121: • Comparing raw counts from unequal exposures. Ninety-six stops in eight shifts is not worse than seventy in five; convert to rates first.
...

Sheet E-12 Weibull Expon Lognorm
A1: Made by Jose Zapatero, jmazsantos@gmail.com
B2: E-12 — Weibull, Exponential and Lognormal | K2: MEASURE
B3: ← Back to Index | D3: Phase: MEASURE | Data required: Times to event | Min. sample: 15 | Complexity: 4/5 | Typical output: Fitted shape and scale, reliability estimate
B5: BLOCK 1 — QUICK CARD
B6: What question does this answer? | C6: How do I model time to failure, or any strongly skewed positive quantity?
B7: When you would reach for it | C7: Reliability work, maintenance planning, and any data bounded below by zero.
B8: What it gives you | C8: Reliability at a given time, MTTF, B10 life, and fitted Weibull parameters.
B10: BLOCK 2 — CONCEPT
B11: Three distributions cover almost all positive, right-skewed data on a packaging line.
B12: The exponential distribution describes events with a constant failure rate: no wear-out, no infant mortality.
B13: Its defining property is memorylessness - a component that has run 500 hours is as likely to fail in the next hour as a brand new one. That is true of electronic failures and of many random external causes, and false of almost every mechanical wear item.
B16: The Weibull distribution generalises it with a shape parameter beta. Beta below 1 means infant mortality, failures concentrated early, typically bad installation or commissioning. Beta equal to 1 is the exponential.
B18: Beta above 1 means wear-out, which is what a seal, a bearing or a filling valve actually does. Reading beta off your failure data therefore tells you whether preventive replacement will help at all: with beta at or below 1 it will not, because a new part is no better than the old one.
B21: The lognormal distribution applies when the logarithm of the quantity is normal. It fits repair times well, because most repairs are quick and a few are very long.
B24: BLOCK 3 — WHEN TO USE / WHEN NOT TO USE / ASSUMPTIONS
B25: WHEN TO USE IT | E25: WHEN NOT TO USE IT
B26: ✓ Deciding whether preventive replacement of a component makes sense. | E26: ✗ Not for data that can be negative or that is symmetric.
B27: ✓ Estimating B10 life for a spare parts and maintenance interval decision. | E27: ✗ Do not fit a Weibull to fewer than about 10 failures: the shape estimate will be worthless.
B28: ✓ Modelling repair times, which are almost always lognormal. | E28: ✗ Do not mix failure modes: a Weibull fitted across two mechanisms describes neither.
B29: ✓ Any strongly skewed positive data where the normal model fails.
B31: Assumption | C31: How to check it | D31: What to do if it fails | E31: Go to
B32: Failures come from a single failure mode | C32: Look for a bend in the probability plot, and check the correlation | D32: Split the data by mode and fit each separately | E32: H-09 Stratification
B33: Times are complete, not censored | C33: Check whether components still running have been excluded | D33: Excluding survivors biases the estimate optimistically; use censored methods
B34: Enough failures to estimate the shape | C34: At least 10, ideally 20 or more | D34: Report the exponential as a conservative fallback | E34: E-13 Identifying the Distribution of Your Data
B36: BLOCK 4 — FORMULA AND DERIVATION
B37: Weibull, two parameter (beta = shape, eta = scale or characteristic life):
B38: F(t) = 1 - EXP( -(t/eta)^beta ) R(t) = EXP( -(t/eta)^beta ) MTTF = eta * GAMMA(1 + 1/beta)
B40: B10 = eta * ( -LN(0.9) )^(1/beta)
B41: Exponential (the special case beta = 1):
B42: R(t) = EXP( -t / MTBF ) failure rate is constant at 1/MTBF
B43: Lognormal:
B44: X is lognormal if LN(X) is normal with mean mu and standard deviation sigma
B45: Median rank regression, the graphical fit used below:
B46: median rank MR(i) = (i - 0.3) / (n + 0.4) for the i-th ordered failure plot y = LN(-LN(1 - MR)) against x = LN(t)
B48: beta = slope of that line eta = EXP( -intercept / beta )
B50: BLOCK 5 — EXCEL IMPLEMENTATION
B51: Function used | C51: Syntax | D51: What the arguments mean
B52: WEIBULL | C52: WEIBULL(x, alpha, beta, cumulative) | D52: Excel calls the shape alpha and the scale beta; TRUE returns F(t)
B53: EXPONDIST | C53: EXPONDIST(x, lambda, cumulative) | D53: lambda is the rate, equal to 1 divided by the MTBF
B54: LOGNORMDIST | C54: LOGNORMDIST(x, mean, standard_dev) | D54: mean and standard_dev are those of LN(x)
B55: GAMMALN | C55: EXP(GAMMALN(1+1/beta)) | D55: Computes the gamma function needed for the Weibull MTTF
B56: RANK | C56: RANK(value, range, 1) | D56: Orders the failure times so the data need not be sorted
B57: SLOPE / INTERCEPT | C57: SLOPE(known_y, known_x) | D57: Fits the median rank regression line
B58: CORREL | C58: CORREL(range1, range2) | D58: Goodness of fit of the probability plot
B59: Legacy function names are used throughout (STDEV, TDIST, NORMSDIST). They are accepted by every Excel version and by LibreOffice, and they avoid the unresolved-function name-resolution errors produced by the newer dotted names on some engines.
B61: BLOCK 6 — WORKED EXAMPLE (INTERACTIVE)
B62: Fifteen recorded failure times, in operating hours, of the filling valve seals on the Innofil.
B63: Enter the times in any order; the sheet ranks them, fits a Weibull and tells you whether preventive replacement is justified.
B65: YELLOW = overwrite with your data | C65: GREEN = calculated automatically
B67: Weibull shape beta (for the calculator) | C67: 1.8
B68: Weibull scale eta (hours) | C68: 420
B69: Time of interest t (hours) | C69: 200
B70: Exponential MTBF (hours) | C70: 380
B71: Lognormal: mean of LN(x) | C71: 1.2
B72: Lognormal: StDev of LN(x) | C72: 0.65
B74: Weibull F(t) probability of failure by t | C74: =WEIBULL(C69,C67,C68,TRUE()) -> 0.23128116
B75: Weibull R(t) reliability at t | C75: =1-WEIBULL(C69,C67,C68,TRUE()) -> 0.76871884
B76: Weibull MTTF (hours) | C76: =C68*EXP(GAMMALN(1+1/C67)) -> 373.50043
B77: Weibull B10 life (hours) | C77: =C68*(-LN(0.9))^(1/C67) -> 120.30746
B78: Exponential R(t) | C78: =1-EXPONDIST(C69,1/C70,TRUE()) -> 0.59077751
B79: Lognormal F(t) | C79: =LOGNORMDIST(C69,C71,C72) -> 1
B81: MEDIAN RANK REGRESSION - FIT WEIBULL TO YOUR OWN FAILURE TIMES
B82: Failure time t (h) | C82: Median rank | D82: x = LN(t) | E82: y = LN(-LN(1-MR))
B83: 86 | C83: =(RANK(B83,$B$83:$B$97,1)-0.3)/(15+0.4) -> 0.045454545 | D83: =LN(B83) -> 4.4543473 | E83: =LN(-LN(1-C83)) -> -3.0678726
B84: 132 | C84: =(RANK(B84,$B$83:$B$97,1)-0.3)/(15+0.4) -> 0.11038961 | D84: =LN(B84) -> 4.8828019 | E84: =LN(-LN(1-C84)) -> -2.1458235
B85: 171 | C85: =(RANK(B85,$B$83:$B$97,1)-0.3)/(15+0.4) -> 0.17532468 | D85: =LN(B85) -> 5.1416636 | E85: =LN(-LN(1-C85)) -> -1.6462808
B86: 204 | C86: =(RANK(B86,$B$83:$B$97,1)-0.3)/(15+0.4) -> 0.24025974 | D86: =LN(B86) -> 5.31812 | E86: =LN(-LN(1-C86)) -> -1.2917894
B87: 238 | C87: =(RANK(B87,$B$83:$B$97,1)-0.3)/(15+0.4) -> 0.30519481 | D87: =LN(B87) -> 5.4722707 | E87: =LN(-LN(1-C87)) -> -1.0102614
B88: 271 | C88: =(RANK(B88,$B$83:$B$97,1)-0.3)/(15+0.4) -> 0.37012987 | D88: =LN(B88) -> 5.6021188 | E88: =LN(-LN(1-C88)) -> -0.77166753
B89: 305 | C89: =(RANK(B89,$B$83:$B$97,1)-0.3)/(15+0.4) -> 0.43506494 | D89: =LN(B89) -> 5.7203118 | E89: =LN(-LN(1-C89)) -> -0.56028817
B90: 342 | C90: =(RANK(B90,$B$83:$B$97,1)-0.3)/(15+0.4) -> 0.5 | D90: =LN(B90) -> 5.8348107 | E90: =LN(-LN(1-C90)) -> -0.36651292
B91: 381 | C91: =(RANK(B91,$B$83:$B$97,1)-0.3)/(15+0.4) -> 0.56493506 | D91: =LN(B91) -> 5.9427994 | E91: =LN(-LN(1-C91)) -> -0.18361041
B92: 425 | C92: =(RANK(B92,$B$83:$B$97,1)-0.3)/(15+0.4) -> 0.62987013 | D92: =LN(B92) -> 6.0520892 | E92: =LN(-LN(1-C92)) -> -0.0061173382
B93: 470 | C93: =(RANK(B93,$B$83:$B$97,1)-0.3)/(15+0.4) -> 0.69480519 | D93: =LN(B93) -> 6.1527327 | E93: =LN(-LN(1-C93)) -> 0.17126482
B94: 522 | C94: =(RANK(B94,$B$83:$B$97,1)-0.3)/(15+0.4) -> 0.75974026 | D94: =LN(B94) -> 6.2576676 | E94: =LN(-LN(1-C94)) -> 0.35489765
... B97: 812 | C97: =(RANK(B97,$B$83:$B$97,1)-0.3)/(15+0.4) -> 0.95454545 | D97: =LN(B97) -> 6.6995003 | E97: =LN(-LN(1-C97)) -> 1.1285084
B99: Fitted shape beta | C99: =SLOPE($E$83:$E$97,$D$83:$D$97) -> 1.831864
B100: Fitted scale eta (hours) | C100: =EXP(-INTERCEPT($E$83:$E$97,$D$83:$D$97)/C99) -> 425.85935
B101: Correlation of the probability plot | C101: =CORREL($D$83:$D$97,$E$83:$E$97) -> 0.99892904
B102: Fitted MTTF (hours) | C102: =C100*EXP(GAMMALN(1+1/C99)) -> 378.40792
B103: Fitted B10 life (hours) | C103: =C100*(-LN(0.9))^(1/C99) -> 124.66766
B105: BLOCK 7 — DECISION RULE AND INTERPRETATION
B106: VERDICT | C106: =IF(C101<0.95,"POOR FIT - the probability plot is not straight. Suspect two mixed failure modes; stratify on H-09.",IF(C99<0.9,"INFANT MORTALITY (beta < 1) - failures fall with age. Preventive replacement will make things WORSE. Attack installation, commissioning and burn-in.",IF(C99<1.2,"RANDOM FAILURE (beta near 1) - constant failure rate. Preventive replacement is pointless; improve detection and spares availability instead.","WEAR-OUT (beta > 1) - failure rate rises with age. Preventive replacement before the B10 life is justified."))) -> WEAR-OUT (beta > 1) - failure rate rises with age. Preventive replacement before the B10 life is justified.
B108: Criterion | C108: Numeric rule | D108: What it means in practice
B109: Beta below 1 | C109: Infant mortality | D109: Replacing early parts makes reliability worse, not better
B110: Beta about 1 | C110: Random, constant rate | D110: Time-based replacement adds cost and no reliability
B111: Beta above 1 | C111: Wear-out | D111: Time-based preventive replacement is justified; use B10 as the interval
B112: Plot correlation | C112: r >= 0.95 | D112: Below this, the single-Weibull model is doubtful
B114: COMMON MISTAKES
B115: • Fitting a Weibull to fewer than ten failures and quoting beta to three decimals.
B116: • Mixing failure modes. Seal wear and installation damage produce a bent plot and a meaningless beta.
B117: • Excluding components that have not yet failed. Those are censored observations and ignoring them makes the fleet look worse than it is.
B118: • Setting a preventive replacement interval when beta is 1. You are paying for parts and downtime and buying nothing.
B119: • Confusing MTTF with the median life. For a right-skewed distribution the mean sits well above the median.
B121: BLOCK 8 — SELF-CHECK
B122: Answer in your head, then select the cell in column N on the same row to reveal the answer (the text is white, not hidden). | N122: ANSWERS → select the cell to read the white text
B123: Q1. Your failure data returns a Weibull beta of 0.8. Should you introduce a preventive replacement plan? | N123: A1. No. Beta below 1 means the failure rate falls with age, so a new component is more likely to fail than the one running now. Replacing on a schedule would inject fresh infant mortality. Investigate installation, commissioning and the quality of the spare instead.
B124: Q2. What does memorylessness mean, and why does it disqualify time-based maintenance? | N124: A2. For the exponential distribution the probability of failing in the next hour is the same regardless of how long the item has already run. Replacement therefore resets nothing: the new part carries exactly the same hazard as the old one, so a time-based interval buys no reliability.
B125: Q3. Why is the lognormal distribution the natural model for repair times? | N125: A3. Repair time is the product of many multiplicative factors: diagnosis, spare availability, access, skill. Products of positive random effects tend to lognormal, which produces the familiar shape of many quick repairs and a long tail of rare very slow ones.
B127: BLOCK 9 — RELATED SHEETS
...

Sheet E-13 Distribution ID
A1: Made by Jose Zapatero, jmazsantos@gmail.com
B2: E-13 — Identifying the Distribution of Your Data | K2: MEASURE
B3: ← Back to Index | D3: Phase: MEASURE | Data required: Continuous measurements | Min. sample: 25 | Complexity: 4/5 | Typical output: Ranked candidate distributions
B5: BLOCK 1 — QUICK CARD
B6: What question does this answer? | C6: Which distribution actually fits my data?
B7: When you would reach for it | C7: Before a capability study on data that is clearly not symmetric.
B8: What it gives you | C8: A ranked comparison of the normal, lognormal and Weibull fits.
B10: BLOCK 2 — CONCEPT
B11: Identifying the distribution matters for one reason above all others: capability indices convert a distance into a defect rate through the shape of the tail. Choose the wrong shape and the PPM estimate is wrong, often by an order of magnitude, even though the mean and standard deviation are perfectly correct.
B14: The method used here is the probability plot correlation coefficient, and it is the most intuitive of the formal approaches. Each candidate distribution defines a transformation that should straighten the data if that distribution is correct. Compute the correlation of the resulting plot and the highest one wins.
B17: It is deliberately a comparison, not a pass or fail test. With 30 observations no test can reliably reject a distribution, so the practical question is not whether the data IS lognormal but which model describes it best and whether the choice changes the decision you are about to make.
B20: Before reaching for a distribution, always ask whether the shape is caused by mixing two process streams.
B21: Two symmetric shifts running at different means look convincingly skewed when pooled.
B23: BLOCK 3 — WHEN TO USE / WHEN NOT TO USE / ASSUMPTIONS
B24: WHEN TO USE IT | E24: WHEN NOT TO USE IT
B25: ✓ Before a non-normal capability study on E-58. | E25: ✗ Do not use it to justify a distribution when the real cause is a mixture of streams.
B26: ✓ When a histogram is clearly skewed and you need to choose a model. | E26: ✗ Not reliable below about 25 observations.
B27: ✓ When a normality test on E-32 has failed and you want the next best option. | E27: ✗ It compares only three candidates; specialised software will test many more.
B28: ✓ For reliability and downtime data, which is almost never normal.
B30: Assumption | C30: How to check it | D30: What to do if it fails | E30: Go to
B31: The data comes from one stream | C31: Stratify by shift, cavity, SKU and machine before fitting | D31: Split the data; describe each stream with its own model | E31: H-09 Stratification
B32: All values are strictly positive | C32: Check the minimum; lognormal and Weibull need x > 0 | D32: Shift the data by a constant, and document the shift | E32: E-33 When Assumptions Fail: Transformations and Alternatives
B33: The process is stable | C33: Control chart the data first | D33: An unstable process has no single distribution to identify | E33: E-49 Individuals and Moving Range Chart
B35: BLOCK 4 — FORMULA AND DERIVATION
B36: Median rank of the i-th ordered value:
B37: MR(i) = (i - 0.3) / (n + 0.4)
B38: Each candidate distribution defines a plotting transformation:
B39: Normal x-axis = x y-axis = NORMSINV(MR) Lognormal x-axis = LN(x) y-axis = NORMSINV(MR) Weibull x-axis = LN(x) y-axis = LN(-LN(1 - MR))
B42: Decision rule:
B43: compute the correlation of each plot; the highest correlation is the best fitting model a correlation below about 0.95 means none of the three is adequate
B46: BLOCK 5 — EXCEL IMPLEMENTATION
B47: Function used | C47: Syntax | D47: What the arguments mean
B48: RANK | C48: RANK(value, range, 1) | D48: Ascending rank, so the data need not be sorted
B49: NORMSINV | C49: NORMSINV(probability) | D49: Normal score for the normal and lognormal plots
B50: LN | C50: LN(number) | D50: Natural logarithm, used by both the lognormal and Weibull transformations
B51: CORREL | C51: CORREL(range1, range2) | D51: Correlation of each probability plot
B52: MAX | C52: MAX(range) | D52: Picks the best of the three correlations
B53: INDEX / MATCH | C53: INDEX(names, MATCH(MAX(r), r, 0)) | D53: Returns the name of the winning distribution
B54: Legacy function names are used throughout (STDEV, TDIST, NORMSDIST). They are accepted by every Excel version and by LibreOffice, and they avoid the unresolved-function name-resolution errors produced by the newer dotted names on some engines.
B56: BLOCK 6 — WORKED EXAMPLE (INTERACTIVE)
B57: Thirty recorded downtime durations in minutes from the Robopac wrapper. Overwrite the yellow column with your own data; the three fits and the winner update immediately.
B59: YELLOW = overwrite with your data | C59: GREEN = calculated automatically
B61: Value x | C61: Median rank | D61: Normal score | E61: LN(x) | F61: Weibull y
B62: 2.1 | C62: =(RANK(B62,$B$62:$B$91,1)-0.3)/(30+0.4) -> 0.15460526 | D62: =NORMSINV(C62) -> -1.01688 | E62: =LN(B62) -> 0.74193734 | F62: =LN(-LN(1-C62)) -> -1.7840793
B63: 3.4 | C63: =(RANK(B63,$B$62:$B$91,1)-0.3)/(30+0.4) -> 0.48355263 | D63: =NORMSINV(C63) -> -0.041239125 | E63: =LN(B63) -> 1.2237754 | F63: =LN(-LN(1-C63)) -> -0.41433145
B64: 1.8 | C64: =(RANK(B64,$B$62:$B$91,1)-0.3)/(30+0.4) -> 0.088815789 | D64: =NORMSINV(C64) -> -1.3480833 | E64: =LN(B64) -> 0.58778666 | F64: =LN(-LN(1-C64)) -> -2.3750462
B65: 5.2 | C65: =(RANK(B65,$B$62:$B$91,1)-0.3)/(30+0.4) -> 0.77960526 | D65: =NORMSINV(C65) -> 0.77086075 | E65: =LN(B65) -> 1.6486586 | F65: =LN(-LN(1-C65)) -> 0.41365487
B66: 2.9 | C66: =(RANK(B66,$B$62:$B$91,1)-0.3)/(30+0.4) -> 0.38486842 | D66: =NORMSINV(C66) -> -0.29271914 | E66: =LN(B66) -> 1.0647107 | F66: =LN(-LN(1-C66)) -> -0.72171316
B67: 4.1 | C67: =(RANK(B67,$B$62:$B$91,1)-0.3)/(30+0.4) -> 0.61513158 | D67: =NORMSINV(C67) -> 0.29271914 | E67: =LN(B67) -> 1.410987 | F67: =LN(-LN(1-C67)) -> -0.046197074
B68: 1.5 | C68: =(RANK(B68,$B$62:$B$91,1)-0.3)/(30+0.4) -> 0.023026316 | D68: =NORMSINV(C68) -> -1.9949106 | E68: =LN(B68) -> 0.40546511 | F68: =LN(-LN(1-C68)) -> -3.7594924
B69: 6.8 | C69: =(RANK(B69,$B$62:$B$91,1)-0.3)/(30+0.4) -> 0.87828947 | D69: =NORMSINV(C69) -> 1.1664785 | E69: =LN(B69) -> 1.9169226 | F69: =LN(-LN(1-C69)) -> 0.74484254
B70: 3.2 | C70: =(RANK(B70,$B$62:$B$91,1)-0.3)/(30+0.4) -> 0.45065789 | D70: =NORMSINV(C70) -> -0.12399935 | E70: =LN(B70) -> 1.1631508 | F70: =LN(-LN(1-C70)) -> -0.51243711
B71: 2.4 | C71: =(RANK(B71,$B$62:$B$91,1)-0.3)/(30+0.4) -> 0.25328947 | D71: =NORMSINV(C71) -> -0.66417401 | E71: =LN(B71) -> 0.87546874 | F71: =LN(-LN(1-C71)) -> -1.2307355
B72: 8.1 | C72: =(RANK(B72,$B$62:$B$91,1)-0.3)/(30+0.4) -> 0.94407895 | D72: =NORMSINV(C72) -> 1.5899676 | E72: =LN(B72) -> 2.0918641 | F72: =LN(-LN(1-C72)) -> 1.0591138
B73: 3.9 | C73: =(RANK(B73,$B$62:$B$91,1)-0.3)/(30+0.4) -> 0.58223684 | D73: =NORMSINV(C73) -> 0.20761919 | E73: =LN(B73) -> 1.3609766 | F73: =LN(-LN(1-C73)) -> -0.13600231
... B91: 6.2 | C91: =(RANK(B91,$B$62:$B$91,1)-0.3)/(30+0.4) -> 0.84539474 | D91: =NORMSINV(C91) -> 1.01688 | E91: =LN(B91) -> 1.8245493 | F91: =LN(-LN(1-C91)) -> 0.62426864
B93: GOODNESS OF FIT - PROBABILITY PLOT CORRELATION
B94: Candidate distribution | C94: Plot correlation | D94: Interpretation
B95: Normal | C95: =CORREL($B$62:$B$91,$D$62:$D$91) -> 0.95890624 | D95: Symmetric; the standard capability toolkit applies
B96: Lognormal | C96: =CORREL($E$62:$E$91,$D$62:$D$91) -> 0.99595226 | D96: Right skewed; typical of repair and downtime data
B97: Weibull | C97: =CORREL($E$62:$E$91,$F$62:$F$91) -> 0.96541081 | D97: Right skewed; typical of time to failure data
B99: Best fitting distribution | C99: =INDEX($B$95:$B$97,MATCH(MAX($C$95:$C$97),$C$95:$C$97,0)) -> Lognormal
B100: Its plot correlation | C100: =MAX($C$95:$C$97) -> 0.99595226
B101: Margin over the second best | C101: =MAX($C$95:$C$97)-LARGE($C$95:$C$97,2) -> 0.030541448
B102: Skewness of the raw data | C102: =SKEW($B$62:$B$91) -> 0.99447438
B104: BLOCK 7 — DECISION RULE AND INTERPRETATION
B105: VERDICT | C105: =IF(C100<0.95,"NO ADEQUATE FIT - none of the three models is straight enough. Check first whether two process streams are mixed (H-09) before looking for an exotic distribution.",IF(C101<0.01,"CLOSE CALL between the top two models. Either will serve; choose the one with the physical justification and record the choice.","CLEAR WINNER: "&C99&". Use it for capability on E-58, and state the model alongside every PPM you quote.")) -> CLEAR WINNER: Lognormal. Use it for capability on E-58, and state the model alongside every PPM you quote.
B107: Criterion | C107: Numeric rule | D107: What it means in practice
B108: Plot correlation | C108: r >= 0.99 | D108: Excellent fit; the model can be trusted in the tail
B109: Plot correlation | C109: 0.95 to 0.99 | D109: Adequate for capability work with the model stated
B110: Plot correlation | C110: Below 0.95 | D110: Inadequate; suspect a mixture or a special cause
B111: Margin over second best | C111: Below 0.01 | D111: The two models are indistinguishable at this sample size
B113: COMMON MISTAKES
B114: • Fitting an exotic distribution to data that is simply two shifts mixed together.
B115: • Reporting a capability index without stating the distribution used to compute it.
B116: • Identifying a distribution from an unstable process. Stability comes first, always.
B117: • Choosing the model with the highest correlation when a lower-scoring model has a physical justification, such as Weibull for time to failure.
B118: • Forgetting that the transformation must be reversed before the result is discussed with operators. Nobody on the floor thinks in log minutes.
B120: BLOCK 8 — SELF-CHECK
B121: Answer in your head, then select the cell in column N on the same row to reveal the answer (the text is white, not hidden). | N121: ANSWERS → select the cell to read the white text
B122: Q1. Why does the choice of distribution matter far more for capability than for the mean? | N122: A1. Because a capability index converts a distance from the specification into a defect rate through the tail of the assumed distribution. The centre of most distributions behaves similarly, but the tails differ enormously, so the predicted PPM can change by a factor of ten while the mean does not move.
B123: Q2. Your data has a probability plot correlation of 0.91 for all three candidates. What is the most likely explanation? | N123: A2. That the data is not one distribution at all. The usual cause on a packaging line is a mixture of streams - two shifts, two cavities or two SKUs - or a special cause event embedded in the data. Stratify on H-09 and control chart the series before hunting for a better distribution.
B124: Q3. Lognormal scores 0.987 and Weibull 0.984 on your downtime data. Which do you use? | N124: A3. The margin is negligible, so statistics will not decide it. Choose on physical grounds: repair and downtime durations are conventionally modelled as lognormal, time to failure as Weibull. Record the choice and the reason, and state it whenever the capability figure is quoted.
B126: BLOCK 9 — RELATED SHEETS
B127: Previous tool | C127: Next tool | D127: Alternative if assumptions fail
B128: E-12 Weibull, Exponential and Lognormal | C128: E-14 Standard Error vs Standard Deviation | D128: E-58 Non-Normal and Attribute Capability, Z-bench

Sheet E-14 Standard Error
A1: Made by Jose Zapatero, jmazsantos@gmail.com
B2: E-14 — Standard Error vs Standard Deviation | K2: MEASURE
B3: ← Back to Index | D3: Phase: MEASURE | Data required: StDev and n | Min. sample: 5 | Complexity: 2/5 | Typical output: Standard error and precision statement
B5: BLOCK 1 — QUICK CARD
B6: What question does this answer? | C6: How precise is my estimate of the mean, and how much would more sampling buy me?
B7: When you would reach for it | C7: When deciding how many units to measure, or defending a sample size to a manager.
B8: What it gives you | C8: The standard error, and the diminishing return curve of increasing n.
B10: BLOCK 2 — CONCEPT
B11: Two numbers are constantly confused, and confusing them produces wrong conclusions in both directions.
B12: The standard deviation describes the spread of individual bottles. It answers: how different is one bottle from another? It is a property of the process and it does not change when you sample more.
B14: The standard error describes the spread of sample MEANS. It answers: how precisely do I know the average?
B15: It is a property of your study, and it falls as the square root of the sample size.
B16: Use the standard deviation when talking about product: specification limits, capability, what the customer receives. Use the standard error when talking about knowledge: confidence intervals, hypothesis tests, whether an observed difference is real.
B19: The square root law has a hard commercial consequence. Halving the standard error requires quadrupling the sample. Going from 30 to 120 measurements halves your uncertainty; going from 120 to 210 barely helps.
B21: That is why sample size should be calculated from the effect you need to detect, not chosen by habit.
B23: BLOCK 3 — WHEN TO USE / WHEN NOT TO USE / ASSUMPTIONS
B24: WHEN TO USE IT | E24: WHEN NOT TO USE IT
B25: ✓ Justifying a sample size before collection starts. | E25: ✗ Never use the standard error to describe the product the customer receives.
B26: ✓ Explaining why a confidence interval is narrower than the process spread. | E26: ✗ Never compute capability from the standard error; capability uses the standard deviation.
B27: ✓ Deciding whether more data will actually change the decision. | E27: ✗ Not valid if the observations are not independent.
B28: ✓ Reviewing a study that concluded 'no difference' from a very small sample.
B30: Assumption | C30: How to check it | D30: What to do if it fails | E30: Go to
B31: Observations are independent | C31: Check the sampling scheme for repeated units from the same source | D31: Correlated data inflates the effective standard error; redesign the sampling | E31: E-05 Sampling Strategies and Rational Subgrouping
B32: The standard deviation estimate is reliable | C32: n of at least 25 to 30 for a usable estimate of s | D32: Widen the interval, or use the chi-square interval for sigma on E-16 | E32: E-16 Confidence Intervals for Proportion and Std Dev
B33: The process is stable during collection | C33: Control chart the data as it is collected | D33: A drifting process has no single mean to estimate | E33: E-49 Individuals and Moving Range Chart
B35: BLOCK 4 — FORMULA AND DERIVATION
B36: Standard deviation of individual values (a property of the process):
B37: s = SQRT( SUM((xi - xbar)^2) / (n - 1) )
B38: Standard error of the mean (a property of your study):
B39: SE = s / SQRT(n)
B40: Sample size needed to reach a target standard error:
B41: n = (s / SE_target)^2
B42: The square root law in one line:
B43: to halve the standard error, multiply the sample size by four
B45: BLOCK 5 — EXCEL IMPLEMENTATION
B46: Function used | C46: Syntax | D46: What the arguments mean
B47: STDEV | C47: STDEV(range) | D47: Sample standard deviation of individual values
B48: COUNT | C48: COUNT(range) | D48: Sample size n
B49: SQRT | C49: SQRT(n) | D49: The square root that governs the whole relationship
B50: ROUNDUP | C50: ROUNDUP(number, 0) | D50: Sample sizes are always rounded up, never down
